Workbook
Name V: _xludf.LAMBDA(loc, input_param, INDEX(in_loc!$D:$AD, MATCH(input_param, in_loc!$A:$A, 0), MATCH(loc, in_loc!$D$1:$AD$1, 0)))

Sheet summary
A1: =in_loc!A1 -> 0 | B1: =in_loc!D1 -> n_2 | C1: =in_loc!E1 -> n_25 | D1: =in_loc!F1 -> n_10 | E1: =in_loc!G1 -> b_2 | F1: =in_loc!H1 -> b_25 | G1: =in_loc!I1 -> b_10 | H1: =in_loc!J1 -> m_2 | I1: =in_loc!K1 -> m_25 | J1: =in_loc!L1 -> m_10 | K1: =B1&"_pes" -> n_2_pes | L1: =C1&"_pes" -> n_25_pes | M1: =D1&"_pes" -> n_10_pes | N1: =E1&"_pes" -> b_2_pes | O1: =F1&"_pes" -> b_25_pes | P1: =G1&"_pes" -> b_10_pes | Q1: =H1&"_pes" -> m_2_pes | R1: =I1&"_pes" -> m_25_pes | S1: =J1&"_pes" -> m_10_pes | T1: =B1&"_opt" -> n_2_opt | U1: =C1&"_opt" -> n_25_opt | V1: =D1&"_opt" -> n_10_opt | W1: =E1&"_opt" -> b_2_opt | X1: =F1&"_opt" -> b_25_opt | Y1: =G1&"_opt" -> b_10_opt | Z1: =H1&"_opt" -> m_2_opt | AA1: =I1&"_opt" -> m_25_opt | AB1: =J1&"_opt" -> m_10_opt
A2: CAPEX (€) | B2: =out_loc!D$23 -> 3895514.9 | C2: =out_loc!E$23 -> 18215574 | D2: =out_loc!F$23 -> 13368498 | E2: =out_loc!G$23 -> 2610396.9 | F2: =out_loc!H$23 -> 12850985 | G2: =out_loc!I$23 -> 9697751.9 | H2: =out_loc!J$23 -> 2561106.1 | I2: =out_loc!K$23 -> 12591531 | ... AB2: =out_loc!AD$23 -> 9001158.4
A3: OPEX (€) | B3: =out_loc!D$25+out_loc!D$29 -> 515087.46 | C3: =out_loc!E$25+out_loc!E$29 -> 2575437.3 | D3: =out_loc!F$25+out_loc!F$29 -> 1794221.3 | E3: =out_loc!G$25+out_loc!G$29 -> 412069.97 | F3: =out_loc!H$25+out_loc!H$29 -> 2060349.8 | G3: =out_loc!I$25+out_loc!I$29 -> 1435377.1 | H3: =out_loc!J$25+out_loc!J$29 -> 257543.73 | I3: =out_loc!K$25+out_loc!K$29 -> 1287718.7 | ... AB3: =out_loc!AD$25+out_loc!AD$29 -> 897198.23
A4: Revenue (€) | B4: =out_loc!D$30 -> 2866869.6 | C4: =out_loc!E$30 -> 14334348 | D4: =out_loc!F$30 -> 13115756 | E4: =out_loc!G$30 -> 3026445.1 | F4: =out_loc!H$30 -> 15132225 | G4: =out_loc!I$30 -> 13952094 | H4: =out_loc!J$30 -> 4317061.9 | I4: =out_loc!K$30 -> 21585310 | ... AB4: =out_loc!AD$30 -> 20793882
A5: LCOE (€) | B5: =out_loc!D26 -> 0.1846168 | C5: =out_loc!E26 -> 0.17405196 | D5: =out_loc!F26 -> 0.13872828 | E5: =out_loc!G26 -> 0.11984226 | F5: =out_loc!H26 -> 0.11824831 | G5: =out_loc!I26 -> 0.095754475 | H5: =out_loc!J26 -> 0.078349116 | I5: =out_loc!K26 -> 0.077159417 | ... AB5: =out_loc!AD26 -> 0.054837797
A6: NPV (€) | B6: =out_loc!D31 -> -1734179.8 | C6: =out_loc!E31 -> -7070346.4 | D6: =out_loc!F31 -> -2856592.4 | E6: =out_loc!G31 -> -138507.13 | F6: =out_loc!H31 -> -361234.42 | G6: =out_loc!I31 -> 2158881.8 | H6: =out_loc!J31 -> 1360693.1 | I6: =out_loc!K31 -> 7127787.8 | ... AB6: =out_loc!AD31 -> 10284081
A7: ROI (%) | B7: =out_loc!D32 -> -0.44517346 | C7: =out_loc!E32 -> -0.38814842 | D7: =out_loc!F32 -> -0.21368089 | E7: =out_loc!G32 -> -0.053059796 | F7: =out_loc!H32 -> -0.028109474 | G7: =out_loc!I32 -> 0.22261673 | H7: =out_loc!J32 -> 0.5312912 | I7: =out_loc!K32 -> 0.56607795 | ... AB7: =out_loc!AD32 -> 1.1425287
A8: Payback (y) | B8: =out_loc!D33 -> - | C8: =out_loc!E33 -> - | D8: =out_loc!F33 -> - | E8: =out_loc!G33 -> - | F8: =out_loc!H33 -> - | G8: =out_loc!I33 -> 16 | H8: =out_loc!J33 -> 11 | I8: =out_loc!K33 -> 11 | ... AB8: =out_loc!AD33 -> 7
A9: IRR (%) | B9: =out_loc!D34 -> -0.063591133 | C9: =out_loc!E34 -> -0.057564486 | D9: =out_loc!F34 -> -0.030717707 | E9: =out_loc!G34 -> -0.011461387 | F9: =out_loc!H34 -> -0.0095622736 | G9: =out_loc!I34 -> 0.022949343 | H9: =out_loc!J34 -> 0.056559485 | I9: =out_loc!K34 -> 0.059693657 | ... AB9: =out_loc!AD34 -> 0.12580191

Sheet in_loc
B1: Comment | C1: Dir | D1: n_2 | E1: n_25 | F1: n_10 | G1: b_2 | H1: b_25 | I1: b_10 | J1: m_2 | K1: m_25 | L1: m_10 | M1: =D1&"_pes" -> n_2_pes | N1: =E1&"_pes" -> n_25_pes | O1: =F1&"_pes" -> n_10_pes | P1: =G1&"_pes" -> b_2_pes | Q1: =H1&"_pes" -> b_25_pes | R1: =I1&"_pes" -> b_10_pes | S1: =J1&"_pes" -> m_2_pes | T1: =K1&"_pes" -> m_25_pes | U1: =L1&"_pes" -> m_10_pes | V1: =D1&"_opt" -> n_2_opt | W1: =E1&"_opt" -> n_25_opt | X1: =F1&"_opt" -> n_10_opt | Y1: =G1&"_opt" -> b_2_opt | Z1: =H1&"_opt" -> b_25_opt | AA1: =I1&"_opt" -> b_10_opt | AB1: =J1&"_opt" -> m_2_opt | AC1: =K1&"_opt" -> m_25_opt | AD1: =L1&"_opt" -> m_10_opt
A2: Cost (€)
A3: installation_pontoons_equipment_cost | C3: 1 | D3: 750000 | E3: 690000 | F3: 2050000 | G3: 307000 | H3: 295600 | I3: 625000 | J3: 277000 | K3: 265600 | L3: 535000 | M3: =D3*(1+in_gen!$C$44*$C3) -> 780000 | N3: =E3*(1+in_gen!$C$44*$C3) -> 717600 | O3: =F3*(1+in_gen!$C$44*$C3) -> 2132000 | P3: =G3*(1+in_gen!$C$44*$C3) -> 319280 | Q3: =H3*(1+in_gen!$C$44*$C3) -> 307424 | R3: =I3*(1+in_gen!$C$44*$C3) -> 650000 | S3: =J3*(1+in_gen!$C$44*$C3) -> 288080 | T3: =K3*(1+in_gen!$C$44*$C3) -> 276224 | U3: =L3*(1+in_gen!$C$44*$C3) -> 556400 | V3: =D3*(1+in_gen!$C$44*-$C3) -> 720000 | W3: =E3*(1+in_gen!$C$44*-$C3) -> 662400 | X3: =F3*(1+in_gen!$C$44*-$C3) -> 1968000 | Y3: =G3*(1+in_gen!$C$44*-$C3) -> 294720 | Z3: =H3*(1+in_gen!$C$44*-$C3) -> 283776 | AA3: =I3*(1+in_gen!$C$44*-$C3) -> 600000 | AB3: =J3*(1+in_gen!$C$44*-$C3) -> 265920 | AC3: =K3*(1+in_gen!$C$44*-$C3) -> 254976 | AD3: =L3*(1+in_gen!$C$44*-$C3) -> 513600
A4: installation_pontoons_fuel_cost | C4: 1 | D4: 321000 | E4: 299800 | F4: 861000 | G4: 38000 | H4: 36200 | I4: 82000 | J4: 21000 | K4: 20000 | L4: 42000 | M4: =D4*(1+in_gen!$C$44*$C4) -> 333840 | N4: =E4*(1+in_gen!$C$44*$C4) -> 311792 | O4: =F4*(1+in_gen!$C$44*$C4) -> 895440 | P4: =G4*(1+in_gen!$C$44*$C4) -> 39520 | Q4: =H4*(1+in_gen!$C$44*$C4) -> 37648 | R4: =I4*(1+in_gen!$C$44*$C4) -> 85280 | S4: =J4*(1+in_gen!$C$44*$C4) -> 21840 | T4: =K4*(1+in_gen!$C$44*$C4) -> 20800 | U4: =L4*(1+in_gen!$C$44*$C4) -> 43680 | V4: =D4*(1+in_gen!$C$44*-$C4) -> 308160 | W4: =E4*(1+in_gen!$C$44*-$C4) -> 287808 | X4: =F4*(1+in_gen!$C$44*-$C4) -> 826560 | Y4: =G4*(1+in_gen!$C$44*-$C4) -> 36480 | Z4: =H4*(1+in_gen!$C$44*-$C4) -> 34752 | AA4: =I4*(1+in_gen!$C$44*-$C4) -> 78720 | AB4: =J4*(1+in_gen!$C$44*-$C4) -> 20160 | AC4: =K4*(1+in_gen!$C$44*-$C4) -> 19200 | AD4: =L4*(1+in_gen!$C$44*-$C4) -> 40320
A5: installation_pontoons_personnel_cost | C5: 1 | D5: 65000 | E5: 72800 | F5: 234000 | G5: 95000 | H5: 91000 | I5: 260000 | J5: 82000 | K5: 78000 | L5: 221000 | M5: =D5*(1+in_gen!$C$44*$C5) -> 67600 | N5: =E5*(1+in_gen!$C$44*$C5) -> 75712 | O5: =F5*(1+in_gen!$C$44*$C5) -> 243360 | P5: =G5*(1+in_gen!$C$44*$C5) -> 98800 | Q5: =H5*(1+in_gen!$C$44*$C5) -> 94640 | R5: =I5*(1+in_gen!$C$44*$C5) -> 270400 | S5: =J5*(1+in_gen!$C$44*$C5) -> 85280 | T5: =K5*(1+in_gen!$C$44*$C5) -> 81120 | U5: =L5*(1+in_gen!$C$44*$C5) -> 229840 | V5: =D5*(1+in_gen!$C$44*-$C5) -> 62400 | W5: =E5*(1+in_gen!$C$44*-$C5) -> 69888 | X5: =F5*(1+in_gen!$C$44*-$C5) -> 224640 | Y5: =G5*(1+in_gen!$C$44*-$C5) -> 91200 | Z5: =H5*(1+in_gen!$C$44*-$C5) -> 87360 | AA5: =I5*(1+in_gen!$C$44*-$C5) -> 249600 | AB5: =J5*(1+in_gen!$C$44*-$C5) -> 78720 | AC5: =K5*(1+in_gen!$C$44*-$C5) -> 74880 | AD5: =L5*(1+in_gen!$C$44*-$C5) -> 212160
A6: installation_pv_system_equipment_cost | C6: 1 | D6: 560000 | E6: 400000 | F6: 1760000 | G6: 144000 | H6: 132600 | I6: 639000 | J6: 126000 | K6: 107800 | L6: 503000 | M6: =D6*(1+in_gen!$C$44*$C6) -> 582400 | N6: =E6*(1+in_gen!$C$44*$C6) -> 416000 | O6: =F6*(1+in_gen!$C$44*$C6) -> 1830400 | P6: =G6*(1+in_gen!$C$44*$C6) -> 149760 | Q6: =H6*(1+in_gen!$C$44*$C6) -> 137904 | R6: =I6*(1+in_gen!$C$44*$C6) -> 664560 | S6: =J6*(1+in_gen!$C$44*$C6) -> 131040 | T6: =K6*(1+in_gen!$C$44*$C6) -> 112112 | U6: =L6*(1+in_gen!$C$44*$C6) -> 523120 | V6: =D6*(1+in_gen!$C$44*-$C6) -> 537600 | W6: =E6*(1+in_gen!$C$44*-$C6) -> 384000 | X6: =F6*(1+in_gen!$C$44*-$C6) -> 1689600 | Y6: =G6*(1+in_gen!$C$44*-$C6) -> 138240 | Z6: =H6*(1+in_gen!$C$44*-$C6) -> 127296 | AA6: =I6*(1+in_gen!$C$44*-$C6) -> 613440 | AB6: =J6*(1+in_gen!$C$44*-$C6) -> 120960 | AC6: =K6*(1+in_gen!$C$44*-$C6) -> 103488 | AD6: =L6*(1+in_gen!$C$44*-$C6) -> 482880
A7: installation_pv_system_fuel_cost | C7: 1 | D7: 87000 | E7: 101800 | F7: 435000 | G7: 12000 | H7: 10600 | I7: 53000 | J7: 9000 | K7: 8000 | L7: 40000 | M7: =D7*(1+in_gen!$C$44*$C7) -> 90480 | N7: =E7*(1+in_gen!$C$44*$C7) -> 105872 | O7: =F7*(1+in_gen!$C$44*$C7) -> 452400 | P7: =G7*(1+in_gen!$C$44*$C7) -> 12480 | Q7: =H7*(1+in_gen!$C$44*$C7) -> 11024 | R7: =I7*(1+in_gen!$C$44*$C7) -> 55120 | S7: =J7*(1+in_gen!$C$44*$C7) -> 9360 | T7: =K7*(1+in_gen!$C$44*$C7) -> 8320 | U7: =L7*(1+in_gen!$C$44*$C7) -> 41600 | V7: =D7*(1+in_gen!$C$44*-$C7) -> 83520 | W7: =E7*(1+in_gen!$C$44*-$C7) -> 97728 | X7: =F7*(1+in_gen!$C$44*-$C7) -> 417600 | Y7: =G7*(1+in_gen!$C$44*-$C7) -> 11520 | Z7: =H7*(1+in_gen!$C$44*-$C7) -> 10176 | AA7: =I7*(1+in_gen!$C$44*-$C7) -> 50880 | AB7: =J7*(1+in_gen!$C$44*-$C7) -> 8640 | AC7: =K7*(1+in_gen!$C$44*-$C7) -> 7680 | AD7: =L7*(1+in_gen!$C$44*-$C7) -> 38400
A8: installation_pv_system_personnel_cost | C8: 1 | D8: 91000 | E8: 57200 | F8: 267000 | G8: 85000 | H8: 74800 | I8: 358000 | J8: 69000 | K8: 61800 | L8: 283000 | M8: =D8*(1+in_gen!$C$44*$C8) -> 94640 | N8: =E8*(1+in_gen!$C$44*$C8) -> 59488 | O8: =F8*(1+in_gen!$C$44*$C8) -> 277680 | P8: =G8*(1+in_gen!$C$44*$C8) -> 88400 | Q8: =H8*(1+in_gen!$C$44*$C8) -> 77792 | R8: =I8*(1+in_gen!$C$44*$C8) -> 372320 | S8: =J8*(1+in_gen!$C$44*$C8) -> 71760 | T8: =K8*(1+in_gen!$C$44*$C8) -> 64272 | U8: =L8*(1+in_gen!$C$44*$C8) -> 294320 | V8: =D8*(1+in_gen!$C$44*-$C8) -> 87360 | W8: =E8*(1+in_gen!$C$44*-$C8) -> 54912 | X8: =F8*(1+in_gen!$C$44*-$C8) -> 256320 | Y8: =G8*(1+in_gen!$C$44*-$C8) -> 81600 | Z8: =H8*(1+in_gen!$C$44*-$C8) -> 71808 | AA8: =I8*(1+in_gen!$C$44*-$C8) -> 343680 | AB8: =J8*(1+in_gen!$C$44*-$C8) -> 66240 | AC8: =K8*(1+in_gen!$C$44*-$C8) -> 59328 | AD8: =L8*(1+in_gen!$C$44*-$C8) -> 271680
A9: maintenance_pontoons_equipment_cost | C9: 1 | D9: 70000 | E9: 38000 | F9: 130000 | G9: 33000 | H9: 28200 | I9: 87000 | J9: 27000 | K9: 22200 | L9: 63000 | M9: =D9*(1+in_gen!$C$44*$C9) -> 72800 | N9: =E9*(1+in_gen!$C$44*$C9) -> 39520 | O9: =F9*(1+in_gen!$C$44*$C9) -> 135200 | P9: =G9*(1+in_gen!$C$44*$C9) -> 34320 | Q9: =H9*(1+in_gen!$C$44*$C9) -> 29328 | R9: =I9*(1+in_gen!$C$44*$C9) -> 90480 | S9: =J9*(1+in_gen!$C$44*$C9) -> 28080 | T9: =K9*(1+in_gen!$C$44*$C9) -> 23088 | U9: =L9*(1+in_gen!$C$44*$C9) -> 65520 | V9: =D9*(1+in_gen!$C$44*-$C9) -> 67200 | W9: =E9*(1+in_gen!$C$44*-$C9) -> 36480 | X9: =F9*(1+in_gen!$C$44*-$C9) -> 124800 | Y9: =G9*(1+in_gen!$C$44*-$C9) -> 31680 | Z9: =H9*(1+in_gen!$C$44*-$C9) -> 27072 | AA9: =I9*(1+in_gen!$C$44*-$C9) -> 83520 | AB9: =J9*(1+in_gen!$C$44*-$C9) -> 25920 | AC9: =K9*(1+in_gen!$C$44*-$C9) -> 21312 | AD9: =L9*(1+in_gen!$C$44*-$C9) -> 60480
A10: maintenance_pontoons_fuel_cost | C10: 1 | D10: 14000 | E10: 6800 | F10: 24000 | G10: 5000 | H10: 4000 | I10: 12000 | J10: 2000 | K10: 1200 | L10: 4000 | M10: =D10*(1+in_gen!$C$44*$C10) -> 14560 | N10: =E10*(1+in_gen!$C$44*$C10) -> 7072 | O10: =F10*(1+in_gen!$C$44*$C10) -> 24960 | P10: =G10*(1+in_gen!$C$44*$C10) -> 5200 | Q10: =H10*(1+in_gen!$C$44*$C10) -> 4160 | R10: =I10*(1+in_gen!$C$44*$C10) -> 12480 | S10: =J10*(1+in_gen!$C$44*$C10) -> 2080 | T10: =K10*(1+in_gen!$C$44*$C10) -> 1248 | U10: =L10*(1+in_gen!$C$44*$C10) -> 4160 | V10: =D10*(1+in_gen!$C$44*-$C10) -> 13440 | W10: =E10*(1+in_gen!$C$44*-$C10) -> 6528 | X10: =F10*(1+in_gen!$C$44*-$C10) -> 23040 | Y10: =G10*(1+in_gen!$C$44*-$C10) -> 4800 | Z10: =H10*(1+in_gen!$C$44*-$C10) -> 3840 | AA10: =I10*(1+in_gen!$C$44*-$C10) -> 11520 | AB10: =J10*(1+in_gen!$C$44*-$C10) -> 1920 | AC10: =K10*(1+in_gen!$C$44*-$C10) -> 1152 | AD10: =L10*(1+in_gen!$C$44*-$C10) -> 3840
A11: maintenance_pontoons_personnel_cost | C11: 1 | D11: 23000 | E11: 12400 | F11: 43000 | G11: 20000 | H11: 15600 | I11: 49000 | J11: 17000 | K11: 12400 | L11: 36000 | M11: =D11*(1+in_gen!$C$44*$C11) -> 23920 | N11: =E11*(1+in_gen!$C$44*$C11) -> 12896 | O11: =F11*(1+in_gen!$C$44*$C11) -> 44720 | P11: =G11*(1+in_gen!$C$44*$C11) -> 20800 | Q11: =H11*(1+in_gen!$C$44*$C11) -> 16224 | R11: =I11*(1+in_gen!$C$44*$C11) -> 50960 | S11: =J11*(1+in_gen!$C$44*$C11) -> 17680 | T11: =K11*(1+in_gen!$C$44*$C11) -> 12896 | U11: =L11*(1+in_gen!$C$44*$C11) -> 37440 | V11: =D11*(1+in_gen!$C$44*-$C11) -> 22080 | W11: =E11*(1+in_gen!$C$44*-$C11) -> 11904 | X11: =F11*(1+in_gen!$C$44*-$C11) -> 41280 | Y11: =G11*(1+in_gen!$C$44*-$C11) -> 19200 | Z11: =H11*(1+in_gen!$C$44*-$C11) -> 14976 | AA11: =I11*(1+in_gen!$C$44*-$C11) -> 47040 | AB11: =J11*(1+in_gen!$C$44*-$C11) -> 16320 | AC11: =K11*(1+in_gen!$C$44*-$C11) -> 11904 | AD11: =L11*(1+in_gen!$C$44*-$C11) -> 34560
A12: replacement_of_pv_system_equipment_cost | C12: 1 | D12: 600000 | E12: 408000 | F12: 2040000 | G12: 167000 | H12: 145200 | I12: 769000 | J12: 149000 | K12: 130800 | L12: 679000 | M12: =D12*(1+in_gen!$C$44*$C12) -> 624000 | N12: =E12*(1+in_gen!$C$44*$C12) -> 424320 | O12: =F12*(1+in_gen!$C$44*$C12) -> 2121600 | P12: =G12*(1+in_gen!$C$44*$C12) -> 173680 | Q12: =H12*(1+in_gen!$C$44*$C12) -> 151008 | R12: =I12*(1+in_gen!$C$44*$C12) -> 799760 | S12: =J12*(1+in_gen!$C$44*$C12) -> 154960 | T12: =K12*(1+in_gen!$C$44*$C12) -> 136032 | U12: =L12*(1+in_gen!$C$44*$C12) -> 706160 | V12: =D12*(1+in_gen!$C$44*-$C12) -> 576000 | W12: =E12*(1+in_gen!$C$44*-$C12) -> 391680 | X12: =F12*(1+in_gen!$C$44*-$C12) -> 1958400 | Y12: =G12*(1+in_gen!$C$44*-$C12) -> 160320 | Z12: =H12*(1+in_gen!$C$44*-$C12) -> 139392 | AA12: =I12*(1+in_gen!$C$44*-$C12) -> 738240 | AB12: =J12*(1+in_gen!$C$44*-$C12) -> 143040 | AC12: =K12*(1+in_gen!$C$44*-$C12) -> 125568 | AD12: =L12*(1+in_gen!$C$44*-$C12) -> 651840
A13: replacement_of_pv_system_fuel_cost | C13: 1 | D13: 90000 | E13: 103000 | F13: 503000 | G13: 17000 | H13: 15600 | I13: 80000 | J13: 13000 | K13: 12000 | L13: 61000 | M13: =D13*(1+in_gen!$C$44*$C13) -> 93600 | N13: =E13*(1+in_gen!$C$44*$C13) -> 107120 | O13: =F13*(1+in_gen!$C$44*$C13) -> 523120 | P13: =G13*(1+in_gen!$C$44*$C13) -> 17680 | Q13: =H13*(1+in_gen!$C$44*$C13) -> 16224 | R13: =I13*(1+in_gen!$C$44*$C13) -> 83200 | S13: =J13*(1+in_gen!$C$44*$C13) -> 13520 | T13: =K13*(1+in_gen!$C$44*$C13) -> 12480 | U13: =L13*(1+in_gen!$C$44*$C13) -> 63440 | V13: =D13*(1+in_gen!$C$44*-$C13) -> 86400 | W13: =E13*(1+in_gen!$C$44*-$C13) -> 98880 | X13: =F13*(1+in_gen!$C$44*-$C13) -> 482880 | Y13: =G13*(1+in_gen!$C$44*-$C13) -> 16320 | Z13: =H13*(1+in_gen!$C$44*-$C13) -> 14976 | AA13: =I13*(1+in_gen!$C$44*-$C13) -> 76800 | AB13: =J13*(1+in_gen!$C$44*-$C13) -> 12480 | AC13: =K13*(1+in_gen!$C$44*-$C13) -> 11520 | AD13: =L13*(1+in_gen!$C$44*-$C13) -> 58560
A14: replacement_of_pv_system_personnel_cost | C14: 1 | D14: 111000 | E14: 84600 | F14: 423000 | G14: 134000 | H14: 117000 | I14: 611000 | J14: 108000 | K14: 96200 | L14: 481000 | M14: =D14*(1+in_gen!$C$44*$C14) -> 115440 | N14: =E14*(1+in_gen!$C$44*$C14) -> 87984 | O14: =F14*(1+in_gen!$C$44*$C14) -> 439920 | P14: =G14*(1+in_gen!$C$44*$C14) -> 139360 | Q14: =H14*(1+in_gen!$C$44*$C14) -> 121680 | R14: =I14*(1+in_gen!$C$44*$C14) -> 635440 | S14: =J14*(1+in_gen!$C$44*$C14) -> 112320 | T14: =K14*(1+in_gen!$C$44*$C14) -> 100048 | U14: =L14*(1+in_gen!$C$44*$C14) -> 500240 | V14: =D14*(1+in_gen!$C$44*-$C14) -> 106560 | W14: =E14*(1+in_gen!$C$44*-$C14) -> 81216 | X14: =F14*(1+in_gen!$C$44*-$C14) -> 406080 | Y14: =G14*(1+in_gen!$C$44*-$C14) -> 128640 | Z14: =H14*(1+in_gen!$C$44*-$C14) -> 112320 | AA14: =I14*(1+in_gen!$C$44*-$C14) -> 586560 | AB14: =J14*(1+in_gen!$C$44*-$C14) -> 103680 | AC14: =K14*(1+in_gen!$C$44*-$C14) -> 92352 | AD14: =L14*(1+in_gen!$C$44*-$C14) -> 461760
A15: inverters_transformers_cost | C15: 1 | D15: 36000 | E15: 36000 | F15: 300000 | G15: 27000 | H15: 27000 | I15: 220000 | J15: 27000 | K15: 27000 | L15: 240000 | M15: =D15*(1+in_gen!$C$44*$C15) -> 37440 | N15: =E15*(1+in_gen!$C$44*$C15) -> 37440 | O15: =F15*(1+in_gen!$C$44*$C15) -> 312000 | P15: =G15*(1+in_gen!$C$44*$C15) -> 28080 | Q15: =H15*(1+in_gen!$C$44*$C15) -> 28080 | R15: =I15*(1+in_gen!$C$44*$C15) -> 228800 | S15: =J15*(1+in_gen!$C$44*$C15) -> 28080 | T15: =K15*(1+in_gen!$C$44*$C15) -> 28080 | U15: =L15*(1+in_gen!$C$44*$C15) -> 249600 | V15: =D15*(1+in_gen!$C$44*-$C15) -> 34560 | W15: =E15*(1+in_gen!$C$44*-$C15) -> 34560 | X15: =F15*(1+in_gen!$C$44*-$C15) -> 288000 | Y15: =G15*(1+in_gen!$C$44*-$C15) -> 25920 | Z15: =H15*(1+in_gen!$C$44*-$C15) -> 25920 | AA15: =I15*(1+in_gen!$C$44*-$C15) -> 211200 | AB15: =J15*(1+in_gen!$C$44*-$C15) -> 25920 | AC15: =K15*(1+in_gen!$C$44*-$C15) -> 25920 | AD15: =L15*(1+in_gen!$C$44*-$C15) -> 230400
A16: solar_maintenance_cost_per_kw_per_year | B16: Boat trips to site already included in pontoon maintenance. Larger size reduces cost. Waves increase cost. Robust panels decrease costs. Cooling reduces costs. Otherwise same as for land. | C16: 1 | D16: 20 | E16: 20 | F16: 15 | G16: 16 | H16: 16 | I16: 12 | J16: 10 | K16: 10 | L16: 7.5 | M16: =D16*(1+in_gen!$C$44*$C16) -> 20.8 | N16: =E16*(1+in_gen!$C$44*$C16) -> 20.8 | O16: =F16*(1+in_gen!$C$44*$C16) -> 15.6 | P16: =G16*(1+in_gen!$C$44*$C16) -> 16.64 | Q16: =H16*(1+in_gen!$C$44*$C16) -> 16.64 | R16: =I16*(1+in_gen!$C$44*$C16) -> 12.48 | S16: =J16*(1+in_gen!$C$44*$C16) -> 10.4 | T16: =K16*(1+in_gen!$C$44*$C16) -> 10.4 | U16: =L16*(1+in_gen!$C$44*$C16) -> 7.8 | V16: =D16*(1+in_gen!$C$44*-$C16) -> 19.2 | W16: =E16*(1+in_gen!$C$44*-$C16) -> 19.2 | X16: =F16*(1+in_gen!$C$44*-$C16) -> 14.4 | Y16: =G16*(1+in_gen!$C$44*-$C16) -> 15.36 | Z16: =H16*(1+in_gen!$C$44*-$C16) -> 15.36 | AA16: =I16*(1+in_gen!$C$44*-$C16) -> 11.52 | AB16: =J16*(1+in_gen!$C$44*-$C16) -> 9.6 | AC16: =K16*(1+in_gen!$C$44*-$C16) -> 9.6 | AD16: =L16*(1+in_gen!$C$44*-$C16) -> 7.2
A18: Count
A19: anchors_count | C19: 0 | D19: 16 | E19: 16 | F19: 38 | G19: 16 | H19: 16 | I19: 26 | J19: 16 | K19: 16 | L19: 26 | M19: =D19*(1+in_gen!$C$44*$C19) -> 16 | N19: =E19*(1+in_gen!$C$44*$C19) -> 16 | O19: =F19*(1+in_gen!$C$44*$C19) -> 38 | P19: =G19*(1+in_gen!$C$44*$C19) -> 16 | Q19: =H19*(1+in_gen!$C$44*$C19) -> 16 | R19: =I19*(1+in_gen!$C$44*$C19) -> 26 | S19: =J19*(1+in_gen!$C$44*$C19) -> 16 | T19: =K19*(1+in_gen!$C$44*$C19) -> 16 | U19: =L19*(1+in_gen!$C$44*$C19) -> 26 | V19: =D19*(1+in_gen!$C$44*-$C19) -> 16 | W19: =E19*(1+in_gen!$C$44*-$C19) -> 16 | X19: =F19*(1+in_gen!$C$44*-$C19) -> 38 | Y19: =G19*(1+in_gen!$C$44*-$C19) -> 16 | Z19: =H19*(1+in_gen!$C$44*-$C19) -> 16 | AA19: =I19*(1+in_gen!$C$44*-$C19) -> 26 | AB19: =J19*(1+in_gen!$C$44*-$C19) -> 16 | AC19: =K19*(1+in_gen!$C$44*-$C19) -> 16 | AD19: =L19*(1+in_gen!$C$44*-$C19) -> 26
A20: pontoons_count | C20: 0 | D20: 32 | E20: 32 | F20: 91 | G20: 32 | H20: 32 | I20: 91 | J20: 32 | K20: 32 | L20: 91 | M20: =D20*(1+in_gen!$C$44*$C20) -> 32 | N20: =E20*(1+in_gen!$C$44*$C20) -> 32 | O20: =F20*(1+in_gen!$C$44*$C20) -> 91 | P20: =G20*(1+in_gen!$C$44*$C20) -> 32 | Q20: =H20*(1+in_gen!$C$44*$C20) -> 32 | R20: =I20*(1+in_gen!$C$44*$C20) -> 91 | S20: =J20*(1+in_gen!$C$44*$C20) -> 32 | T20: =K20*(1+in_gen!$C$44*$C20) -> 32 | U20: =L20*(1+in_gen!$C$44*$C20) -> 91 | V20: =D20*(1+in_gen!$C$44*-$C20) -> 32 | W20: =E20*(1+in_gen!$C$44*-$C20) -> 32 | X20: =F20*(1+in_gen!$C$44*-$C20) -> 91 | Y20: =G20*(1+in_gen!$C$44*-$C20) -> 32 | Z20: =H20*(1+in_gen!$C$44*-$C20) -> 32 | AA20: =I20*(1+in_gen!$C$44*-$C20) -> 91 | AB20: =J20*(1+in_gen!$C$44*-$C20) -> 32 | AC20: =K20*(1+in_gen!$C$44*-$C20) -> 32 | AD20: =L20*(1+in_gen!$C$44*-$C20) -> 91
A21: matrices_per_quadrant | C21: 0 | D21: 17 | E21: 17 | F21: 17 | G21: 17 | H21: 17 | I21: 17 | J21: 17 | K21: 17 | L21: 17 | M21: =D21*(1+in_gen!$C$44*$C21) -> 17 | N21: =E21*(1+in_gen!$C$44*$C21) -> 17 | O21: =F21*(1+in_gen!$C$44*$C21) -> 17 | P21: =G21*(1+in_gen!$C$44*$C21) -> 17 | Q21: =H21*(1+in_gen!$C$44*$C21) -> 17 | R21: =I21*(1+in_gen!$C$44*$C21) -> 17 | S21: =J21*(1+in_gen!$C$44*$C21) -> 17 | T21: =K21*(1+in_gen!$C$44*$C21) -> 17 | U21: =L21*(1+in_gen!$C$44*$C21) -> 17 | V21: =D21*(1+in_gen!$C$44*-$C21) -> 17 | W21: =E21*(1+in_gen!$C$44*-$C21) -> 17 | X21: =F21*(1+in_gen!$C$44*-$C21) -> 17 | Y21: =G21*(1+in_gen!$C$44*-$C21) -> 17 | Z21: =H21*(1+in_gen!$C$44*-$C21) -> 17 | AA21: =I21*(1+in_gen!$C$44*-$C21) -> 17 | AB21: =J21*(1+in_gen!$C$44*-$C21) -> 17 | AC21: =K21*(1+in_gen!$C$44*-$C21) -> 17 | AD21: =L21*(1+in_gen!$C$44*-$C21) -> 17
A22: rings_count | C22: 0 | D22: 1 | E22: 5 | F22: 1 | G22: 1 | H22: 5 | I22: 1 | J22: 1 | K22: 5 | L22: 1 | M22: =D22*(1+in_gen!$C$44*$C22) -> 1 | N22: =E22*(1+in_gen!$C$44*$C22) -> 5 | O22: =F22*(1+in_gen!$C$44*$C22) -> 1 | P22: =G22*(1+in_gen!$C$44*$C22) -> 1 | Q22: =H22*(1+in_gen!$C$44*$C22) -> 5 | R22: =I22*(1+in_gen!$C$44*$C22) -> 1 | S22: =J22*(1+in_gen!$C$44*$C22) -> 1 | T22: =K22*(1+in_gen!$C$44*$C22) -> 5 | U22: =L22*(1+in_gen!$C$44*$C22) -> 1 | V22: =D22*(1+in_gen!$C$44*-$C22) -> 1 | W22: =E22*(1+in_gen!$C$44*-$C22) -> 5 | X22: =F22*(1+in_gen!$C$44*-$C22) -> 1 | Y22: =G22*(1+in_gen!$C$44*-$C22) -> 1 | Z22: =H22*(1+in_gen!$C$44*-$C22) -> 5 | AA22: =I22*(1+in_gen!$C$44*-$C22) -> 1 | AB22: =J22*(1+in_gen!$C$44*-$C22) -> 1 | AC22: =K22*(1+in_gen!$C$44*-$C22) -> 5 | AD22: =L22*(1+in_gen!$C$44*-$C22) -> 1
A24: Weight (t)
A25: anchor_weight | C25: 0 | D25: 46.7 | E25: 46.7 | F25: 58.41 | G25: 9.5 | H25: 9.5 | I25: 24.22 | J25: 26.38 | K25: 26.38 | L25: 58.41 | M25: =D25*(1+in_gen!$C$44*$C25) -> 46.7 | N25: =E25*(1+in_gen!$C$44*$C25) -> 46.7 | O25: =F25*(1+in_gen!$C$44*$C25) -> 58.41 | P25: =G25*(1+in_gen!$C$44*$C25) -> 9.5 | Q25: =H25*(1+in_gen!$C$44*$C25) -> 9.5 | R25: =I25*(1+in_gen!$C$44*$C25) -> 24.22 | S25: =J25*(1+in_gen!$C$44*$C25) -> 26.38 | T25: =K25*(1+in_gen!$C$44*$C25) -> 26.38 | U25: =L25*(1+in_gen!$C$44*$C25) -> 58.41 | V25: =D25*(1+in_gen!$C$44*-$C25) -> 46.7 | W25: =E25*(1+in_gen!$C$44*-$C25) -> 46.7 | X25: =F25*(1+in_gen!$C$44*-$C25) -> 58.41 | Y25: =G25*(1+in_gen!$C$44*-$C25) -> 9.5 | Z25: =H25*(1+in_gen!$C$44*-$C25) -> 9.5 | AA25: =I25*(1+in_gen!$C$44*-$C25) -> 24.22 | AB25: =J25*(1+in_gen!$C$44*-$C25) -> 26.38 | AC25: =K25*(1+in_gen!$C$44*-$C25) -> 26.38 | AD25: =L25*(1+in_gen!$C$44*-$C25) -> 58.41
A26: chain_weight | C26: 0 | D26: 18.27 | E26: 18.27 | F26: 31.92 | G26: 11.82 | H26: 11.82 | I26: 25.35 | J26: 12.72 | K26: 12.72 | L26: 30.61 | M26: =D26*(1+in_gen!$C$44*$C26) -> 18.27 | N26: =E26*(1+in_gen!$C$44*$C26) -> 18.27 | O26: =F26*(1+in_gen!$C$44*$C26) -> 31.92 | P26: =G26*(1+in_gen!$C$44*$C26) -> 11.82 | Q26: =H26*(1+in_gen!$C$44*$C26) -> 11.82 | R26: =I26*(1+in_gen!$C$44*$C26) -> 25.35 | S26: =J26*(1+in_gen!$C$44*$C26) -> 12.72 | T26: =K26*(1+in_gen!$C$44*$C26) -> 12.72 | U26: =L26*(1+in_gen!$C$44*$C26) -> 30.61 | V26: =D26*(1+in_gen!$C$44*-$C26) -> 18.27 | W26: =E26*(1+in_gen!$C$44*-$C26) -> 18.27 | X26: =F26*(1+in_gen!$C$44*-$C26) -> 31.92 | Y26: =G26*(1+in_gen!$C$44*-$C26) -> 11.82 | Z26: =H26*(1+in_gen!$C$44*-$C26) -> 11.82 | AA26: =I26*(1+in_gen!$C$44*-$C26) -> 25.35 | AB26: =J26*(1+in_gen!$C$44*-$C26) -> 12.72 | AC26: =K26*(1+in_gen!$C$44*-$C26) -> 12.72 | AD26: =L26*(1+in_gen!$C$44*-$C26) -> 30.61
A27: pvc_pipe_weight | C27: 0 | D27: 13.6 | E27: 68 | F27: 56.9 | G27: 13.6 | H27: 68 | I27: 56.9 | J27: 13.6 | K27: 68 | L27: 56.9 | M27: =D27*(1+in_gen!$C$44*$C27) -> 13.6 | N27: =E27*(1+in_gen!$C$44*$C27) -> 68 | O27: =F27*(1+in_gen!$C$44*$C27) -> 56.9 | P27: =G27*(1+in_gen!$C$44*$C27) -> 13.6 | Q27: =H27*(1+in_gen!$C$44*$C27) -> 68 | R27: =I27*(1+in_gen!$C$44*$C27) -> 56.9 | S27: =J27*(1+in_gen!$C$44*$C27) -> 13.6 | T27: =K27*(1+in_gen!$C$44*$C27) -> 68 | U27: =L27*(1+in_gen!$C$44*$C27) -> 56.9 | V27: =D27*(1+in_gen!$C$44*-$C27) -> 13.6 | W27: =E27*(1+in_gen!$C$44*-$C27) -> 68 | X27: =F27*(1+in_gen!$C$44*-$C27) -> 56.9 | Y27: =G27*(1+in_gen!$C$44*-$C27) -> 13.6 | Z27: =H27*(1+in_gen!$C$44*-$C27) -> 68 | AA27: =I27*(1+in_gen!$C$44*-$C27) -> 56.9 | AB27: =J27*(1+in_gen!$C$44*-$C27) -> 13.6 | AC27: =K27*(1+in_gen!$C$44*-$C27) -> 68 | AD27: =L27*(1+in_gen!$C$44*-$C27) -> 56.9
A28: polypropylene_rope_weight | C28: 0 | D28: 0.9 | E28: 4.5 | F28: 4.1 | G28: 0.9 | H28: 4.5 | I28: 4.1 | J28: 0.9 | K28: 4.5 | L28: 4.1 | M28: =D28*(1+in_gen!$C$44*$C28) -> 0.9 | N28: =E28*(1+in_gen!$C$44*$C28) -> 4.5 | O28: =F28*(1+in_gen!$C$44*$C28) -> 4.1 | P28: =G28*(1+in_gen!$C$44*$C28) -> 0.9 | Q28: =H28*(1+in_gen!$C$44*$C28) -> 4.5 | R28: =I28*(1+in_gen!$C$44*$C28) -> 4.1 | S28: =J28*(1+in_gen!$C$44*$C28) -> 0.9 | T28: =K28*(1+in_gen!$C$44*$C28) -> 4.5 | U28: =L28*(1+in_gen!$C$44*$C28) -> 4.1 | V28: =D28*(1+in_gen!$C$44*-$C28) -> 0.9 | W28: =E28*(1+in_gen!$C$44*-$C28) -> 4.5 | X28: =F28*(1+in_gen!$C$44*-$C28) -> 4.1 | Y28: =G28*(1+in_gen!$C$44*-$C28) -> 0.9 | Z28: =H28*(1+in_gen!$C$44*-$C28) -> 4.5 | AA28: =I28*(1+in_gen!$C$44*-$C28) -> 4.1 | AB28: =J28*(1+in_gen!$C$44*-$C28) -> 0.9 | AC28: =K28*(1+in_gen!$C$44*-$C28) -> 4.5 | AD28: =L28*(1+in_gen!$C$44*-$C28) -> 4.1
A30: Distance (m)
A31: solar_pipe_distance | C31: 0 | D31: 7.5 | E31: 7.5 | F31: 15 | G31: 7.5 | H31: 7.5 | I31: 15 | J31: 7.5 | K31: 7.5 | L31: 15 | M31: =D31*(1+in_gen!$C$44*$C31) -> 7.5 | N31: =E31*(1+in_gen!$C$44*$C31) -> 7.5 | O31: =F31*(1+in_gen!$C$44*$C31) -> 15 | P31: =G31*(1+in_gen!$C$44*$C31) -> 7.5 | Q31: =H31*(1+in_gen!$C$44*$C31) -> 7.5 | R31: =I31*(1+in_gen!$C$44*$C31) -> 15 | S31: =J31*(1+in_gen!$C$44*$C31) -> 7.5 | T31: =K31*(1+in_gen!$C$44*$C31) -> 7.5 | U31: =L31*(1+in_gen!$C$44*$C31) -> 15 | V31: =D31*(1+in_gen!$C$44*-$C31) -> 7.5 | W31: =E31*(1+in_gen!$C$44*-$C31) -> 7.5 | X31: =F31*(1+in_gen!$C$44*-$C31) -> 15 | Y31: =G31*(1+in_gen!$C$44*-$C31) -> 7.5 | Z31: =H31*(1+in_gen!$C$44*-$C31) -> 7.5 | AA31: =I31*(1+in_gen!$C$44*-$C31) -> 15 | AB31: =J31*(1+in_gen!$C$44*-$C31) -> 7.5 | AC31: =K31*(1+in_gen!$C$44*-$C31) -> 7.5 | AD31: =L31*(1+in_gen!$C$44*-$C31) -> 15
A32: pipe_wavebreaker_distance | C32: 0 | D32: 7.5 | E32: 7.5 | F32: 15 | G32: 7.5 | H32: 7.5 | I32: 15 | J32: 7.5 | K32: 7.5 | L32: 15 | M32: =D32*(1+in_gen!$C$44*$C32) -> 7.5 | N32: =E32*(1+in_gen!$C$44*$C32) -> 7.5 | O32: =F32*(1+in_gen!$C$44*$C32) -> 15 | P32: =G32*(1+in_gen!$C$44*$C32) -> 7.5 | Q32: =H32*(1+in_gen!$C$44*$C32) -> 7.5 | R32: =I32*(1+in_gen!$C$44*$C32) -> 15 | S32: =J32*(1+in_gen!$C$44*$C32) -> 7.5 | T32: =K32*(1+in_gen!$C$44*$C32) -> 7.5 | U32: =L32*(1+in_gen!$C$44*$C32) -> 15 | V32: =D32*(1+in_gen!$C$44*-$C32) -> 7.5 | W32: =E32*(1+in_gen!$C$44*-$C32) -> 7.5 | X32: =F32*(1+in_gen!$C$44*-$C32) -> 15 | Y32: =G32*(1+in_gen!$C$44*-$C32) -> 7.5 | Z32: =H32*(1+in_gen!$C$44*-$C32) -> 7.5 | AA32: =I32*(1+in_gen!$C$44*-$C32) -> 15 | AB32: =J32*(1+in_gen!$C$44*-$C32) -> 7.5 | AC32: =K32*(1+in_gen!$C$44*-$C32) -> 7.5 | AD32: =L32*(1+in_gen!$C$44*-$C32) -> 15
A33: matrix_side_length | C33: 0 | D33: 14 | E33: 14 | F33: 28 | G33: 14 | H33: 14 | I33: 28 | J33: 14 | K33: 14 | L33: 28 | M33: =D33*(1+in_gen!$C$44*$C33) -> 14 | N33: =E33*(1+in_gen!$C$44*$C33) -> 14 | O33: =F33*(1+in_gen!$C$44*$C33) -> 28 | P33: =G33*(1+in_gen!$C$44*$C33) -> 14 | Q33: =H33*(1+in_gen!$C$44*$C33) -> 14 | R33: =I33*(1+in_gen!$C$44*$C33) -> 28 | S33: =J33*(1+in_gen!$C$44*$C33) -> 14 | T33: =K33*(1+in_gen!$C$44*$C33) -> 14 | U33: =L33*(1+in_gen!$C$44*$C33) -> 28 | V33: =D33*(1+in_gen!$C$44*-$C33) -> 14 | W33: =E33*(1+in_gen!$C$44*-$C33) -> 14 | X33: =F33*(1+in_gen!$C$44*-$C33) -> 28 | Y33: =G33*(1+in_gen!$C$44*-$C33) -> 14 | Z33: =H33*(1+in_gen!$C$44*-$C33) -> 14 | AA33: =I33*(1+in_gen!$C$44*-$C33) -> 28 | AB33: =J33*(1+in_gen!$C$44*-$C33) -> 14 | AC33: =K33*(1+in_gen!$C$44*-$C33) -> 14 | AD33: =L33*(1+in_gen!$C$44*-$C33) -> 28
A34: distance_to_shore | C34: 0 | D34: 170000 | E34: 170000 | F34: 170000 | G34: 30000 | H34: 30000 | I34: 30000 | J34: 11000 | K34: 11000 | L34: 11000 | M34: =D34*(1+in_gen!$C$44*$C34) -> 170000 | N34: =E34*(1+in_gen!$C$44*$C34) -> 170000 | O34: =F34*(1+in_gen!$C$44*$C34) -> 170000 | P34: =G34*(1+in_gen!$C$44*$C34) -> 30000 | Q34: =H34*(1+in_gen!$C$44*$C34) -> 30000 | R34: =I34*(1+in_gen!$C$44*$C34) -> 30000 | S34: =J34*(1+in_gen!$C$44*$C34) -> 11000 | T34: =K34*(1+in_gen!$C$44*$C34) -> 11000 | U34: =L34*(1+in_gen!$C$44*$C34) -> 11000 | V34: =D34*(1+in_gen!$C$44*-$C34) -> 170000 | W34: =E34*(1+in_gen!$C$44*-$C34) -> 170000 | X34: =F34*(1+in_gen!$C$44*-$C34) -> 170000 | Y34: =G34*(1+in_gen!$C$44*-$C34) -> 30000 | Z34: =H34*(1+in_gen!$C$44*-$C34) -> 30000 | AA34: =I34*(1+in_gen!$C$44*-$C34) -> 30000 | AB34: =J34*(1+in_gen!$C$44*-$C34) -> 11000 | AC34: =K34*(1+in_gen!$C$44*-$C34) -> 11000 | AD34: =L34*(1+in_gen!$C$44*-$C34) -> 11000
A35: panel_transport_km | C35: 0 | D35: 620 | E35: 620 | F35: 620 | G35: 909 | H35: 909 | I35: 909 | J35: 2901 | K35: 2901 | L35: 2901 | M35: =D35*(1+in_gen!$C$44*$C35) -> 620 | N35: =E35*(1+in_gen!$C$44*$C35) -> 620 | O35: =F35*(1+in_gen!$C$44*$C35) -> 620 | P35: =G35*(1+in_gen!$C$44*$C35) -> 909 | Q35: =H35*(1+in_gen!$C$44*$C35) -> 909 | R35: =I35*(1+in_gen!$C$44*$C35) -> 909 | S35: =J35*(1+in_gen!$C$44*$C35) -> 2901 | T35: =K35*(1+in_gen!$C$44*$C35) -> 2901 | U35: =L35*(1+in_gen!$C$44*$C35) -> 2901 | V35: =D35*(1+in_gen!$C$44*-$C35) -> 620 | W35: =E35*(1+in_gen!$C$44*-$C35) -> 620 | X35: =F35*(1+in_gen!$C$44*-$C35) -> 620 | Y35: =G35*(1+in_gen!$C$44*-$C35) -> 909 | Z35: =H35*(1+in_gen!$C$44*-$C35) -> 909 | AA35: =I35*(1+in_gen!$C$44*-$C35) -> 909 | AB35: =J35*(1+in_gen!$C$44*-$C35) -> 2901 | AC35: =K35*(1+in_gen!$C$44*-$C35) -> 2901 | AD35: =L35*(1+in_gen!$C$44*-$C35) -> 2901
A37: Percentages (%)
A38: solar_degradation_yearly | C38: 1 | D38: 0.00375 | E38: 0.00375 | F38: 0.005 | G38: 0.001875 | H38: 0.001875 | I38: 0.0025 | J38: 0.000825 | K38: 0.000825 | L38: 0.00125 | M38: =D38*(1+in_gen!$C$44*$C38) -> 0.0039 | N38: =E38*(1+in_gen!$C$44*$C38) -> 0.0039 | O38: =F38*(1+in_gen!$C$44*$C38) -> 0.0052 | P38: =G38*(1+in_gen!$C$44*$C38) -> 0.00195 | Q38: =H38*(1+in_gen!$C$44*$C38) -> 0.00195 | R38: =I38*(1+in_gen!$C$44*$C38) -> 0.0026 | S38: =J38*(1+in_gen!$C$44*$C38) -> 0.000858 | T38: =K38*(1+in_gen!$C$44*$C38) -> 0.000858 | U38: =L38*(1+in_gen!$C$44*$C38) -> 0.0013 | V38: =D38*(1+in_gen!$C$44*-$C38) -> 0.0036 | W38: =E38*(1+in_gen!$C$44*-$C38) -> 0.0036 | X38: =F38*(1+in_gen!$C$44*-$C38) -> 0.0048 | Y38: =G38*(1+in_gen!$C$44*-$C38) -> 0.0018 | Z38: =H38*(1+in_gen!$C$44*-$C38) -> 0.0018 | AA38: =I38*(1+in_gen!$C$44*-$C38) -> 0.0024 | AB38: =J38*(1+in_gen!$C$44*-$C38) -> 0.000792 | AC38: =K38*(1+in_gen!$C$44*-$C38) -> 0.000792 | AD38: =L38*(1+in_gen!$C$44*-$C38) -> 0.0012
A39: solar_wave_loss | C39: 1 | D39: 0.015 | E39: 0.015 | F39: 0.02 | G39: 0.0075 | H39: 0.0075 | I39: 0.01 | J39: 0.0033 | K39: 0.0033 | L39: 0.005 | M39: =D39*(1+in_gen!$C$44*$C39) -> 0.0156 | N39: =E39*(1+in_gen!$C$44*$C39) -> 0.0156 | O39: =F39*(1+in_gen!$C$44*$C39) -> 0.0208 | P39: =G39*(1+in_gen!$C$44*$C39) -> 0.0078 | Q39: =H39*(1+in_gen!$C$44*$C39) -> 0.0078 | R39: =I39*(1+in_gen!$C$44*$C39) -> 0.0104 | S39: =J39*(1+in_gen!$C$44*$C39) -> 0.003432 | T39: =K39*(1+in_gen!$C$44*$C39) -> 0.003432 | U39: =L39*(1+in_gen!$C$44*$C39) -> 0.0052 | V39: =D39*(1+in_gen!$C$44*-$C39) -> 0.0144 | W39: =E39*(1+in_gen!$C$44*-$C39) -> 0.0144 | X39: =F39*(1+in_gen!$C$44*-$C39) -> 0.0192 | Y39: =G39*(1+in_gen!$C$44*-$C39) -> 0.0072 | Z39: =H39*(1+in_gen!$C$44*-$C39) -> 0.0072 | AA39: =I39*(1+in_gen!$C$44*-$C39) -> 0.0096 | AB39: =J39*(1+in_gen!$C$44*-$C39) -> 0.003168 | AC39: =K39*(1+in_gen!$C$44*-$C39) -> 0.003168 | AD39: =L39*(1+in_gen!$C$44*-$C39) -> 0.0048
A41: Energy (kWh)
A42: solar_production_yearly | C42: -1 | D42: 898 | E42: 898 | F42: 898 | G42: 927 | H42: 927 | I42: 927 | J42: 1306 | K42: 1306 | L42: 1306 | M42: =D42*(1+in_gen!$C$44*$C42) -> 862.08 | N42: =E42*(1+in_gen!$C$44*$C42) -> 862.08 | O42: =F42*(1+in_gen!$C$44*$C42) -> 862.08 | P42: =G42*(1+in_gen!$C$44*$C42) -> 889.92 | Q42: =H42*(1+in_gen!$C$44*$C42) -> 889.92 | R42: =I42*(1+in_gen!$C$44*$C42) -> 889.92 | S42: =J42*(1+in_gen!$C$44*$C42) -> 1253.76 | T42: =K42*(1+in_gen!$C$44*$C42) -> 1253.76 | U42: =L42*(1+in_gen!$C$44*$C42) -> 1253.76 | V42: =D42*(1+in_gen!$C$44*-$C42) -> 933.92 | W42: =E42*(1+in_gen!$C$44*-$C42) -> 933.92 | X42: =F42*(1+in_gen!$C$44*-$C42) -> 933.92 | Y42: =G42*(1+in_gen!$C$44*-$C42) -> 964.08 | Z42: =H42*(1+in_gen!$C$44*-$C42) -> 964.08 | AA42: =I42*(1+in_gen!$C$44*-$C42) -> 964.08 | AB42: =J42*(1+in_gen!$C$44*-$C42) -> 1358.24 | AC42: =K42*(1+in_gen!$C$44*-$C42) -> 1358.24 | AD42: =L42*(1+in_gen!$C$44*-$C42) -> 1358.24

Sheet in_gen
A1: Parameter | B1: Unit | C1: Value | D1: Dir | E1: Pes | F1: Opt | G1: Comment
A2: Cost (€)
A3: solar_panel_prod_workhours_cost_per_hour | B3: € / h | C3: 40 | D3: 1 | E3: =$C3*(1+$C$44*D3) -> 41.6 | F3: =$C3*(1+$C$44*-D3) -> 38.4 | G3: Cost per hour for workers assembly of floating solar panels.
A4: solar_panel_prod_material_costs | B4: € / kW | C4: 250 | D4: 1 | E4: =$C4*(1+$C$44*D4) -> 260 | F4: =$C4*(1+$C$44*-D4) -> 240 | G4: Aggregate material costs per kilowatt of nominal power, including the solar panel, polyurethane, pvc pipe, etc.
A5: solar_panel_prod_other_costs | B5: € / kW | C5: 90 | D5: 1 | E5: =$C5*(1+$C$44*D5) -> 93.6 | F5: =$C5*(1+$C$44*-D5) -> 86.4 | G5: Packaging, insurance, rent, energy, etc, per kilowatt of nominal power.
A6: container_transport_cost_road | B6: €/km per container | C6: 2 | D6: 1 | E6: =$C6*(1+$C$44*D6) -> 2.08 | F6: =$C6*(1+$C$44*-D6) -> 1.92 | G6: Standard European trucking rates for containers.
A7: container_transport_cost_sea | B7: €/km per container | C7: 5 | D7: 1 | E7: =$C7*(1+$C$44*D7) -> 5.2 | F7: =$C7*(1+$C$44*-D7) -> 4.8 | G7: Short-sea shipping rates from Maersk and MSC.
A8: dc_cable_cost_per_m | B8: €/m | C8: 2 | D8: 1 | E8: =$C8*(1+$C$44*D8) -> 2.08 | F8: =$C8*(1+$C$44*-D8) -> 1.92 | G8: Standard PV DC cables (e.g., 6mm² or 10mm² XLPE-insulated).
A9: ac_cable_cost_per_m | B9: €/m | C9: 80 | D9: 1 | E9: =$C9*(1+$C$44*D9) -> 83.2 | F9: =$C9*(1+$C$44*-D9) -> 76.8 | G9: Pricing for 33 kV medium-voltage aluminum cables.
A10: mv_floating_cable_cost_per_m | B10: €/m | C10: 95 | D10: 1 | E10: =$C10*(1+$C$44*D10) -> 98.8 | F10: =$C10*(1+$C$44*-D10) -> 91.2 | G10: Marine-certified floating cables like Prysmian FlexoMarine.
A11: mv_submarine_cable_cost_per_m | B11: €/m | C11: 150 | D11: 1 | E11: =$C11*(1+$C$44*D11) -> 156 | F11: =$C11*(1+$C$44*-D11) -> 144 | G11: Pricing for 33 kV offshore submarine cables.
A12: cable_installation_cost_per_m | B12: €/m | C12: 50 | D12: 1 | E12: =$C12*(1+$C$44*D12) -> 52 | F12: =$C12*(1+$C$44*-D12) -> 48 | G12: Typical cost for ROV-assisted submarine cable installation.
A13: scada_ppc | B13: € | C13: 12000 | D13: 1 | E13: =$C13*(1+$C$44*D13) -> 12480 | F13: =$C13*(1+$C$44*-D13) -> 11520 | G13: Power Plant Controller required for grid compliance
A14: scada_sems | B14: € | C14: 5000 | D14: 1 | E14: =$C14*(1+$C$44*D14) -> 5200 | F14: =$C14*(1+$C$44*-D14) -> 4800 | G14: Optional if cloud-only is used
... A25: anchor_chain_cost_per_t | B25: €/t | C25: 3000 | D25: 1 | E25: =$C25*(1+$C$44*D25) -> 3120 | F25: =$C25*(1+$C$44*-D25) -> 2880 | G25: Anchor chain cost per ton. Higher requirements than anchors, more expensive
A26: solar_energy_target_price | B26: €/kWh | C26: 0.12 | D26: 1 | E26: =$C26*(1+$C$44*D26) -> 0.1248 | F26: =$C26*(1+$C$44*-D26) -> 0.1152
A28: Count (unit)
A29: panels_per_container | B29: panels | C29: 400 | D29: 0 | E29: =$C29*(1+$C$44*D29) -> 400 | F29: =$C29*(1+$C$44*-D29) -> 400 | G29: A 40-ft high-cube container typically holds 380–420 panels.
A30: solar_lifetimes_per_wavebreaker_lifetime | C30: 2 | D30: 0 | E30: =$C30*(1+$C$44*D30) -> 2 | F30: =$C30*(1+$C$44*-D30) -> 2 | G30: How many solar lifetimes the wavebreaker lasts (i.e 50 years compared to 25 years for solar)
A32: Distance (m)
A33: dc_cable_per_panel | B33: m/panel | C33: 4 | D33: 0 | E33: =$C33*(1+$C$44*D33) -> 4 | F33: =$C33*(1+$C$44*-D33) -> 4 | G33: Based on average cabling per panel in utility solar installations
A34: ac_cable_length | B34: m | C34: 30 | D34: 0 | E34: =$C34*(1+$C$44*D34) -> 30 | F34: =$C34*(1+$C$44*-D34) -> 30 | G34: Estimated short connection between inverters and transformers.
A35: mv_floating_cable_length | B35: m | C35: 300 | D35: 0 | E35: =$C35*(1+$C$44*D35) -> 300 | F35: =$C35*(1+$C$44*-D35) -> 300 | G35: Bridges the distance between floating transformers and substation.
A36: solar_panel_width | B36: mm | C36: 1303 | D36: 0 | E36: =$C36*(1+$C$44*D36) -> 1303 | F36: =$C36*(1+$C$44*-D36) -> 1303 | G36: Width of the solar panel, excluding connecting joint
A37: solar_panel_length | B37: mm | C37: 2384 | D37: 0 | E37: =$C37*(1+$C$44*D37) -> 2384 | F37: =$C37*(1+$C$44*-D37) -> 2384 | G37: Length of the solar panel, excluding connecting joint
A38: solar_panel_hinge_length | B38: mm | C38: 150 | D38: 0 | E38: =$C38*(1+$C$44*D38) -> 150 | F38: =$C38*(1+$C$44*-D38) -> 150 | G38: Length of the hinge connecting the solar panels
A39: pontoon_width | B39: m | C39: 5 | D39: 0 | E39: =$C39*(1+$C$44*D39) -> 5 | F39: =$C39*(1+$C$44*-D39) -> 5 | G39: Width of pontoon, used for calculating space not usable for solar panels.
A41: Percentages (%)
A42: discount_rate | B42: % | C42: 0.085 | D42: 1 | E42: =$C42*(1+$C$44*D42) -> 0.0884 | F42: =$C42*(1+$C$44*-D42) -> 0.0816 | G42: Cost of lending money / alternative investment rate
A43: solar_extra_production_from_cooling | B43: % | C43: 0.08 | D43: -1 | E43: =$C43*(1+$C$44*D43) -> 0.0768 | F43: =$C43*(1+$C$44*-D43) -> 0.0832 | G43: Water has better heat conductivity than air. But as shown in the temperatures sheet, air temps are usually a bit cooler than the water for most locations. We therefore apply a flat cooling factor based on earlier tests for Sunlit Sea's product.
A44: sensitivity_margin | B44: % | C44: 0.04 | D44: 0 | E44: =$C44*(1+$C$44*D44) -> 0.04 | F44: =$C44*(1+$C$44*-D44) -> 0.04
A46: Power (W)
A47: solar_panel_power | B47: W per panel | C47: 730 | D47: 0 | E47: =$C47*(1+$C$44*D47) -> 730 | F47: =$C47*(1+$C$44*-D47) -> 730 | G47: Newer high-efficiency bifacial panels offer 650–750 W.
A49: Time (h / d / y)
A50: solar_panel_prod_workhours_per_kw | B50: h / kW | C50: 4 | D50: 1 | E50: =$C50*(1+$C$44*D50) -> 4.16 | F50: =$C50*(1+$C$44*-D50) -> 3.84 | G50: Production workhours to produce 1 kilowatt of nominal power. With a panel of 0.67 W that equals 1.493 panels
A51: solar_lifetime | B51: y | C51: 25 | D51: -1 | E51: =$C51*(1+$C$44*D51) -> 24 | F51: =$C51*(1+$C$44*-D51) -> 26 | G51: Lifetime for marine solar panels

Sheet inter_gen
A1: Parameter | B1: Unit | C1: Value | E1: Pes | F1: Opt | G1: Comment | H1: Formula
A2: total_ac_cable_cost | B2: € | C2: =in_gen!C9 * in_gen!C34 -> 2400 | E2: =in_gen!E9 * in_gen!E34 -> 2496 | F2: =in_gen!F9 * in_gen!F34 -> 2304 | H2: =in_gen!A9 & " * " & in_gen!A34 -> ac_cable_cost_per_m * ac_cable_length
A3: total_mv_floating_cable_cost | B3: € | C3: =in_gen!C10 * in_gen!C35 -> 28500 | E3: =in_gen!E10 * in_gen!E35 -> 29640 | F3: =in_gen!F10 * in_gen!F35 -> 27360 | H3: =in_gen!A10 & " * " & in_gen!A35 -> mv_floating_cable_cost_per_m * mv_floating_cable_length
A4: solar_panel_cost | B4: € / kW | C4: =in_gen!C50 * in_gen!C3 + in_gen!C4 + in_gen!C5 -> 500 | E4: =in_gen!E50 * in_gen!E3 + in_gen!E4 + in_gen!E5 -> 526.656 | F4: =in_gen!F50 * in_gen!F3 + in_gen!F4 + in_gen!F5 -> 473.856 | G4: Sunlit Sea floating solar panels market price. See own calculation | H4: =in_gen!A50 & " * " & in_gen!A3 & " + " & in_gen!A4 & " + " & in_gen!A5 -> solar_panel_prod_workhours_per_kw * solar_panel_prod_workhours_cost_per_hour + solar_panel_prod_material_costs + solar_panel_prod_other_costs
A5: scada_system | B5: € | C5: =in_gen!C13+in_gen!C14+in_gen!C15+in_gen!C16+in_gen!C17+in_gen!C18+in_gen!C19+in_gen!C20+in_gen!C21 -> 39000 | E5: =in_gen!E13+in_gen!E14+in_gen!E15+in_gen!E16+in_gen!E17+in_gen!E18+in_gen!E19+in_gen!E20+in_gen!E21 -> 40560 | F5: =in_gen!F13+in_gen!F14+in_gen!F15+in_gen!F16+in_gen!F17+in_gen!F18+in_gen!F19+in_gen!F20+in_gen!F21 -> 37440 | H5: =in_gen!A13 & " + " & in_gen!A14 & " + " & in_gen!A15 & " + " & in_gen!A16 & " + " & in_gen!A17 & " + " & in_gen!A18 & " + " & in_gen!A19 & " + " & in_gen!A20 & " + " & in_gen!A21 -> scada_ppc + scada_sems + scada_weather_station + scada_smart_energy_meter + scada_gateway_rtu + scada_switch_fiber + scada_local_hmi + scada_license_config + scada_cabling_racks_power_backup

Sheet out_loc
A1: Parameter | B1: Unit | C1: Comment | D1: n_2 | E1: n_25 | F1: n_10 | G1: b_2 | H1: b_25 | I1: b_10 | J1: m_2 | K1: m_25 | L1: m_10 | M1: =D1&"_pes" -> n_2_pes | N1: =E1&"_pes" -> n_25_pes | O1: =F1&"_pes" -> n_10_pes | P1: =G1&"_pes" -> b_2_pes | Q1: =H1&"_pes" -> b_25_pes | R1: =I1&"_pes" -> b_10_pes | S1: =J1&"_pes" -> m_2_pes | T1: =K1&"_pes" -> m_25_pes | U1: =L1&"_pes" -> m_10_pes | V1: =D1&"_opt" -> n_2_opt | W1: =E1&"_opt" -> n_25_opt | X1: =F1&"_opt" -> n_10_opt | Y1: =G1&"_opt" -> b_2_opt | Z1: =H1&"_opt" -> b_25_opt | AA1: =I1&"_opt" -> b_10_opt | AB1: =J1&"_opt" -> m_2_opt | AC1: =K1&"_opt" -> m_25_opt | AD1: =L1&"_opt" -> m_10_opt
A2: solar_panels_per_matrix_width | B2: unit | D2: =FLOOR((in_loc!D$33*1000+in_gen!$C$38)/(in_gen!$C$36+in_gen!$C$38),1) -> 9 | E2: =FLOOR((in_loc!E$33*1000+in_gen!$C$38)/(in_gen!$C$36+in_gen!$C$38),1) -> 9 | F2: =FLOOR((in_loc!F$33*1000+in_gen!$C$38)/(in_gen!$C$36+in_gen!$C$38),1) -> 19 | G2: =FLOOR((in_loc!G$33*1000+in_gen!$C$38)/(in_gen!$C$36+in_gen!$C$38),1) -> 9 | H2: =FLOOR((in_loc!H$33*1000+in_gen!$C$38)/(in_gen!$C$36+in_gen!$C$38),1) -> 9 | I2: =FLOOR((in_loc!I$33*1000+in_gen!$C$38)/(in_gen!$C$36+in_gen!$C$38),1) -> 19 | J2: =FLOOR((in_loc!J$33*1000+in_gen!$C$38)/(in_gen!$C$36+in_gen!$C$38),1) -> 9 | K2: =FLOOR((in_loc!K$33*1000+in_gen!$C$38)/(in_gen!$C$36+in_gen!$C$38),1) -> 9 | L2: =FLOOR((in_loc!L$33*1000+in_gen!$C$38)/(in_gen!$C$36+in_gen!$C$38),1) -> 19 | M2: =FLOOR((in_loc!M$33*1000+in_gen!$C$38)/(in_gen!$E$36+in_gen!$E$38),1) -> 9 | N2: =FLOOR((in_loc!N$33*1000+in_gen!$C$38)/(in_gen!$E$36+in_gen!$E$38),1) -> 9 | O2: =FLOOR((in_loc!O$33*1000+in_gen!$C$38)/(in_gen!$E$36+in_gen!$E$38),1) -> 19 | P2: =FLOOR((in_loc!P$33*1000+in_gen!$C$38)/(in_gen!$E$36+in_gen!$E$38),1) -> 9 | Q2: =FLOOR((in_loc!Q$33*1000+in_gen!$C$38)/(in_gen!$E$36+in_gen!$E$38),1) -> 9 | R2: =FLOOR((in_loc!R$33*1000+in_gen!$C$38)/(in_gen!$E$36+in_gen!$E$38),1) -> 19 | S2: =FLOOR((in_loc!S$33*1000+in_gen!$C$38)/(in_gen!$E$36+in_gen!$E$38),1) -> 9 | T2: =FLOOR((in_loc!T$33*1000+in_gen!$C$38)/(in_gen!$E$36+in_gen!$E$38),1) -> 9 | U2: =FLOOR((in_loc!U$33*1000+in_gen!$C$38)/(in_gen!$E$36+in_gen!$E$38),1) -> 19 | V2: =FLOOR((in_loc!V$33*1000+in_gen!$F$38)/(in_gen!$F$36+in_gen!$F$38),1) -> 9 | W2: =FLOOR((in_loc!W$33*1000+in_gen!$F$38)/(in_gen!$F$36+in_gen!$F$38),1) -> 9 | X2: =FLOOR((in_loc!X$33*1000+in_gen!$F$38)/(in_gen!$F$36+in_gen!$F$38),1) -> 19 | Y2: =FLOOR((in_loc!Y$33*1000+in_gen!$F$38)/(in_gen!$F$36+in_gen!$F$38),1) -> 9 | Z2: =FLOOR((in_loc!Z$33*1000+in_gen!$F$38)/(in_gen!$F$36+in_gen!$F$38),1) -> 9 | AA2: =FLOOR((in_loc!AA$33*1000+in_gen!$F$38)/(in_gen!$F$36+in_gen!$F$38),1) -> 19 | AB2: =FLOOR((in_loc!AB$33*1000+in_gen!$F$38)/(in_gen!$F$36+in_gen!$F$38),1) -> 9 | AC2: =FLOOR((in_loc!AC$33*1000+in_gen!$F$38)/(in_gen!$F$36+in_gen!$F$38),1) -> 9 | AD2: =FLOOR((in_loc!AD$33*1000+in_gen!$F$38)/(in_gen!$F$36+in_gen!$F$38),1) -> 19
A3: solar_panels_per_matrix_length | B3: unit | D3: =FLOOR((in_loc!D$33*1000+in_gen!$C$38)/(in_gen!$C$37+in_gen!$C$38),1) -> 5 | E3: =FLOOR((in_loc!E$33*1000+in_gen!$C$38)/(in_gen!$C$37+in_gen!$C$38),1) -> 5 | F3: =FLOOR((in_loc!F$33*1000+in_gen!$C$38)/(in_gen!$C$37+in_gen!$C$38),1) -> 11 | G3: =FLOOR((in_loc!G$33*1000+in_gen!$C$38)/(in_gen!$C$37+in_gen!$C$38),1) -> 5 | H3: =FLOOR((in_loc!H$33*1000+in_gen!$C$38)/(in_gen!$C$37+in_gen!$C$38),1) -> 5 | I3: =FLOOR((in_loc!I$33*1000+in_gen!$C$38)/(in_gen!$C$37+in_gen!$C$38),1) -> 11 | J3: =FLOOR((in_loc!J$33*1000+in_gen!$C$38)/(in_gen!$C$37+in_gen!$C$38),1) -> 5 | K3: =FLOOR((in_loc!K$33*1000+in_gen!$C$38)/(in_gen!$C$37+in_gen!$C$38),1) -> 5 | L3: =FLOOR((in_loc!L$33*1000+in_gen!$C$38)/(in_gen!$C$37+in_gen!$C$38),1) -> 11 | M3: =FLOOR((in_loc!M$33*1000+in_gen!$E$38)/(in_gen!$E$37+in_gen!$E$38),1) -> 5 | N3: =FLOOR((in_loc!N$33*1000+in_gen!$E$38)/(in_gen!$E$37+in_gen!$E$38),1) -> 5 | O3: =FLOOR((in_loc!O$33*1000+in_gen!$E$38)/(in_gen!$E$37+in_gen!$E$38),1) -> 11 | P3: =FLOOR((in_loc!P$33*1000+in_gen!$E$38)/(in_gen!$E$37+in_gen!$E$38),1) -> 5 | Q3: =FLOOR((in_loc!Q$33*1000+in_gen!$E$38)/(in_gen!$E$37+in_gen!$E$38),1) -> 5 | R3: =FLOOR((in_loc!R$33*1000+in_gen!$E$38)/(in_gen!$E$37+in_gen!$E$38),1) -> 11 | S3: =FLOOR((in_loc!S$33*1000+in_gen!$E$38)/(in_gen!$E$37+in_gen!$E$38),1) -> 5 | T3: =FLOOR((in_loc!T$33*1000+in_gen!$E$38)/(in_gen!$E$37+in_gen!$E$38),1) -> 5 | U3: =FLOOR((in_loc!U$33*1000+in_gen!$E$38)/(in_gen!$E$37+in_gen!$E$38),1) -> 11 | V3: =FLOOR((in_loc!V$33*1000+in_gen!$F$38)/(in_gen!$F$37+in_gen!$F$38),1) -> 5 | W3: =FLOOR((in_loc!W$33*1000+in_gen!$F$38)/(in_gen!$F$37+in_gen!$F$38),1) -> 5 | X3: =FLOOR((in_loc!X$33*1000+in_gen!$F$38)/(in_gen!$F$37+in_gen!$F$38),1) -> 11 | Y3: =FLOOR((in_loc!Y$33*1000+in_gen!$F$38)/(in_gen!$F$37+in_gen!$F$38),1) -> 5 | Z3: =FLOOR((in_loc!Z$33*1000+in_gen!$F$38)/(in_gen!$F$37+in_gen!$F$38),1) -> 5 | AA3: =FLOOR((in_loc!AA$33*1000+in_gen!$F$38)/(in_gen!$F$37+in_gen!$F$38),1) -> 11 | AB3: =FLOOR((in_loc!AB$33*1000+in_gen!$F$38)/(in_gen!$F$37+in_gen!$F$38),1) -> 5 | AC3: =FLOOR((in_loc!AC$33*1000+in_gen!$F$38)/(in_gen!$F$37+in_gen!$F$38),1) -> 5 | AD3: =FLOOR((in_loc!AD$33*1000+in_gen!$F$38)/(in_gen!$F$37+in_gen!$F$38),1) -> 11
A4: solar_panels_per_matrix | B4: unit | D4: =D$2*D$3 -> 45 | E4: =E$2*E$3 -> 45 | F4: =F$2*F$3 -> 209 | G4: =G$2*G$3 -> 45 | H4: =H$2*H$3 -> 45 | I4: =I$2*I$3 -> 209 | J4: =J$2*J$3 -> 45 | K4: =K$2*K$3 -> 45 | ... AD4: =AD$2*AD$3 -> 209
A5: solar_radius | B5: m | D5: =CEILING(SQRT(1+D$7^2)*in_loc!D$33,1) +in_gen!$C$39/2 -> 74.5 | E5: =CEILING(SQRT(1+E$7^2)*in_loc!E$33,1) +in_gen!$C$39/2 -> 74.5 | F5: =CEILING(SQRT(1+F$7^2)*in_loc!F$33,1) +in_gen!$C$39/2 -> 145.5 | G5: =CEILING(SQRT(1+G$7^2)*in_loc!G$33,1) +in_gen!$C$39/2 -> 74.5 | H5: =CEILING(SQRT(1+H$7^2)*in_loc!H$33,1) +in_gen!$C$39/2 -> 74.5 | I5: =CEILING(SQRT(1+I$7^2)*in_loc!I$33,1) +in_gen!$C$39/2 -> 145.5 | J5: =CEILING(SQRT(1+J$7^2)*in_loc!J$33,1) +in_gen!$C$39/2 -> 74.5 | K5: =CEILING(SQRT(1+K$7^2)*in_loc!K$33,1) +in_gen!$C$39/2 -> 74.5 | L5: =CEILING(SQRT(1+L$7^2)*in_loc!L$33,1) +in_gen!$C$39/2 -> 145.5 | M5: =CEILING(SQRT(1+M$7^2)*in_loc!M$33,1) +in_gen!$E$39/2 -> 74.5 | N5: =CEILING(SQRT(1+N$7^2)*in_loc!N$33,1) +in_gen!$E$39/2 -> 74.5 | O5: =CEILING(SQRT(1+O$7^2)*in_loc!O$33,1) +in_gen!$E$39/2 -> 145.5 | P5: =CEILING(SQRT(1+P$7^2)*in_loc!P$33,1) +in_gen!$E$39/2 -> 74.5 | Q5: =CEILING(SQRT(1+Q$7^2)*in_loc!Q$33,1) +in_gen!$E$39/2 -> 74.5 | R5: =CEILING(SQRT(1+R$7^2)*in_loc!R$33,1) +in_gen!$E$39/2 -> 145.5 | S5: =CEILING(SQRT(1+S$7^2)*in_loc!S$33,1) +in_gen!$E$39/2 -> 74.5 | T5: =CEILING(SQRT(1+T$7^2)*in_loc!T$33,1) +in_gen!$E$39/2 -> 74.5 | U5: =CEILING(SQRT(1+U$7^2)*in_loc!U$33,1) +in_gen!$E$39/2 -> 145.5 | V5: =CEILING(SQRT(1+V$7^2)*in_loc!V$33,1) +in_gen!$F$39/2 -> 74.5 | W5: =CEILING(SQRT(1+W$7^2)*in_loc!W$33,1) +in_gen!$F$39/2 -> 74.5 | X5: =CEILING(SQRT(1+X$7^2)*in_loc!X$33,1) +in_gen!$F$39/2 -> 145.5 | Y5: =CEILING(SQRT(1+Y$7^2)*in_loc!Y$33,1) +in_gen!$F$39/2 -> 74.5 | Z5: =CEILING(SQRT(1+Z$7^2)*in_loc!Z$33,1) +in_gen!$F$39/2 -> 74.5 | AA5: =CEILING(SQRT(1+AA$7^2)*in_loc!AA$33,1) +in_gen!$F$39/2 -> 145.5 | AB5: =CEILING(SQRT(1+AB$7^2)*in_loc!AB$33,1) +in_gen!$F$39/2 -> 74.5 | AC5: =CEILING(SQRT(1+AC$7^2)*in_loc!AC$33,1) +in_gen!$F$39/2 -> 74.5 | AD5: =CEILING(SQRT(1+AD$7^2)*in_loc!AD$33,1) +in_gen!$F$39/2 -> 145.5
A6: total_solar_panels | B6: unit | D6: =D$4*in_loc!D$21*4 -> 3060 | E6: =E$4*in_loc!E$21*4 -> 3060 | F6: =F$4*in_loc!F$21*4 -> 14212 | G6: =G$4*in_loc!G$21*4 -> 3060 | H6: =H$4*in_loc!H$21*4 -> 3060 | I6: =I$4*in_loc!I$21*4 -> 14212 | J6: =J$4*in_loc!J$21*4 -> 3060 | K6: =K$4*in_loc!K$21*4 -> 3060 | ... AD6: =AD$4*in_loc!AD$21*4 -> 14212
A7: solar_matrices_along_radii | B7: unit | D7: =CEILING(SQRT(in_loc!D$21),1) -> 5 | E7: =CEILING(SQRT(in_loc!E$21),1) -> 5 | F7: =CEILING(SQRT(in_loc!F$21),1) -> 5 | G7: =CEILING(SQRT(in_loc!G$21),1) -> 5 | H7: =CEILING(SQRT(in_loc!H$21),1) -> 5 | I7: =CEILING(SQRT(in_loc!I$21),1) -> 5 | J7: =CEILING(SQRT(in_loc!J$21),1) -> 5 | K7: =CEILING(SQRT(in_loc!K$21),1) -> 5 | ... AD7: =CEILING(SQRT(in_loc!AD$21),1) -> 5
A8: total_dc_cable_cost | B8: € | D8: =in_gen!$C$8*in_gen!$C$33*D$6 -> 24480 | E8: =in_gen!$C$8*in_gen!$C$33*E$6 -> 24480 | F8: =in_gen!$C$8*in_gen!$C$33*F$6 -> 113696 | G8: =in_gen!$C$8*in_gen!$C$33*G$6 -> 24480 | H8: =in_gen!$C$8*in_gen!$C$33*H$6 -> 24480 | I8: =in_gen!$C$8*in_gen!$C$33*I$6 -> 113696 | J8: =in_gen!$C$8*in_gen!$C$33*J$6 -> 24480 | K8: =in_gen!$C$8*in_gen!$C$33*K$6 -> 24480 | L8: =in_gen!$C$8*in_gen!$C$33*L$6 -> 113696 | M8: =in_gen!$E$8*in_gen!$E$33*M$6 -> 25459.2 | N8: =in_gen!$E$8*in_gen!$E$33*N$6 -> 25459.2 | O8: =in_gen!$E$8*in_gen!$E$33*O$6 -> 118243.84 | P8: =in_gen!$E$8*in_gen!$E$33*P$6 -> 25459.2 | Q8: =in_gen!$E$8*in_gen!$E$33*Q$6 -> 25459.2 | R8: =in_gen!$E$8*in_gen!$E$33*R$6 -> 118243.84 | S8: =in_gen!$E$8*in_gen!$E$33*S$6 -> 25459.2 | T8: =in_gen!$E$8*in_gen!$E$33*T$6 -> 25459.2 | U8: =in_gen!$E$8*in_gen!$E$33*U$6 -> 118243.84 | V8: =in_gen!$F$8*in_gen!$F$33*V$6 -> 23500.8 | W8: =in_gen!$F$8*in_gen!$F$33*W$6 -> 23500.8 | X8: =in_gen!$F$8*in_gen!$F$33*X$6 -> 109148.16 | Y8: =in_gen!$F$8*in_gen!$F$33*Y$6 -> 23500.8 | Z8: =in_gen!$F$8*in_gen!$F$33*Z$6 -> 23500.8 | AA8: =in_gen!$F$8*in_gen!$F$33*AA$6 -> 109148.16 | AB8: =in_gen!$F$8*in_gen!$F$33*AB$6 -> 23500.8 | AC8: =in_gen!$F$8*in_gen!$F$33*AC$6 -> 23500.8 | AD8: =in_gen!$F$8*in_gen!$F$33*AD$6 -> 109148.16
A9: total_solar_power | B9: kW | D9: =D$6*in_gen!$C$47/1000 -> 2233.8 | E9: =E$6*in_gen!$C$47/1000 -> 2233.8 | F9: =F$6*in_gen!$C$47/1000 -> 10374.76 | G9: =G$6*in_gen!$C$47/1000 -> 2233.8 | H9: =H$6*in_gen!$C$47/1000 -> 2233.8 | I9: =I$6*in_gen!$C$47/1000 -> 10374.76 | J9: =J$6*in_gen!$C$47/1000 -> 2233.8 | K9: =K$6*in_gen!$C$47/1000 -> 2233.8 | L9: =L$6*in_gen!$C$47/1000 -> 10374.76 | M9: =M$6*in_gen!$E$47/1000 -> 2233.8 | N9: =N$6*in_gen!$E$47/1000 -> 2233.8 | O9: =O$6*in_gen!$E$47/1000 -> 10374.76 | P9: =P$6*in_gen!$E$47/1000 -> 2233.8 | Q9: =Q$6*in_gen!$E$47/1000 -> 2233.8 | R9: =R$6*in_gen!$E$47/1000 -> 10374.76 | S9: =S$6*in_gen!$E$47/1000 -> 2233.8 | T9: =T$6*in_gen!$E$47/1000 -> 2233.8 | U9: =U$6*in_gen!$E$47/1000 -> 10374.76 | V9: =V$6*in_gen!$F$47/1000 -> 2233.8 | W9: =W$6*in_gen!$F$47/1000 -> 2233.8 | X9: =X$6*in_gen!$F$47/1000 -> 10374.76 | Y9: =Y$6*in_gen!$F$47/1000 -> 2233.8 | Z9: =Z$6*in_gen!$F$47/1000 -> 2233.8 | AA9: =AA$6*in_gen!$F$47/1000 -> 10374.76 | AB9: =AB$6*in_gen!$F$47/1000 -> 2233.8 | AC9: =AC$6*in_gen!$F$47/1000 -> 2233.8 | AD9: =AD$6*in_gen!$F$47/1000 -> 10374.76
A10: solar_container_count | B10: unit | D10: =CEILING(D$6/in_gen!$C$29,1) -> 8 | E10: =CEILING(E$6/in_gen!$C$29,1) -> 8 | F10: =CEILING(F$6/in_gen!$C$29,1) -> 36 | G10: =CEILING(G$6/in_gen!$C$29,1) -> 8 | H10: =CEILING(H$6/in_gen!$C$29,1) -> 8 | I10: =CEILING(I$6/in_gen!$C$29,1) -> 36 | J10: =CEILING(J$6/in_gen!$C$29,1) -> 8 | K10: =CEILING(K$6/in_gen!$C$29,1) -> 8 | L10: =CEILING(L$6/in_gen!$C$29,1) -> 36 | M10: =CEILING(M$6/in_gen!$E$29,1) -> 8 | N10: =CEILING(N$6/in_gen!$E$29,1) -> 8 | O10: =CEILING(O$6/in_gen!$E$29,1) -> 36 | P10: =CEILING(P$6/in_gen!$E$29,1) -> 8 | Q10: =CEILING(Q$6/in_gen!$E$29,1) -> 8 | R10: =CEILING(R$6/in_gen!$E$29,1) -> 36 | S10: =CEILING(S$6/in_gen!$E$29,1) -> 8 | T10: =CEILING(T$6/in_gen!$E$29,1) -> 8 | U10: =CEILING(U$6/in_gen!$E$29,1) -> 36 | V10: =CEILING(V$6/in_gen!$F$29,1) -> 8 | W10: =CEILING(W$6/in_gen!$F$29,1) -> 8 | X10: =CEILING(X$6/in_gen!$F$29,1) -> 36 | Y10: =CEILING(Y$6/in_gen!$F$29,1) -> 8 | Z10: =CEILING(Z$6/in_gen!$F$29,1) -> 8 | AA10: =CEILING(AA$6/in_gen!$F$29,1) -> 36 | AB10: =CEILING(AB$6/in_gen!$F$29,1) -> 8 | AC10: =CEILING(AC$6/in_gen!$F$29,1) -> 8 | AD10: =CEILING(AD$6/in_gen!$F$29,1) -> 36
A11: total_mv_submarine_cable_cost | B11: € | D11: =(in_gen!$C$11+in_gen!$C$12)*in_loc!D$34 -> 34000000 | E11: =(in_gen!$C$11+in_gen!$C$12)*in_loc!E$34 -> 34000000 | F11: =(in_gen!$C$11+in_gen!$C$12)*in_loc!F$34 -> 34000000 | G11: =(in_gen!$C$11+in_gen!$C$12)*in_loc!G$34 -> 6000000 | H11: =(in_gen!$C$11+in_gen!$C$12)*in_loc!H$34 -> 6000000 | I11: =(in_gen!$C$11+in_gen!$C$12)*in_loc!I$34 -> 6000000 | J11: =(in_gen!$C$11+in_gen!$C$12)*in_loc!J$34 -> 2200000 | K11: =(in_gen!$C$11+in_gen!$C$12)*in_loc!K$34 -> 2200000 | L11: =(in_gen!$C$11+in_gen!$C$12)*in_loc!L$34 -> 2200000 | M11: =(in_gen!$E$11+in_gen!$E$12)*in_loc!M$34 -> 35360000 | N11: =(in_gen!$E$11+in_gen!$E$12)*in_loc!N$34 -> 35360000 | O11: =(in_gen!$E$11+in_gen!$E$12)*in_loc!O$34 -> 35360000 | P11: =(in_gen!$E$11+in_gen!$E$12)*in_loc!P$34 -> 6240000 | Q11: =(in_gen!$E$11+in_gen!$E$12)*in_loc!Q$34 -> 6240000 | R11: =(in_gen!$E$11+in_gen!$E$12)*in_loc!R$34 -> 6240000 | S11: =(in_gen!$E$11+in_gen!$E$12)*in_loc!S$34 -> 2288000 | T11: =(in_gen!$E$11+in_gen!$E$12)*in_loc!T$34 -> 2288000 | U11: =(in_gen!$E$11+in_gen!$E$12)*in_loc!U$34 -> 2288000 | V11: =(in_gen!$F$11+in_gen!$F$12)*in_loc!V$34 -> 32640000 | W11: =(in_gen!$F$11+in_gen!$F$12)*in_loc!W$34 -> 32640000 | X11: =(in_gen!$F$11+in_gen!$F$12)*in_loc!X$34 -> 32640000 | Y11: =(in_gen!$F$11+in_gen!$F$12)*in_loc!Y$34 -> 5760000 | Z11: =(in_gen!$F$11+in_gen!$F$12)*in_loc!Z$34 -> 5760000 | AA11: =(in_gen!$F$11+in_gen!$F$12)*in_loc!AA$34 -> 5760000 | AB11: =(in_gen!$F$11+in_gen!$F$12)*in_loc!AB$34 -> 2112000 | AC11: =(in_gen!$F$11+in_gen!$F$12)*in_loc!AC$34 -> 2112000 | AD11: =(in_gen!$F$11+in_gen!$F$12)*in_loc!AD$34 -> 2112000
A13: total_pvc_cost | B13: € | D13: =in_gen!$C$22*in_loc!D$27 -> 16728 | E13: =in_gen!$C$22*in_loc!E$27 -> 83640 | F13: =in_gen!$C$22*in_loc!F$27 -> 69987 | G13: =in_gen!$C$22*in_loc!G$27 -> 16728 | H13: =in_gen!$C$22*in_loc!H$27 -> 83640 | I13: =in_gen!$C$22*in_loc!I$27 -> 69987 | J13: =in_gen!$C$22*in_loc!J$27 -> 16728 | K13: =in_gen!$C$22*in_loc!K$27 -> 83640 | L13: =in_gen!$C$22*in_loc!L$27 -> 69987 | M13: =in_gen!$E$22*in_loc!M$27 -> 17397.12 | N13: =in_gen!$E$22*in_loc!N$27 -> 86985.6 | O13: =in_gen!$E$22*in_loc!O$27 -> 72786.48 | P13: =in_gen!$E$22*in_loc!P$27 -> 17397.12 | Q13: =in_gen!$E$22*in_loc!Q$27 -> 86985.6 | R13: =in_gen!$E$22*in_loc!R$27 -> 72786.48 | S13: =in_gen!$E$22*in_loc!S$27 -> 17397.12 | T13: =in_gen!$E$22*in_loc!T$27 -> 86985.6 | U13: =in_gen!$E$22*in_loc!U$27 -> 72786.48 | V13: =in_gen!$F$22*in_loc!V$27 -> 16058.88 | W13: =in_gen!$F$22*in_loc!W$27 -> 80294.4 | X13: =in_gen!$F$22*in_loc!X$27 -> 67187.52 | Y13: =in_gen!$F$22*in_loc!Y$27 -> 16058.88 | Z13: =in_gen!$F$22*in_loc!Z$27 -> 80294.4 | AA13: =in_gen!$F$22*in_loc!AA$27 -> 67187.52 | AB13: =in_gen!$F$22*in_loc!AB$27 -> 16058.88 | AC13: =in_gen!$F$22*in_loc!AC$27 -> 80294.4 | AD13: =in_gen!$F$22*in_loc!AD$27 -> 67187.52
A14: total_rope_cost | B14: € | D14: =in_gen!$C$23*in_loc!D$28 -> 2700 | E14: =in_gen!$C$23*in_loc!E$28 -> 13500 | F14: =in_gen!$C$23*in_loc!F$28 -> 12300 | G14: =in_gen!$C$23*in_loc!G$28 -> 2700 | H14: =in_gen!$C$23*in_loc!H$28 -> 13500 | I14: =in_gen!$C$23*in_loc!I$28 -> 12300 | J14: =in_gen!$C$23*in_loc!J$28 -> 2700 | K14: =in_gen!$C$23*in_loc!K$28 -> 13500 | L14: =in_gen!$C$23*in_loc!L$28 -> 12300 | M14: =in_gen!$E$23*in_loc!M$28 -> 2808 | N14: =in_gen!$E$23*in_loc!N$28 -> 14040 | O14: =in_gen!$E$23*in_loc!O$28 -> 12792 | P14: =in_gen!$E$23*in_loc!P$28 -> 2808 | Q14: =in_gen!$E$23*in_loc!Q$28 -> 14040 | R14: =in_gen!$E$23*in_loc!R$28 -> 12792 | S14: =in_gen!$E$23*in_loc!S$28 -> 2808 | T14: =in_gen!$E$23*in_loc!T$28 -> 14040 | U14: =in_gen!$E$23*in_loc!U$28 -> 12792 | V14: =in_gen!$F$23*in_loc!V$28 -> 2592 | W14: =in_gen!$F$23*in_loc!W$28 -> 12960 | X14: =in_gen!$F$23*in_loc!X$28 -> 11808 | Y14: =in_gen!$F$23*in_loc!Y$28 -> 2592 | Z14: =in_gen!$F$23*in_loc!Z$28 -> 12960 | AA14: =in_gen!$F$23*in_loc!AA$28 -> 11808 | AB14: =in_gen!$F$23*in_loc!AB$28 -> 2592 | AC14: =in_gen!$F$23*in_loc!AC$28 -> 12960 | AD14: =in_gen!$F$23*in_loc!AD$28 -> 11808
A15: solar_freight_cost | B15: € | D15: =in_loc!D$22*in_loc!D$35*D$10*VLOOKUP(D$13,freight!$A$2:$B999,2, TRUE) -> 3501.264 | E15: =in_loc!E$22*in_loc!E$35*E$10*VLOOKUP(E$13,freight!$A$2:$B999,2, TRUE) -> 17506.32 | F15: =in_loc!F$22*in_loc!F$35*F$10*VLOOKUP(F$13,freight!$A$2:$B999,2, TRUE) -> 15755.688 | G15: =in_loc!G$22*in_loc!G$35*G$10*VLOOKUP(G$13,freight!$A$2:$B999,2, TRUE) -> 5133.3048 | H15: =in_loc!H$22*in_loc!H$35*H$10*VLOOKUP(H$13,freight!$A$2:$B999,2, TRUE) -> 25666.524 | I15: =in_loc!I$22*in_loc!I$35*I$10*VLOOKUP(I$13,freight!$A$2:$B999,2, TRUE) -> 23099.872 | J15: =in_loc!J$22*in_loc!J$35*J$10*VLOOKUP(J$13,freight!$A$2:$B999,2, TRUE) -> 16382.527 | K15: =in_loc!K$22*in_loc!K$35*K$10*VLOOKUP(K$13,freight!$A$2:$B999,2, TRUE) -> 81912.636 | ... AD15: =in_loc!AD$22*in_loc!AD$35*AD$10*VLOOKUP(AD$13,freight!$A$2:$B999,2, TRUE) -> 73721.372
A16: total_pontoon_cost | B16: € | D16: {=INDEX(pontoons!$AA3:$AA999, MATCH(D$1, pontoons!$Z3:$Z999, 0))} -> 678095.6 | E16: {=INDEX(pontoons!$AA3:$AA999, MATCH(E$1, pontoons!$Z3:$Z999, 0))} -> 3390478 | F16: {=INDEX(pontoons!$AA3:$AA999, MATCH(F$1, pontoons!$Z3:$Z999, 0))} -> 2118899 | G16: {=INDEX(pontoons!$AA3:$AA999, MATCH(G$1, pontoons!$Z3:$Z999, 0))} -> 678095.6 | H16: {=INDEX(pontoons!$AA3:$AA999, MATCH(H$1, pontoons!$Z3:$Z999, 0))} -> 3390478 | I16: {=INDEX(pontoons!$AA3:$AA999, MATCH(I$1, pontoons!$Z3:$Z999, 0))} -> 2118899 | J16: {=INDEX(pontoons!$AA3:$AA999, MATCH(J$1, pontoons!$Z3:$Z999, 0))} -> 678095.6 | K16: {=INDEX(pontoons!$AA3:$AA999, MATCH(K$1, pontoons!$Z3:$Z999, 0))} -> 3390478 | ... AD16: {=INDEX(pontoons!$AA3:$AA999, MATCH(AD$1, pontoons!$Z3:$Z999, 0))} -> 2034143
A17: total_cost_solar_panels | B17: € | D17: =in_loc!D$22*inter_gen!$C$4*D$9 -> 1116900 | E17: =in_loc!E$22*inter_gen!$C$4*E$9 -> 5584500 | F17: =in_loc!F$22*inter_gen!$C$4*F$9 -> 5187380 | G17: =in_loc!G$22*inter_gen!$C$4*G$9 -> 1116900 | H17: =in_loc!H$22*inter_gen!$C$4*H$9 -> 5584500 | I17: =in_loc!I$22*inter_gen!$C$4*I$9 -> 5187380 | J17: =in_loc!J$22*inter_gen!$C$4*J$9 -> 1116900 | K17: =in_loc!K$22*inter_gen!$C$4*K$9 -> 5584500 | L17: =in_loc!L$22*inter_gen!$C$4*L$9 -> 5187380 | M17: =in_loc!M$22*inter_gen!$F$4*M$9 -> 1058499.5 | N17: =in_loc!N$22*inter_gen!$F$4*N$9 -> 5292497.7 | O17: =in_loc!O$22*inter_gen!$F$4*O$9 -> 4916142.3 | P17: =in_loc!P$22*inter_gen!$F$4*P$9 -> 1058499.5 | Q17: =in_loc!Q$22*inter_gen!$F$4*Q$9 -> 5292497.7 | R17: =in_loc!R$22*inter_gen!$F$4*R$9 -> 4916142.3 | S17: =in_loc!S$22*inter_gen!$F$4*S$9 -> 1058499.5 | T17: =in_loc!T$22*inter_gen!$F$4*T$9 -> 5292497.7 | ... AD17: =in_loc!AD$22*inter_gen!$F$4*AD$9 -> 4916142.3
A18: total_cost_cabling_short_alternative | B18: € | D18: =in_loc!D$22*(D$8+inter_gen!$C$2+inter_gen!$C$3) -> 55380 | E18: =in_loc!E$22*(E$8+inter_gen!$C$2+inter_gen!$C$3) -> 276900 | F18: =in_loc!F$22*(F$8+inter_gen!$C$2+inter_gen!$C$3) -> 144596 | G18: =in_loc!G$22*(G$8+inter_gen!$C$2+inter_gen!$C$3) -> 55380 | H18: =in_loc!H$22*(H$8+inter_gen!$C$2+inter_gen!$C$3) -> 276900 | I18: =in_loc!I$22*(I$8+inter_gen!$C$2+inter_gen!$C$3) -> 144596 | J18: =in_loc!J$22*(J$8+inter_gen!$C$2+inter_gen!$C$3) -> 55380 | K18: =in_loc!K$22*(K$8+inter_gen!$C$2+inter_gen!$C$3) -> 276900 | L18: =in_loc!L$22*(L$8+inter_gen!$C$2+inter_gen!$C$3) -> 144596 | M18: =in_loc!M$22*(M$8+inter_gen!$F$2+inter_gen!$F$3) -> 55123.2 | N18: =in_loc!N$22*(N$8+inter_gen!$F$2+inter_gen!$F$3) -> 275616 | O18: =in_loc!O$22*(O$8+inter_gen!$F$2+inter_gen!$F$3) -> 147907.84 | P18: =in_loc!P$22*(P$8+inter_gen!$F$2+inter_gen!$F$3) -> 55123.2 | Q18: =in_loc!Q$22*(Q$8+inter_gen!$F$2+inter_gen!$F$3) -> 275616 | R18: =in_loc!R$22*(R$8+inter_gen!$F$2+inter_gen!$F$3) -> 147907.84 | S18: =in_loc!S$22*(S$8+inter_gen!$F$2+inter_gen!$F$3) -> 55123.2 | T18: =in_loc!T$22*(T$8+inter_gen!$F$2+inter_gen!$F$3) -> 275616 | ... AD18: =in_loc!AD$22*(AD$8+inter_gen!$F$2+inter_gen!$F$3) -> 138812.16
A19: total_cost_cabling_long_alternative | B19: € | D19: =in_loc!D$22*(D$8+inter_gen!$C$2)+D$11 -> 34026880 | E19: =in_loc!E$22*(E$8+inter_gen!$C$2)+E$11 -> 34134400 | F19: =in_loc!F$22*(F$8+inter_gen!$C$2)+F$11 -> 34116096 | G19: =in_loc!G$22*(G$8+inter_gen!$C$2)+G$11 -> 6026880 | H19: =in_loc!H$22*(H$8+inter_gen!$C$2)+H$11 -> 6134400 | I19: =in_loc!I$22*(I$8+inter_gen!$C$2)+I$11 -> 6116096 | J19: =in_loc!J$22*(J$8+inter_gen!$C$2)+J$11 -> 2226880 | K19: =in_loc!K$22*(K$8+inter_gen!$C$2)+K$11 -> 2334400 | L19: =in_loc!L$22*(L$8+inter_gen!$C$2)+L$11 -> 2316096 | M19: =in_loc!M$22*(M$8+inter_gen!$F$2)+M$11 -> 35387763 | N19: =in_loc!N$22*(N$8+inter_gen!$F$2)+N$11 -> 35498816 | O19: =in_loc!O$22*(O$8+inter_gen!$F$2)+O$11 -> 35480548 | P19: =in_loc!P$22*(P$8+inter_gen!$F$2)+P$11 -> 6267763.2 | Q19: =in_loc!Q$22*(Q$8+inter_gen!$F$2)+Q$11 -> 6378816 | R19: =in_loc!R$22*(R$8+inter_gen!$F$2)+R$11 -> 6360547.8 | S19: =in_loc!S$22*(S$8+inter_gen!$F$2)+S$11 -> 2315763.2 | T19: =in_loc!T$22*(T$8+inter_gen!$F$2)+T$11 -> 2426816 | ... AD19: =in_loc!AD$22*(AD$8+inter_gen!$F$2)+AD$11 -> 2223452.2
A20: total_cost_anchoring_mooring | B20: € | D20: =in_loc!D$22*(in_loc!D$25*in_gen!$C$24+in_loc!D$26*in_gen!$C$25) -> 148210 | E20: =in_loc!E$22*(in_loc!E$25*in_gen!$C$24+in_loc!E$26*in_gen!$C$25) -> 741050 | F20: =in_loc!F$22*(in_loc!F$25*in_gen!$C$24+in_loc!F$26*in_gen!$C$25) -> 212580 | G20: =in_loc!G$22*(in_loc!G$25*in_gen!$C$24+in_loc!G$26*in_gen!$C$25) -> 54460 | H20: =in_loc!H$22*(in_loc!H$25*in_gen!$C$24+in_loc!H$26*in_gen!$C$25) -> 272300 | I20: =in_loc!I$22*(in_loc!I$25*in_gen!$C$24+in_loc!I$26*in_gen!$C$25) -> 124490 | J20: =in_loc!J$22*(in_loc!J$25*in_gen!$C$24+in_loc!J$26*in_gen!$C$25) -> 90920 | K20: =in_loc!K$22*(in_loc!K$25*in_gen!$C$24+in_loc!K$26*in_gen!$C$25) -> 454600 | L20: =in_loc!L$22*(in_loc!L$25*in_gen!$C$24+in_loc!L$26*in_gen!$C$25) -> 208650 | M20: =in_loc!M$22*(in_loc!M$25*in_gen!$E$24+in_loc!M$26*in_gen!$E$25) -> 154138.4 | N20: =in_loc!N$22*(in_loc!N$25*in_gen!$E$24+in_loc!N$26*in_gen!$E$25) -> 770692 | O20: =in_loc!O$22*(in_loc!O$25*in_gen!$E$24+in_loc!O$26*in_gen!$E$25) -> 221083.2 | P20: =in_loc!P$22*(in_loc!P$25*in_gen!$E$24+in_loc!P$26*in_gen!$E$25) -> 56638.4 | Q20: =in_loc!Q$22*(in_loc!Q$25*in_gen!$E$24+in_loc!Q$26*in_gen!$E$25) -> 283192 | R20: =in_loc!R$22*(in_loc!R$25*in_gen!$E$24+in_loc!R$26*in_gen!$E$25) -> 129469.6 | S20: =in_loc!S$22*(in_loc!S$25*in_gen!$E$24+in_loc!S$26*in_gen!$E$25) -> 94556.8 | T20: =in_loc!T$22*(in_loc!T$25*in_gen!$E$24+in_loc!T$26*in_gen!$E$25) -> 472784 | U20: =in_loc!U$22*(in_loc!U$25*in_gen!$E$24+in_loc!U$26*in_gen!$E$25) -> 216996 | V20: =in_loc!V$22*(in_loc!V$25*in_gen!$F$24+in_loc!V$26*in_gen!$F$25) -> 142281.6 | W20: =in_loc!W$22*(in_loc!W$25*in_gen!$F$24+in_loc!W$26*in_gen!$F$25) -> 711408 | X20: =in_loc!X$22*(in_loc!X$25*in_gen!$F$24+in_loc!X$26*in_gen!$F$25) -> 204076.8 | Y20: =in_loc!Y$22*(in_loc!Y$25*in_gen!$F$24+in_loc!Y$26*in_gen!$F$25) -> 52281.6 | Z20: =in_loc!Z$22*(in_loc!Z$25*in_gen!$F$24+in_loc!Z$26*in_gen!$F$25) -> 261408 | AA20: =in_loc!AA$22*(in_loc!AA$25*in_gen!$F$24+in_loc!AA$26*in_gen!$F$25) -> 119510.4 | AB20: =in_loc!AB$22*(in_loc!AB$25*in_gen!$F$24+in_loc!AB$26*in_gen!$F$25) -> 87283.2 | AC20: =in_loc!AC$22*(in_loc!AC$25*in_gen!$F$24+in_loc!AC$26*in_gen!$F$25) -> 436416 | AD20: =in_loc!AD$22*(in_loc!AD$25*in_gen!$F$24+in_loc!AD$26*in_gen!$F$25) -> 200304
A21: total_cost_installation | B21: € | D21: =in_loc!D$22*(in_loc!D$3+in_loc!D$4+in_loc!D$5+in_loc!D$6+in_loc!D$7+in_loc!D$8) -> 1874000 | E21: =in_loc!E$22*(in_loc!E$3+in_loc!E$4+in_loc!E$5+in_loc!E$6+in_loc!E$7+in_loc!E$8) -> 8108000 | F21: =in_loc!F$22*(in_loc!F$3+in_loc!F$4+in_loc!F$5+in_loc!F$6+in_loc!F$7+in_loc!F$8) -> 5607000 | G21: =in_loc!G$22*(in_loc!G$3+in_loc!G$4+in_loc!G$5+in_loc!G$6+in_loc!G$7+in_loc!G$8) -> 681000 | H21: =in_loc!H$22*(in_loc!H$3+in_loc!H$4+in_loc!H$5+in_loc!H$6+in_loc!H$7+in_loc!H$8) -> 3204000 | I21: =in_loc!I$22*(in_loc!I$3+in_loc!I$4+in_loc!I$5+in_loc!I$6+in_loc!I$7+in_loc!I$8) -> 2017000 | J21: =in_loc!J$22*(in_loc!J$3+in_loc!J$4+in_loc!J$5+in_loc!J$6+in_loc!J$7+in_loc!J$8) -> 584000 | K21: =in_loc!K$22*(in_loc!K$3+in_loc!K$4+in_loc!K$5+in_loc!K$6+in_loc!K$7+in_loc!K$8) -> 2706000 | ... AD21: =in_loc!AD$22*(in_loc!AD$3+in_loc!AD$4+in_loc!AD$5+in_loc!AD$6+in_loc!AD$7+in_loc!AD$8) -> 1559040
A23: total_capex_cost | B23: € | C23: Short cable alternative | D23: =D$13+D$14+D$15+D$16+D$17+D$18+D$20+D$21 -> 3895514.9 | E23: =E$13+E$14+E$15+E$16+E$17+E$18+E$20+E$21 -> 18215574 | F23: =F$13+F$14+F$15+F$16+F$17+F$18+F$20+F$21 -> 13368498 | G23: =G$13+G$14+G$15+G$16+G$17+G$18+G$20+G$21 -> 2610396.9 | H23: =H$13+H$14+H$15+H$16+H$17+H$18+H$20+H$21 -> 12850985 | I23: =I$13+I$14+I$15+I$16+I$17+I$18+I$20+I$21 -> 9697751.9 | J23: =J$13+J$14+J$15+J$16+J$17+J$18+J$20+J$21 -> 2561106.1 | K23: =K$13+K$14+K$15+K$16+K$17+K$18+K$20+K$21 -> 12591531 | ... AD23: =AD$13+AD$14+AD$15+AD$16+AD$17+AD$18+AD$20+AD$21 -> 9001158.4
A24: total_solar_production | B24: kWh | C24: Production at year 0 summed over lifetime, discounted yearly for discount rate and degradation | D24: {=in_loc!D$22 * D$9 * SUM(in_loc!D$42 * (1 - in_loc!D$39) * (1 + in_gen!$C$43) * (1 - in_loc!D$38 * _xlfn.SEQUENCE(1, in_gen!$C$51, 0, 1)) * (1 - in_gen!$C$42) ^ _xlfn.SEQUENCE(1, in_gen!$C$51, 0, 1))} -> 21732543 | E24: {=in_loc!E$22 * E$9 * SUM(in_loc!E$42 * (1 - in_loc!E$39) * (1 + in_gen!$C$43) * (1 - in_loc!E$38 * _xlfn.SEQUENCE(1, in_gen!$C$51, 0, 1)) * (1 - in_gen!$C$42) ^ _xlfn.SEQUENCE(1, in_gen!$C$51, 0, 1))} -> 1.0866271e+08 | F24: {=in_loc!F$22 * F$9 * SUM(in_loc!F$42 * (1 - in_loc!F$39) * (1 + in_gen!$C$43) * (1 - in_loc!F$38 * _xlfn.SEQUENCE(1, in_gen!$C$51, 0, 1)) * (1 - in_gen!$C$42) ^ _xlfn.SEQUENCE(1, in_gen!$C$51, 0, 1))} -> 99425073 | G24: {=in_loc!G$22 * G$9 * SUM(in_loc!G$42 * (1 - in_loc!G$39) * (1 + in_gen!$C$43) * (1 - in_loc!G$38 * _xlfn.SEQUENCE(1, in_gen!$C$51, 0, 1)) * (1 - in_gen!$C$42) ^ _xlfn.SEQUENCE(1, in_gen!$C$51, 0, 1))} -> 22942217 | H24: {=in_loc!H$22 * H$9 * SUM(in_loc!H$42 * (1 - in_loc!H$39) * (1 + in_gen!$C$43) * (1 - in_loc!H$38 * _xlfn.SEQUENCE(1, in_gen!$C$51, 0, 1)) * (1 - in_gen!$C$42) ^ _xlfn.SEQUENCE(1, in_gen!$C$51, 0, 1))} -> 1.1471109e+08 | I24: {=in_loc!I$22 * I$9 * SUM(in_loc!I$42 * (1 - in_loc!I$39) * (1 + in_gen!$C$43) * (1 - in_loc!I$38 * _xlfn.SEQUENCE(1, in_gen!$C$51, 0, 1)) * (1 - in_gen!$C$42) ^ _xlfn.SEQUENCE(1, in_gen!$C$51, 0, 1))} -> 1.0576501e+08 | J24: {=in_loc!J$22 * J$9 * SUM(in_loc!J$42 * (1 - in_loc!J$39) * (1 + in_gen!$C$43) * (1 - in_loc!J$38 * _xlfn.SEQUENCE(1, in_gen!$C$51, 0, 1)) * (1 - in_gen!$C$42) ^ _xlfn.SEQUENCE(1, in_gen!$C$51, 0, 1))} -> 32725846 | K24: {=in_loc!K$22 * K$9 * SUM(in_loc!K$42 * (1 - in_loc!K$39) * (1 + in_gen!$C$43) * (1 - in_loc!K$38 * _xlfn.SEQUENCE(1, in_gen!$C$51, 0, 1)) * (1 - in_gen!$C$42) ^ _xlfn.SEQUENCE(1, in_gen!$C$51, 0, 1))} -> 1.6362923e+08 | L24: {=in_loc!L$22 * L$9 * SUM(in_loc!L$42 * (1 - in_loc!L$39) * (1 + in_gen!$C$43) * (1 - in_loc!L$38 * _xlfn.SEQUENCE(1, in_gen!$C$51, 0, 1)) * (1 - in_gen!$C$42) ^ _xlfn.SEQUENCE(1, in_gen!$C$51, 0, 1))} -> 1.5123301e+08 | M24: {=in_loc!M$22 * M$9 * SUM(in_loc!M$42 * (1 - in_loc!M$39) * (1 + in_gen!$C$43) * (1 - in_loc!M$38 * _xlfn.SEQUENCE(1, in_gen!$E$51, 0, 1)) * (1 - in_gen!$E$42) ^ _xlfn.SEQUENCE(1, in_gen!$E$51, 0, 1))} -> 20052430 | N24: {=in_loc!N$22 * N$9 * SUM(in_loc!N$42 * (1 - in_loc!N$39) * (1 + in_gen!$C$43) * (1 - in_loc!N$38 * _xlfn.SEQUENCE(1, in_gen!$E$51, 0, 1)) * (1 - in_gen!$E$42) ^ _xlfn.SEQUENCE(1, in_gen!$E$51, 0, 1))} -> 1.0026215e+08 | O24: {=in_loc!O$22 * O$9 * SUM(in_loc!O$42 * (1 - in_loc!O$39) * (1 + in_gen!$C$43) * (1 - in_loc!O$38 * _xlfn.SEQUENCE(1, in_gen!$E$51, 0, 1)) * (1 - in_gen!$E$42) ^ _xlfn.SEQUENCE(1, in_gen!$E$51, 0, 1))} -> 91723739 | P24: {=in_loc!P$22 * P$9 * SUM(in_loc!P$42 * (1 - in_loc!P$39) * (1 + in_gen!$C$43) * (1 - in_loc!P$38 * _xlfn.SEQUENCE(1, in_gen!$E$51, 0, 1)) * (1 - in_gen!$E$42) ^ _xlfn.SEQUENCE(1, in_gen!$E$51, 0, 1))} -> 21173702 | Q24: {=in_loc!Q$22 * Q$9 * SUM(in_loc!Q$42 * (1 - in_loc!Q$39) * (1 + in_gen!$C$43) * (1 - in_loc!Q$38 * _xlfn.SEQUENCE(1, in_gen!$E$51, 0, 1)) * (1 - in_gen!$E$42) ^ _xlfn.SEQUENCE(1, in_gen!$E$51, 0, 1))} -> 1.0586851e+08 | R24: {=in_loc!R$22 * R$9 * SUM(in_loc!R$42 * (1 - in_loc!R$39) * (1 + in_gen!$C$43) * (1 - in_loc!R$38 * _xlfn.SEQUENCE(1, in_gen!$E$51, 0, 1)) * (1 - in_gen!$E$42) ^ _xlfn.SEQUENCE(1, in_gen!$E$51, 0, 1))} -> 97604214 | S24: {=in_loc!S$22 * S$9 * SUM(in_loc!S$42 * (1 - in_loc!S$39) * (1 + in_gen!$C$43) * (1 - in_loc!S$38 * _xlfn.SEQUENCE(1, in_gen!$E$51, 0, 1)) * (1 - in_gen!$E$42) ^ _xlfn.SEQUENCE(1, in_gen!$E$51, 0, 1))} -> 30207203 | T24: {=in_loc!T$22 * T$9 * SUM(in_loc!T$42 * (1 - in_loc!T$39) * (1 + in_gen!$C$43) * (1 - in_loc!T$38 * _xlfn.SEQUENCE(1, in_gen!$E$51, 0, 1)) * (1 - in_gen!$E$42) ^ _xlfn.SEQUENCE(1, in_gen!$E$51, 0, 1))} -> 1.5103602e+08 | U24: {=in_loc!U$22 * U$9 * SUM(in_loc!U$42 * (1 - in_loc!U$39) * (1 + in_gen!$C$43) * (1 - in_loc!U$38 * _xlfn.SEQUENCE(1, in_gen!$E$51, 0, 1)) * (1 - in_gen!$E$42) ^ _xlfn.SEQUENCE(1, in_gen!$E$51, 0, 1))} -> 1.3958627e+08 | V24: {=in_loc!V$22 * V$9 * SUM(in_loc!V$42 * (1 - in_loc!V$39) * (1 + in_gen!$F$43) * (1 - in_loc!V$38 * _xlfn.SEQUENCE(1, in_gen!$F$51, 0, 1)) * (1 - in_gen!$F$42) ^ _xlfn.SEQUENCE(1, in_gen!$F$51, 0, 1))} -> 23604065 | W24: {=in_loc!W$22 * W$9 * SUM(in_loc!W$42 * (1 - in_loc!W$39) * (1 + in_gen!$F$43) * (1 - in_loc!W$38 * _xlfn.SEQUENCE(1, in_gen!$F$51, 0, 1)) * (1 - in_gen!$F$42) ^ _xlfn.SEQUENCE(1, in_gen!$F$51, 0, 1))} -> 1.1802032e+08 | X24: {=in_loc!X$22 * X$9 * SUM(in_loc!X$42 * (1 - in_loc!X$39) * (1 + in_gen!$F$43) * (1 - in_loc!X$38 * _xlfn.SEQUENCE(1, in_gen!$F$51, 0, 1)) * (1 - in_gen!$F$42) ^ _xlfn.SEQUENCE(1, in_gen!$F$51, 0, 1))} -> 1.0800681e+08 | Y24: {=in_loc!Y$22 * Y$9 * SUM(in_loc!Y$42 * (1 - in_loc!Y$39) * (1 + in_gen!$F$43) * (1 - in_loc!Y$38 * _xlfn.SEQUENCE(1, in_gen!$F$51, 0, 1)) * (1 - in_gen!$F$42) ^ _xlfn.SEQUENCE(1, in_gen!$F$51, 0, 1))} -> 24911190 | Z24: {=in_loc!Z$22 * Z$9 * SUM(in_loc!Z$42 * (1 - in_loc!Z$39) * (1 + in_gen!$F$43) * (1 - in_loc!Z$38 * _xlfn.SEQUENCE(1, in_gen!$F$51, 0, 1)) * (1 - in_gen!$F$42) ^ _xlfn.SEQUENCE(1, in_gen!$F$51, 0, 1))} -> 1.2455595e+08 | AA24: {=in_loc!AA$22 * AA$9 * SUM(in_loc!AA$42 * (1 - in_loc!AA$39) * (1 + in_gen!$F$43) * (1 - in_loc!AA$38 * _xlfn.SEQUENCE(1, in_gen!$F$51, 0, 1)) * (1 - in_gen!$F$42) ^ _xlfn.SEQUENCE(1, in_gen!$F$51, 0, 1))} -> 1.1485237e+08 | AB24: {=in_loc!AB$22 * AB$9 * SUM(in_loc!AB$42 * (1 - in_loc!AB$39) * (1 + in_gen!$F$43) * (1 - in_loc!AB$38 * _xlfn.SEQUENCE(1, in_gen!$F$51, 0, 1)) * (1 - in_gen!$F$42) ^ _xlfn.SEQUENCE(1, in_gen!$F$51, 0, 1))} -> 35529163 | AC24: {=in_loc!AC$22 * AC$9 * SUM(in_loc!AC$42 * (1 - in_loc!AC$39) * (1 + in_gen!$F$43) * (1 - in_loc!AC$38 * _xlfn.SEQUENCE(1, in_gen!$F$51, 0, 1)) * (1 - in_gen!$F$42) ^ _xlfn.SEQUENCE(1, in_gen!$F$51, 0, 1))} -> 1.7764582e+08 | AD24: {=in_loc!AD$22 * AD$9 * SUM(in_loc!AD$42 * (1 - in_loc!AD$39) * (1 + in_gen!$F$43) * (1 - in_loc!AD$38 * _xlfn.SEQUENCE(1, in_gen!$F$51, 0, 1)) * (1 - in_gen!$F$42) ^ _xlfn.SEQUENCE(1, in_gen!$F$51, 0, 1))} -> 1.6419765e+08
A25: total_solar_maintenance_cost | B25: € | C25: Total cost of maintenance, discounted | D25: {=in_loc!D$22 * D$9 * SUM(in_loc!D$16 * (1 - in_gen!$C$42) ^ _xlfn.SEQUENCE(1, in_gen!$C$51, 0, 1))} -> 468559.58 | E25: {=in_loc!E$22 * E$9 * SUM(in_loc!E$16 * (1 - in_gen!$C$42) ^ _xlfn.SEQUENCE(1, in_gen!$C$51, 0, 1))} -> 2342797.9 | F25: {=in_loc!F$22 * F$9 * SUM(in_loc!F$16 * (1 - in_gen!$C$42) ^ _xlfn.SEQUENCE(1, in_gen!$C$51, 0, 1))} -> 1632149.2 | G25: {=in_loc!G$22 * G$9 * SUM(in_loc!G$16 * (1 - in_gen!$C$42) ^ _xlfn.SEQUENCE(1, in_gen!$C$51, 0, 1))} -> 374847.66 | H25: {=in_loc!H$22 * H$9 * SUM(in_loc!H$16 * (1 - in_gen!$C$42) ^ _xlfn.SEQUENCE(1, in_gen!$C$51, 0, 1))} -> 1874238.3 | I25: {=in_loc!I$22 * I$9 * SUM(in_loc!I$16 * (1 - in_gen!$C$42) ^ _xlfn.SEQUENCE(1, in_gen!$C$51, 0, 1))} -> 1305719.4 | J25: {=in_loc!J$22 * J$9 * SUM(in_loc!J$16 * (1 - in_gen!$C$42) ^ _xlfn.SEQUENCE(1, in_gen!$C$51, 0, 1))} -> 234279.79 | K25: {=in_loc!K$22 * K$9 * SUM(in_loc!K$16 * (1 - in_gen!$C$42) ^ _xlfn.SEQUENCE(1, in_gen!$C$51, 0, 1))} -> 1171399 | L25: {=in_loc!L$22 * L$9 * SUM(in_loc!L$16 * (1 - in_gen!$C$42) ^ _xlfn.SEQUENCE(1, in_gen!$C$51, 0, 1))} -> 816074.6 | M25: {=in_loc!M$22 * M$9 * SUM(in_loc!M$16 * (1 - in_gen!$E$42) ^ _xlfn.SEQUENCE(1, in_gen!$E$51, 0, 1))} -> 468588.96 | N25: {=in_loc!N$22 * N$9 * SUM(in_loc!N$16 * (1 - in_gen!$E$42) ^ _xlfn.SEQUENCE(1, in_gen!$E$51, 0, 1))} -> 2342944.8 | O25: {=in_loc!O$22 * O$9 * SUM(in_loc!O$16 * (1 - in_gen!$E$42) ^ _xlfn.SEQUENCE(1, in_gen!$E$51, 0, 1))} -> 1632251.5 | P25: {=in_loc!P$22 * P$9 * SUM(in_loc!P$16 * (1 - in_gen!$E$42) ^ _xlfn.SEQUENCE(1, in_gen!$E$51, 0, 1))} -> 374871.17 | Q25: {=in_loc!Q$22 * Q$9 * SUM(in_loc!Q$16 * (1 - in_gen!$E$42) ^ _xlfn.SEQUENCE(1, in_gen!$E$51, 0, 1))} -> 1874355.8 | R25: {=in_loc!R$22 * R$9 * SUM(in_loc!R$16 * (1 - in_gen!$E$42) ^ _xlfn.SEQUENCE(1, in_gen!$E$51, 0, 1))} -> 1305801.2 | S25: {=in_loc!S$22 * S$9 * SUM(in_loc!S$16 * (1 - in_gen!$E$42) ^ _xlfn.SEQUENCE(1, in_gen!$E$51, 0, 1))} -> 234294.48 | T25: {=in_loc!T$22 * T$9 * SUM(in_loc!T$16 * (1 - in_gen!$E$42) ^ _xlfn.SEQUENCE(1, in_gen!$E$51, 0, 1))} -> 1171472.4 | U25: {=in_loc!U$22 * U$9 * SUM(in_loc!U$16 * (1 - in_gen!$E$42) ^ _xlfn.SEQUENCE(1, in_gen!$E$51, 0, 1))} -> 816125.77 | V25: {=in_loc!V$22 * V$9 * SUM(in_loc!V$16 * (1 - in_gen!$F$42) ^ _xlfn.SEQUENCE(1, in_gen!$F$51, 0, 1))} -> 468124.32 | W25: {=in_loc!W$22 * W$9 * SUM(in_loc!W$16 * (1 - in_gen!$F$42) ^ _xlfn.SEQUENCE(1, in_gen!$F$51, 0, 1))} -> 2340621.6 | X25: {=in_loc!X$22 * X$9 * SUM(in_loc!X$16 * (1 - in_gen!$F$42) ^ _xlfn.SEQUENCE(1, in_gen!$F$51, 0, 1))} -> 1630633.1 | Y25: {=in_loc!Y$22 * Y$9 * SUM(in_loc!Y$16 * (1 - in_gen!$F$42) ^ _xlfn.SEQUENCE(1, in_gen!$F$51, 0, 1))} -> 374499.46 | Z25: {=in_loc!Z$22 * Z$9 * SUM(in_loc!Z$16 * (1 - in_gen!$F$42) ^ _xlfn.SEQUENCE(1, in_gen!$F$51, 0, 1))} -> 1872497.3 | AA25: {=in_loc!AA$22 * AA$9 * SUM(in_loc!AA$16 * (1 - in_gen!$F$42) ^ _xlfn.SEQUENCE(1, in_gen!$F$51, 0, 1))} -> 1304506.4 | AB25: {=in_loc!AB$22 * AB$9 * SUM(in_loc!AB$16 * (1 - in_gen!$F$42) ^ _xlfn.SEQUENCE(1, in_gen!$F$51, 0, 1))} -> 234062.16 | AC25: {=in_loc!AC$22 * AC$9 * SUM(in_loc!AC$16 * (1 - in_gen!$F$42) ^ _xlfn.SEQUENCE(1, in_gen!$F$51, 0, 1))} -> 1170310.8 | AD25: {=in_loc!AD$22 * AD$9 * SUM(in_loc!AD$16 * (1 - in_gen!$F$42) ^ _xlfn.SEQUENCE(1, in_gen!$F$51, 0, 1))} -> 815316.53
A26: lcoe | B26: €/kWh | C26: all lifetime costs divided by total lifetime production, considering discount rate | D26: =(D$23+D$25+D29)/(D$24+D28) -> 0.1846168 | E26: =(E$23+E$25+E29)/(E$24+E28) -> 0.17405196 | F26: =(F$23+F$25+F29)/(F$24+F28) -> 0.13872828 | G26: =(G$23+G$25+G29)/(G$24+G28) -> 0.11984226 | H26: =(H$23+H$25+H29)/(H$24+H28) -> 0.11824831 | I26: =(I$23+I$25+I29)/(I$24+I28) -> 0.095754475 | J26: =(J$23+J$25+J29)/(J$24+J28) -> 0.078349116 | K26: =(K$23+K$25+K29)/(K$24+K28) -> 0.077159417 | ... AD26: =(AD$23+AD$25+AD29)/(AD$24+AD28) -> 0.054837797
A27: total_solar_reinstall_cost | B27: € | C27: Installing only the solar one time after 25 year. Discounted by discount rate. | D27: {=IFERROR((D$17 + in_loc!D$12 + in_loc!D$13 + in_loc!D$14) * (1 - in_gen!$C$42) * (1 - in_gen!$C$42) ^ _xlfn.SEQUENCE(1, in_gen!$C$30 - 1, in_gen!$C$51, in_gen!$C$51), 0)} -> 190447.12 | E27: {=IFERROR((E$17 + in_loc!E$12 + in_loc!E$13 + in_loc!E$14) * (1 - in_gen!$C$42) * (1 - in_gen!$C$42) ^ _xlfn.SEQUENCE(1, in_gen!$C$30 - 1, in_gen!$C$51, in_gen!$C$51), 0)} -> 613682.8 | F27: {=IFERROR((F$17 + in_loc!F$12 + in_loc!F$13 + in_loc!F$14) * (1 - in_gen!$C$42) * (1 - in_gen!$C$42) ^ _xlfn.SEQUENCE(1, in_gen!$C$30 - 1, in_gen!$C$51, in_gen!$C$51), 0)} -> 809629.14 | G27: {=IFERROR((G$17 + in_loc!G$12 + in_loc!G$13 + in_loc!G$14) * (1 - in_gen!$C$42) * (1 - in_gen!$C$42) ^ _xlfn.SEQUENCE(1, in_gen!$C$30 - 1, in_gen!$C$51, in_gen!$C$51), 0)} -> 142485.31 | H27: {=IFERROR((H$17 + in_loc!H$12 + in_loc!H$13 + in_loc!H$14) * (1 - in_gen!$C$42) * (1 - in_gen!$C$42) ^ _xlfn.SEQUENCE(1, in_gen!$C$30 - 1, in_gen!$C$51, in_gen!$C$51), 0)} -> 582125.31 | I27: {=IFERROR((I$17 + in_loc!I$12 + in_loc!I$13 + in_loc!I$14) * (1 - in_gen!$C$42) * (1 - in_gen!$C$42) ^ _xlfn.SEQUENCE(1, in_gen!$C$30 - 1, in_gen!$C$51, in_gen!$C$51), 0)} -> 660083.61 | J27: {=IFERROR((J$17 + in_loc!J$12 + in_loc!J$13 + in_loc!J$14) * (1 - in_gen!$C$42) * (1 - in_gen!$C$42) ^ _xlfn.SEQUENCE(1, in_gen!$C$30 - 1, in_gen!$C$51, in_gen!$C$51), 0)} -> 137718.92 | K27: {=IFERROR((K$17 + in_loc!K$12 + in_loc!K$13 + in_loc!K$14) * (1 - in_gen!$C$42) * (1 - in_gen!$C$42) ^ _xlfn.SEQUENCE(1, in_gen!$C$30 - 1, in_gen!$C$51, in_gen!$C$51), 0)} -> 578272.48 | L27: {=IFERROR((L$17 + in_loc!L$12 + in_loc!L$13 + in_loc!L$14) * (1 - in_gen!$C$42) * (1 - in_gen!$C$42) ^ _xlfn.SEQUENCE(1, in_gen!$C$30 - 1, in_gen!$C$51, in_gen!$C$51), 0)} -> 636350.96 | M27: {=IFERROR((M$17 + in_loc!M$12 + in_loc!M$13 + in_loc!M$14) * (1 - in_gen!$E$42) * (1 - in_gen!$E$42) ^ _xlfn.SEQUENCE(1, in_gen!$E$30 - 1, in_gen!$E$51, in_gen!$E$51), 0)} -> 187035.19 | N27: {=IFERROR((N$17 + in_loc!N$12 + in_loc!N$13 + in_loc!N$14) * (1 - in_gen!$E$42) * (1 - in_gen!$E$42) ^ _xlfn.SEQUENCE(1, in_gen!$E$30 - 1, in_gen!$E$51, in_gen!$E$51), 0)} -> 584570.08 | O27: {=IFERROR((O$17 + in_loc!O$12 + in_loc!O$13 + in_loc!O$14) * (1 - in_gen!$E$42) * (1 - in_gen!$E$42) ^ _xlfn.SEQUENCE(1, in_gen!$E$30 - 1, in_gen!$E$51, in_gen!$E$51), 0)} -> 791116.36 | P27: {=IFERROR((P$17 + in_loc!P$12 + in_loc!P$13 + in_loc!P$14) * (1 - in_gen!$E$42) * (1 - in_gen!$E$42) ^ _xlfn.SEQUENCE(1, in_gen!$E$30 - 1, in_gen!$E$51, in_gen!$E$51), 0)} -> 137365.86 | Q27: {=IFERROR((Q$17 + in_loc!Q$12 + in_loc!Q$13 + in_loc!Q$14) * (1 - in_gen!$E$42) * (1 - in_gen!$E$42) ^ _xlfn.SEQUENCE(1, in_gen!$E$30 - 1, in_gen!$E$51, in_gen!$E$51), 0)} -> 551889.09 | R27: {=IFERROR((R$17 + in_loc!R$12 + in_loc!R$13 + in_loc!R$14) * (1 - in_gen!$E$42) * (1 - in_gen!$E$42) ^ _xlfn.SEQUENCE(1, in_gen!$E$30 - 1, in_gen!$E$51, in_gen!$E$51), 0)} -> 636246.74 | S27: {=IFERROR((S$17 + in_loc!S$12 + in_loc!S$13 + in_loc!S$14) * (1 - in_gen!$E$42) * (1 - in_gen!$E$42) ^ _xlfn.SEQUENCE(1, in_gen!$E$30 - 1, in_gen!$E$51, in_gen!$E$51), 0)} -> 132429.77 | T27: {=IFERROR((T$17 + in_loc!T$12 + in_loc!T$13 + in_loc!T$14) * (1 - in_gen!$E$42) * (1 - in_gen!$E$42) ^ _xlfn.SEQUENCE(1, in_gen!$E$30 - 1, in_gen!$E$51, in_gen!$E$51), 0)} -> 547899.09 | U27: {=IFERROR((U$17 + in_loc!U$12 + in_loc!U$13 + in_loc!U$14) * (1 - in_gen!$E$42) * (1 - in_gen!$E$42) ^ _xlfn.SEQUENCE(1, in_gen!$E$30 - 1, in_gen!$E$51, in_gen!$E$51), 0)} -> 611669.16 | V27: {=IFERROR((V$17 + in_loc!V$12 + in_loc!V$13 + in_loc!V$14) * (1 - in_gen!$F$42) * (1 - in_gen!$F$42) ^ _xlfn.SEQUENCE(1, in_gen!$F$30 - 1, in_gen!$F$51, in_gen!$F$51), 0)} -> 183530.56 | W27: {=IFERROR((W$17 + in_loc!W$12 + in_loc!W$13 + in_loc!W$14) * (1 - in_gen!$F$42) * (1 - in_gen!$F$42) ^ _xlfn.SEQUENCE(1, in_gen!$F$30 - 1, in_gen!$F$51, in_gen!$F$51), 0)} -> 588945.16 | X27: {=IFERROR((X$17 + in_loc!X$12 + in_loc!X$13 + in_loc!X$14) * (1 - in_gen!$F$42) * (1 - in_gen!$F$42) ^ _xlfn.SEQUENCE(1, in_gen!$F$30 - 1, in_gen!$F$51, in_gen!$F$51), 0)} -> 779683.44 | Y27: {=IFERROR((Y$17 + in_loc!Y$12 + in_loc!Y$13 + in_loc!Y$14) * (1 - in_gen!$F$42) * (1 - in_gen!$F$42) ^ _xlfn.SEQUENCE(1, in_gen!$F$30 - 1, in_gen!$F$51, in_gen!$F$51), 0)} -> 136963.48 | Z27: {=IFERROR((Z$17 + in_loc!Z$12 + in_loc!Z$13 + in_loc!Z$14) * (1 - in_gen!$F$42) * (1 - in_gen!$F$42) ^ _xlfn.SEQUENCE(1, in_gen!$F$30 - 1, in_gen!$F$51, in_gen!$F$51), 0)} -> 558305.37 | AA27: {=IFERROR((AA$17 + in_loc!AA$12 + in_loc!AA$13 + in_loc!AA$14) * (1 - in_gen!$F$42) * (1 - in_gen!$F$42) ^ _xlfn.SEQUENCE(1, in_gen!$F$30 - 1, in_gen!$F$51, in_gen!$F$51), 0)} -> 634486.71 | AB27: {=IFERROR((AB$17 + in_loc!AB$12 + in_loc!AB$13 + in_loc!AB$14) * (1 - in_gen!$F$42) * (1 - in_gen!$F$42) ^ _xlfn.SEQUENCE(1, in_gen!$F$30 - 1, in_gen!$F$51, in_gen!$F$51), 0)} -> 132335.7 | AC27: {=IFERROR((AC$17 + in_loc!AC$12 + in_loc!AC$13 + in_loc!AC$14) * (1 - in_gen!$F$42) * (1 - in_gen!$F$42) ^ _xlfn.SEQUENCE(1, in_gen!$F$30 - 1, in_gen!$F$51, in_gen!$F$51), 0)} -> 554564.58 | AD27: {=IFERROR((AD$17 + in_loc!AD$12 + in_loc!AD$13 + in_loc!AD$14) * (1 - in_gen!$F$42) * (1 - in_gen!$F$42) ^ _xlfn.SEQUENCE(1, in_gen!$F$30 - 1, in_gen!$F$51, in_gen!$F$51), 0)} -> 611444.2
A28: total_solar_reinstall_production | B28: kWh | C28: Aggregated discounted production at reinstall intervals | D28: {=IFERROR((D$24) * (1 - in_gen!$C$42) * (1 - in_gen!$C$42) ^ _xlfn.SEQUENCE(1, in_gen!$C$30 - 1, in_gen!$C$51, in_gen!$C$51), 0)} -> 2158037.5 | E28: {=IFERROR((E$24) * (1 - in_gen!$C$42) * (1 - in_gen!$C$42) ^ _xlfn.SEQUENCE(1, in_gen!$C$30 - 1, in_gen!$C$51, in_gen!$C$51), 0)} -> 10790187 | F28: {=IFERROR((F$24) * (1 - in_gen!$C$42) * (1 - in_gen!$C$42) ^ _xlfn.SEQUENCE(1, in_gen!$C$30 - 1, in_gen!$C$51, in_gen!$C$51), 0)} -> 9872891.5 | G28: {=IFERROR((G$24) * (1 - in_gen!$C$42) * (1 - in_gen!$C$42) ^ _xlfn.SEQUENCE(1, in_gen!$C$30 - 1, in_gen!$C$51, in_gen!$C$51), 0)} -> 2278158 | H28: {=IFERROR((H$24) * (1 - in_gen!$C$42) * (1 - in_gen!$C$42) ^ _xlfn.SEQUENCE(1, in_gen!$C$30 - 1, in_gen!$C$51, in_gen!$C$51), 0)} -> 11390790 | I28: {=IFERROR((I$24) * (1 - in_gen!$C$42) * (1 - in_gen!$C$42) ^ _xlfn.SEQUENCE(1, in_gen!$C$30 - 1, in_gen!$C$51, in_gen!$C$51), 0)} -> 10502446 | J28: {=IFERROR((J$24) * (1 - in_gen!$C$42) * (1 - in_gen!$C$42) ^ _xlfn.SEQUENCE(1, in_gen!$C$30 - 1, in_gen!$C$51, in_gen!$C$51), 0)} -> 3249670.5 | K28: {=IFERROR((K$24) * (1 - in_gen!$C$42) * (1 - in_gen!$C$42) ^ _xlfn.SEQUENCE(1, in_gen!$C$30 - 1, in_gen!$C$51, in_gen!$C$51), 0)} -> 16248352 | L28: {=IFERROR((L$24) * (1 - in_gen!$C$42) * (1 - in_gen!$C$42) ^ _xlfn.SEQUENCE(1, in_gen!$C$30 - 1, in_gen!$C$51, in_gen!$C$51), 0)} -> 15017410 | M28: {=IFERROR((M$24) * (1 - in_gen!$E$42) * (1 - in_gen!$E$42) ^ _xlfn.SEQUENCE(1, in_gen!$E$30 - 1, in_gen!$E$51, in_gen!$E$51), 0)} -> 1982781.8 | N28: {=IFERROR((N$24) * (1 - in_gen!$E$42) * (1 - in_gen!$E$42) ^ _xlfn.SEQUENCE(1, in_gen!$E$30 - 1, in_gen!$E$51, in_gen!$E$51), 0)} -> 9913909 | O28: {=IFERROR((O$24) * (1 - in_gen!$E$42) * (1 - in_gen!$E$42) ^ _xlfn.SEQUENCE(1, in_gen!$E$30 - 1, in_gen!$E$51, in_gen!$E$51), 0)} -> 9069631.9 | P28: {=IFERROR((P$24) * (1 - in_gen!$E$42) * (1 - in_gen!$E$42) ^ _xlfn.SEQUENCE(1, in_gen!$E$30 - 1, in_gen!$E$51, in_gen!$E$51), 0)} -> 2093653 | Q28: {=IFERROR((Q$24) * (1 - in_gen!$E$42) * (1 - in_gen!$E$42) ^ _xlfn.SEQUENCE(1, in_gen!$E$30 - 1, in_gen!$E$51, in_gen!$E$51), 0)} -> 10468265 | R28: {=IFERROR((R$24) * (1 - in_gen!$E$42) * (1 - in_gen!$E$42) ^ _xlfn.SEQUENCE(1, in_gen!$E$30 - 1, in_gen!$E$51, in_gen!$E$51), 0)} -> 9651092.6 | S28: {=IFERROR((S$24) * (1 - in_gen!$E$42) * (1 - in_gen!$E$42) ^ _xlfn.SEQUENCE(1, in_gen!$E$30 - 1, in_gen!$E$51, in_gen!$E$51), 0)} -> 2986884.5 | T28: {=IFERROR((T$24) * (1 - in_gen!$E$42) * (1 - in_gen!$E$42) ^ _xlfn.SEQUENCE(1, in_gen!$E$30 - 1, in_gen!$E$51, in_gen!$E$51), 0)} -> 14934422 | U28: {=IFERROR((U$24) * (1 - in_gen!$E$42) * (1 - in_gen!$E$42) ^ _xlfn.SEQUENCE(1, in_gen!$E$30 - 1, in_gen!$E$51, in_gen!$E$51), 0)} -> 13802273 | V28: {=IFERROR((V$24) * (1 - in_gen!$C$42) * (1 - in_gen!$C$42) ^ _xlfn.SEQUENCE(1, in_gen!$C$30 - 1, in_gen!$C$51, in_gen!$C$51), 0)} -> 2343879.3 | W28: {=IFERROR((W$24) * (1 - in_gen!$C$42) * (1 - in_gen!$C$42) ^ _xlfn.SEQUENCE(1, in_gen!$C$30 - 1, in_gen!$C$51, in_gen!$C$51), 0)} -> 11719396 | X28: {=IFERROR((X$24) * (1 - in_gen!$C$42) * (1 - in_gen!$C$42) ^ _xlfn.SEQUENCE(1, in_gen!$C$30 - 1, in_gen!$C$51, in_gen!$C$51), 0)} -> 10725056 | Y28: {=IFERROR((Y$24) * (1 - in_gen!$C$42) * (1 - in_gen!$C$42) ^ _xlfn.SEQUENCE(1, in_gen!$C$30 - 1, in_gen!$C$51, in_gen!$C$51), 0)} -> 2473676.5 | Z28: {=IFERROR((Z$24) * (1 - in_gen!$C$42) * (1 - in_gen!$C$42) ^ _xlfn.SEQUENCE(1, in_gen!$C$30 - 1, in_gen!$C$51, in_gen!$C$51), 0)} -> 12368383 | AA28: {=IFERROR((AA$24) * (1 - in_gen!$C$42) * (1 - in_gen!$C$42) ^ _xlfn.SEQUENCE(1, in_gen!$C$30 - 1, in_gen!$C$51, in_gen!$C$51), 0)} -> 11404820 | AB28: {=IFERROR((AB$24) * (1 - in_gen!$C$42) * (1 - in_gen!$C$42) ^ _xlfn.SEQUENCE(1, in_gen!$C$30 - 1, in_gen!$C$51, in_gen!$C$51), 0)} -> 3528039.4 | AC28: {=IFERROR((AC$24) * (1 - in_gen!$C$42) * (1 - in_gen!$C$42) ^ _xlfn.SEQUENCE(1, in_gen!$C$30 - 1, in_gen!$C$51, in_gen!$C$51), 0)} -> 17640197 | AD28: {=IFERROR((AD$24) * (1 - in_gen!$C$42) * (1 - in_gen!$C$42) ^ _xlfn.SEQUENCE(1, in_gen!$C$30 - 1, in_gen!$C$51, in_gen!$C$51), 0)} -> 16304797
A29: total_solar_reinstall_maintenance_cost | B29: € | C29: Aggregated discounted maintenance cost at reinstall intervals | D29: {=IFERROR((D$25) * (1 - in_gen!$C$42) * (1 - in_gen!$C$42) ^ _xlfn.SEQUENCE(1, in_gen!$C$30 - 1, in_gen!$C$51, in_gen!$C$51), 0)} -> 46527.88 | E29: {=IFERROR((E$25) * (1 - in_gen!$C$42) * (1 - in_gen!$C$42) ^ _xlfn.SEQUENCE(1, in_gen!$C$30 - 1, in_gen!$C$51, in_gen!$C$51), 0)} -> 232639.4 | F29: {=IFERROR((F$25) * (1 - in_gen!$C$42) * (1 - in_gen!$C$42) ^ _xlfn.SEQUENCE(1, in_gen!$C$30 - 1, in_gen!$C$51, in_gen!$C$51), 0)} -> 162072.12 | G29: {=IFERROR((G$25) * (1 - in_gen!$C$42) * (1 - in_gen!$C$42) ^ _xlfn.SEQUENCE(1, in_gen!$C$30 - 1, in_gen!$C$51, in_gen!$C$51), 0)} -> 37222.304 | H29: {=IFERROR((H$25) * (1 - in_gen!$C$42) * (1 - in_gen!$C$42) ^ _xlfn.SEQUENCE(1, in_gen!$C$30 - 1, in_gen!$C$51, in_gen!$C$51), 0)} -> 186111.52 | I29: {=IFERROR((I$25) * (1 - in_gen!$C$42) * (1 - in_gen!$C$42) ^ _xlfn.SEQUENCE(1, in_gen!$C$30 - 1, in_gen!$C$51, in_gen!$C$51), 0)} -> 129657.69 | J29: {=IFERROR((J$25) * (1 - in_gen!$C$42) * (1 - in_gen!$C$42) ^ _xlfn.SEQUENCE(1, in_gen!$C$30 - 1, in_gen!$C$51, in_gen!$C$51), 0)} -> 23263.94 | K29: {=IFERROR((K$25) * (1 - in_gen!$C$42) * (1 - in_gen!$C$42) ^ _xlfn.SEQUENCE(1, in_gen!$C$30 - 1, in_gen!$C$51, in_gen!$C$51), 0)} -> 116319.7 | L29: {=IFERROR((L$25) * (1 - in_gen!$C$42) * (1 - in_gen!$C$42) ^ _xlfn.SEQUENCE(1, in_gen!$C$30 - 1, in_gen!$C$51, in_gen!$C$51), 0)} -> 81036.058 | M29: {=IFERROR((M$25) * (1 - in_gen!$E$42) * (1 - in_gen!$E$42) ^ _xlfn.SEQUENCE(1, in_gen!$E$30 - 1, in_gen!$E$51, in_gen!$E$51), 0)} -> 46334.018 | N29: {=IFERROR((N$25) * (1 - in_gen!$E$42) * (1 - in_gen!$E$42) ^ _xlfn.SEQUENCE(1, in_gen!$E$30 - 1, in_gen!$E$51, in_gen!$E$51), 0)} -> 231670.09 | O29: {=IFERROR((O$25) * (1 - in_gen!$E$42) * (1 - in_gen!$E$42) ^ _xlfn.SEQUENCE(1, in_gen!$E$30 - 1, in_gen!$E$51, in_gen!$E$51), 0)} -> 161396.83 | P29: {=IFERROR((P$25) * (1 - in_gen!$E$42) * (1 - in_gen!$E$42) ^ _xlfn.SEQUENCE(1, in_gen!$E$30 - 1, in_gen!$E$51, in_gen!$E$51), 0)} -> 37067.215 | Q29: {=IFERROR((Q$25) * (1 - in_gen!$E$42) * (1 - in_gen!$E$42) ^ _xlfn.SEQUENCE(1, in_gen!$E$30 - 1, in_gen!$E$51, in_gen!$E$51), 0)} -> 185336.07 | R29: {=IFERROR((R$25) * (1 - in_gen!$E$42) * (1 - in_gen!$E$42) ^ _xlfn.SEQUENCE(1, in_gen!$E$30 - 1, in_gen!$E$51, in_gen!$E$51), 0)} -> 129117.46 | S29: {=IFERROR((S$25) * (1 - in_gen!$E$42) * (1 - in_gen!$E$42) ^ _xlfn.SEQUENCE(1, in_gen!$E$30 - 1, in_gen!$E$51, in_gen!$E$51), 0)} -> 23167.009 | T29: {=IFERROR((T$25) * (1 - in_gen!$E$42) * (1 - in_gen!$E$42) ^ _xlfn.SEQUENCE(1, in_gen!$E$30 - 1, in_gen!$E$51, in_gen!$E$51), 0)} -> 115835.05 | U29: {=IFERROR((U$25) * (1 - in_gen!$E$42) * (1 - in_gen!$E$42) ^ _xlfn.SEQUENCE(1, in_gen!$E$30 - 1, in_gen!$E$51, in_gen!$E$51), 0)} -> 80698.415 | V29: {=IFERROR((V$25) * (1 - in_gen!$F$42) * (1 - in_gen!$F$42) ^ _xlfn.SEQUENCE(1, in_gen!$F$30 - 1, in_gen!$F$51, in_gen!$F$51), 0)} -> 47013.419 | W29: {=IFERROR((W$25) * (1 - in_gen!$F$42) * (1 - in_gen!$F$42) ^ _xlfn.SEQUENCE(1, in_gen!$F$30 - 1, in_gen!$F$51, in_gen!$F$51), 0)} -> 235067.09 | X29: {=IFERROR((X$25) * (1 - in_gen!$F$42) * (1 - in_gen!$F$42) ^ _xlfn.SEQUENCE(1, in_gen!$F$30 - 1, in_gen!$F$51, in_gen!$F$51), 0)} -> 163763.41 | Y29: {=IFERROR((Y$25) * (1 - in_gen!$F$42) * (1 - in_gen!$F$42) ^ _xlfn.SEQUENCE(1, in_gen!$F$30 - 1, in_gen!$F$51, in_gen!$F$51), 0)} -> 37610.735 | Z29: {=IFERROR((Z$25) * (1 - in_gen!$F$42) * (1 - in_gen!$F$42) ^ _xlfn.SEQUENCE(1, in_gen!$F$30 - 1, in_gen!$F$51, in_gen!$F$51), 0)} -> 188053.67 | AA29: {=IFERROR((AA$25) * (1 - in_gen!$F$42) * (1 - in_gen!$F$42) ^ _xlfn.SEQUENCE(1, in_gen!$F$30 - 1, in_gen!$F$51, in_gen!$F$51), 0)} -> 131010.73 | AB29: {=IFERROR((AB$25) * (1 - in_gen!$F$42) * (1 - in_gen!$F$42) ^ _xlfn.SEQUENCE(1, in_gen!$F$30 - 1, in_gen!$F$51, in_gen!$F$51), 0)} -> 23506.709 | AC29: {=IFERROR((AC$25) * (1 - in_gen!$F$42) * (1 - in_gen!$F$42) ^ _xlfn.SEQUENCE(1, in_gen!$F$30 - 1, in_gen!$F$51, in_gen!$F$51), 0)} -> 117533.55 | AD29: {=IFERROR((AD$25) * (1 - in_gen!$F$42) * (1 - in_gen!$F$42) ^ _xlfn.SEQUENCE(1, in_gen!$F$30 - 1, in_gen!$F$51, in_gen!$F$51), 0)} -> 81881.704
A30: total_revenue | B30: € | C30: Revnue from first and later installations | D30: =in_gen!$C$26*(D$24+D$28) -> 2866869.6 | E30: =in_gen!$C$26*(E$24+E$28) -> 14334348 | F30: =in_gen!$C$26*(F$24+F$28) -> 13115756 | G30: =in_gen!$C$26*(G$24+G$28) -> 3026445.1 | H30: =in_gen!$C$26*(H$24+H$28) -> 15132225 | I30: =in_gen!$C$26*(I$24+I$28) -> 13952094 | J30: =in_gen!$C$26*(J$24+J$28) -> 4317061.9 | K30: =in_gen!$C$26*(K$24+K$28) -> 21585310 | L30: =in_gen!$C$26*(L$24+L$28) -> 19950051 | M30: =in_gen!$E$26*(M$24+M$28) -> 2749994.4 | N30: =in_gen!$E$26*(N$24+N$28) -> 13749972 | O30: =in_gen!$E$26*(O$24+O$28) -> 12579013 | P30: =in_gen!$E$26*(P$24+P$28) -> 2903765.9 | Q30: =in_gen!$E$26*(Q$24+Q$28) -> 14518830 | R30: =in_gen!$E$26*(R$24+R$28) -> 13385462 | S30: =in_gen!$E$26*(S$24+S$28) -> 4142622.1 | T30: =in_gen!$E$26*(T$24+T$28) -> 20713111 | U30: =in_gen!$E$26*(U$24+U$28) -> 19142891 | V30: =in_gen!$F$26*(V$24+V$28) -> 2989203.1 | W30: =in_gen!$F$26*(W$24+W$28) -> 14946016 | X30: =in_gen!$F$26*(X$24+X$28) -> 13677911 | Y30: =in_gen!$F$26*(Y$24+Y$28) -> 3154736.6 | Z30: =in_gen!$F$26*(Z$24+Z$28) -> 15773683 | AA30: =in_gen!$F$26*(AA$24+AA$28) -> 14544829 | AB30: =in_gen!$F$26*(AB$24+AB$28) -> 4499389.8 | AC30: =in_gen!$F$26*(AC$24+AC$28) -> 22496949 | AD30: =in_gen!$F$26*(AD$24+AD$28) -> 20793882
A31: npv | B31: € | C31: Net present value | D31: =D$30-(D$23+D$25+D$27+D$29) -> -1734179.8 | E31: =E$30-(E$23+E$25+E$27+E$29) -> -7070346.4 | F31: =F$30-(F$23+F$25+F$27+F$29) -> -2856592.4 | G31: =G$30-(G$23+G$25+G$27+G$29) -> -138507.13 | H31: =H$30-(H$23+H$25+H$27+H$29) -> -361234.42 | I31: =I$30-(I$23+I$25+I$27+I$29) -> 2158881.8 | J31: =J$30-(J$23+J$25+J$27+J$29) -> 1360693.1 | K31: =K$30-(K$23+K$25+K$27+K$29) -> 7127787.8 | ... AD31: =AD$30-(AD$23+AD$25+AD$27+AD$29) -> 10284081
A32: roi | B32: % | C32: Return on Investment | D32: =D$31/D$23 -> -0.44517346 | E32: =E$31/E$23 -> -0.38814842 | F32: =F$31/F$23 -> -0.21368089 | G32: =G$31/G$23 -> -0.053059796 | H32: =H$31/H$23 -> -0.028109474 | I32: =I$31/I$23 -> 0.22261673 | J32: =J$31/J$23 -> 0.5312912 | K32: =K$31/K$23 -> 0.56607795 | ... AD32: =AD$31/AD$23 -> 1.1425287
A33: payback_period | B33: y | C33: Years to pay back the investment | D33: {=IFERROR(MATCH(TRUE, D$23 <= _xlfn.SCAN(0, in_loc!D$22 * D$9 * (in_gen!$C$26 * in_loc!D$42 * (1 - in_loc!D$39) * (1 + in_gen!$C$43) - in_loc!D$16) * (1 - in_loc!D$38 * _xlfn.SEQUENCE(1, in_gen!$C$51, 0, 1)) * (1 - in_gen!$C$42) ^ _xlfn.SEQUENCE(1, in_gen!$C$51, 0, 1), _xlfn.LAMBDA(_xlpm.a,_xlpm.b, _xlpm.a + _xlpm.b)), 0), "-")} -> - | E33: {=IFERROR(MATCH(TRUE, E$23 <= _xlfn.SCAN(0, in_loc!E$22 * E$9 * (in_gen!$C$26 * in_loc!E$42 * (1 - in_loc!E$39) * (1 + in_gen!$C$43) - in_loc!E$16) * (1 - in_loc!E$38 * _xlfn.SEQUENCE(1, in_gen!$C$51, 0, 1)) * (1 - in_gen!$C$42) ^ _xlfn.SEQUENCE(1, in_gen!$C$51, 0, 1), _xlfn.LAMBDA(_xlpm.a,_xlpm.b, _xlpm.a + _xlpm.b)), 0), "-")} -> - | F33: {=IFERROR(MATCH(TRUE, F$23 <= _xlfn.SCAN(0, in_loc!F$22 * F$9 * (in_gen!$C$26 * in_loc!F$42 * (1 - in_loc!F$39) * (1 + in_gen!$C$43) - in_loc!F$16) * (1 - in_loc!F$38 * _xlfn.SEQUENCE(1, in_gen!$C$51, 0, 1)) * (1 - in_gen!$C$42) ^ _xlfn.SEQUENCE(1, in_gen!$C$51, 0, 1), _xlfn.LAMBDA(_xlpm.a,_xlpm.b, _xlpm.a + _xlpm.b)), 0), "-")} -> - | G33: {=IFERROR(MATCH(TRUE, G$23 <= _xlfn.SCAN(0, in_loc!G$22 * G$9 * (in_gen!$C$26 * in_loc!G$42 * (1 - in_loc!G$39) * (1 + in_gen!$C$43) - in_loc!G$16) * (1 - in_loc!G$38 * _xlfn.SEQUENCE(1, in_gen!$C$51, 0, 1)) * (1 - in_gen!$C$42) ^ _xlfn.SEQUENCE(1, in_gen!$C$51, 0, 1), _xlfn.LAMBDA(_xlpm.a,_xlpm.b, _xlpm.a + _xlpm.b)), 0), "-")} -> - | H33: {=IFERROR(MATCH(TRUE, H$23 <= _xlfn.SCAN(0, in_loc!H$22 * H$9 * (in_gen!$C$26 * in_loc!H$42 * (1 - in_loc!H$39) * (1 + in_gen!$C$43) - in_loc!H$16) * (1 - in_loc!H$38 * _xlfn.SEQUENCE(1, in_gen!$C$51, 0, 1)) * (1 - in_gen!$C$42) ^ _xlfn.SEQUENCE(1, in_gen!$C$51, 0, 1), _xlfn.LAMBDA(_xlpm.a,_xlpm.b, _xlpm.a + _xlpm.b)), 0), "-")} -> - | I33: {=IFERROR(MATCH(TRUE, I$23 <= _xlfn.SCAN(0, in_loc!I$22 * I$9 * (in_gen!$C$26 * in_loc!I$42 * (1 - in_loc!I$39) * (1 + in_gen!$C$43) - in_loc!I$16) * (1 - in_loc!I$38 * _xlfn.SEQUENCE(1, in_gen!$C$51, 0, 1)) * (1 - in_gen!$C$42) ^ _xlfn.SEQUENCE(1, in_gen!$C$51, 0, 1), _xlfn.LAMBDA(_xlpm.a,_xlpm.b, _xlpm.a + _xlpm.b)), 0), "-")} -> 16 | J33: {=IFERROR(MATCH(TRUE, J$23 <= _xlfn.SCAN(0, in_loc!J$22 * J$9 * (in_gen!$C$26 * in_loc!J$42 * (1 - in_loc!J$39) * (1 + in_gen!$C$43) - in_loc!J$16) * (1 - in_loc!J$38 * _xlfn.SEQUENCE(1, in_gen!$C$51, 0, 1)) * (1 - in_gen!$C$42) ^ _xlfn.SEQUENCE(1, in_gen!$C$51, 0, 1), _xlfn.LAMBDA(_xlpm.a,_xlpm.b, _xlpm.a + _xlpm.b)), 0), "-")} -> 11 | K33: {=IFERROR(MATCH(TRUE, K$23 <= _xlfn.SCAN(0, in_loc!K$22 * K$9 * (in_gen!$C$26 * in_loc!K$42 * (1 - in_loc!K$39) * (1 + in_gen!$C$43) - in_loc!K$16) * (1 - in_loc!K$38 * _xlfn.SEQUENCE(1, in_gen!$C$51, 0, 1)) * (1 - in_gen!$C$42) ^ _xlfn.SEQUENCE(1, in_gen!$C$51, 0, 1), _xlfn.LAMBDA(_xlpm.a,_xlpm.b, _xlpm.a + _xlpm.b)), 0), "-")} -> 11 | L33: {=IFERROR(MATCH(TRUE, L$23 <= _xlfn.SCAN(0, in_loc!L$22 * L$9 * (in_gen!$C$26 * in_loc!L$42 * (1 - in_loc!L$39) * (1 + in_gen!$C$43) - in_loc!L$16) * (1 - in_loc!L$38 * _xlfn.SEQUENCE(1, in_gen!$C$51, 0, 1)) * (1 - in_gen!$C$42) ^ _xlfn.SEQUENCE(1, in_gen!$C$51, 0, 1), _xlfn.LAMBDA(_xlpm.a,_xlpm.b, _xlpm.a + _xlpm.b)), 0), "-")} -> 8 | M33: {=IFERROR(MATCH(TRUE, M$23 <= _xlfn.SCAN(0, in_loc!M$22 * M$9 * (in_gen!$E$26 * in_loc!M$42 * (1 - in_loc!M$39) * (1 + in_gen!$E$43) - in_loc!M$16) * (1 - in_loc!M$38 * _xlfn.SEQUENCE(1, in_gen!$E$51, 0, 1)) * (1 - in_gen!$E$42) ^ _xlfn.SEQUENCE(1, in_gen!$E$51, 0, 1), _xlfn.LAMBDA(_xlpm.a,_xlpm.b, _xlpm.a + _xlpm.b)), 0), "-")} -> - | N33: {=IFERROR(MATCH(TRUE, N$23 <= _xlfn.SCAN(0, in_loc!N$22 * N$9 * (in_gen!$E$26 * in_loc!N$42 * (1 - in_loc!N$39) * (1 + in_gen!$E$43) - in_loc!N$16) * (1 - in_loc!N$38 * _xlfn.SEQUENCE(1, in_gen!$E$51, 0, 1)) * (1 - in_gen!$E$42) ^ _xlfn.SEQUENCE(1, in_gen!$E$51, 0, 1), _xlfn.LAMBDA(_xlpm.a,_xlpm.b, _xlpm.a + _xlpm.b)), 0), "-")} -> - | O33: {=IFERROR(MATCH(TRUE, O$23 <= _xlfn.SCAN(0, in_loc!O$22 * O$9 * (in_gen!$E$26 * in_loc!O$42 * (1 - in_loc!O$39) * (1 + in_gen!$E$43) - in_loc!O$16) * (1 - in_loc!O$38 * _xlfn.SEQUENCE(1, in_gen!$E$51, 0, 1)) * (1 - in_gen!$E$42) ^ _xlfn.SEQUENCE(1, in_gen!$E$51, 0, 1), _xlfn.LAMBDA(_xlpm.a,_xlpm.b, _xlpm.a + _xlpm.b)), 0), "-")} -> - | P33: {=IFERROR(MATCH(TRUE, P$23 <= _xlfn.SCAN(0, in_loc!P$22 * P$9 * (in_gen!$E$26 * in_loc!P$42 * (1 - in_loc!P$39) * (1 + in_gen!$E$43) - in_loc!P$16) * (1 - in_loc!P$38 * _xlfn.SEQUENCE(1, in_gen!$E$51, 0, 1)) * (1 - in_gen!$E$42) ^ _xlfn.SEQUENCE(1, in_gen!$E$51, 0, 1), _xlfn.LAMBDA(_xlpm.a,_xlpm.b, _xlpm.a + _xlpm.b)), 0), "-")} -> - | Q33: {=IFERROR(MATCH(TRUE, Q$23 <= _xlfn.SCAN(0, in_loc!Q$22 * Q$9 * (in_gen!$E$26 * in_loc!Q$42 * (1 - in_loc!Q$39) * (1 + in_gen!$E$43) - in_loc!Q$16) * (1 - in_loc!Q$38 * _xlfn.SEQUENCE(1, in_gen!$E$51, 0, 1)) * (1 - in_gen!$E$42) ^ _xlfn.SEQUENCE(1, in_gen!$E$51, 0, 1), _xlfn.LAMBDA(_xlpm.a,_xlpm.b, _xlpm.a + _xlpm.b)), 0), "-")} -> - | R33: {=IFERROR(MATCH(TRUE, R$23 <= _xlfn.SCAN(0, in_loc!R$22 * R$9 * (in_gen!$E$26 * in_loc!R$42 * (1 - in_loc!R$39) * (1 + in_gen!$E$43) - in_loc!R$16) * (1 - in_loc!R$38 * _xlfn.SEQUENCE(1, in_gen!$E$51, 0, 1)) * (1 - in_gen!$E$42) ^ _xlfn.SEQUENCE(1, in_gen!$E$51, 0, 1), _xlfn.LAMBDA(_xlpm.a,_xlpm.b, _xlpm.a + _xlpm.b)), 0), "-")} -> 17 | S33: {=IFERROR(MATCH(TRUE, S$23 <= _xlfn.SCAN(0, in_loc!S$22 * S$9 * (in_gen!$E$26 * in_loc!S$42 * (1 - in_loc!S$39) * (1 + in_gen!$E$43) - in_loc!S$16) * (1 - in_loc!S$38 * _xlfn.SEQUENCE(1, in_gen!$E$51, 0, 1)) * (1 - in_gen!$E$42) ^ _xlfn.SEQUENCE(1, in_gen!$E$51, 0, 1), _xlfn.LAMBDA(_xlpm.a,_xlpm.b, _xlpm.a + _xlpm.b)), 0), "-")} -> 12 | T33: {=IFERROR(MATCH(TRUE, T$23 <= _xlfn.SCAN(0, in_loc!T$22 * T$9 * (in_gen!$E$26 * in_loc!T$42 * (1 - in_loc!T$39) * (1 + in_gen!$E$43) - in_loc!T$16) * (1 - in_loc!T$38 * _xlfn.SEQUENCE(1, in_gen!$E$51, 0, 1)) * (1 - in_gen!$E$42) ^ _xlfn.SEQUENCE(1, in_gen!$E$51, 0, 1), _xlfn.LAMBDA(_xlpm.a,_xlpm.b, _xlpm.a + _xlpm.b)), 0), "-")} -> 11 | U33: {=IFERROR(MATCH(TRUE, U$23 <= _xlfn.SCAN(0, in_loc!U$22 * U$9 * (in_gen!$E$26 * in_loc!U$42 * (1 - in_loc!U$39) * (1 + in_gen!$E$43) - in_loc!U$16) * (1 - in_loc!U$38 * _xlfn.SEQUENCE(1, in_gen!$E$51, 0, 1)) * (1 - in_gen!$E$42) ^ _xlfn.SEQUENCE(1, in_gen!$E$51, 0, 1), _xlfn.LAMBDA(_xlpm.a,_xlpm.b, _xlpm.a + _xlpm.b)), 0), "-")} -> 8 | V33: {=IFERROR(MATCH(TRUE, V$23 <= _xlfn.SCAN(0, in_loc!V$22 * V$9 * (in_gen!$F$26 * in_loc!V$42 * (1 - in_loc!V$39) * (1 + in_gen!$F$43) - in_loc!V$16) * (1 - in_loc!V$38 * _xlfn.SEQUENCE(1, in_gen!$F$51, 0, 1)) * (1 - in_gen!$F$42) ^ _xlfn.SEQUENCE(1, in_gen!$F$51, 0, 1), _xlfn.LAMBDA(_xlpm.a,_xlpm.b, _xlpm.a + _xlpm.b)), 0), "-")} -> - | W33: {=IFERROR(MATCH(TRUE, W$23 <= _xlfn.SCAN(0, in_loc!W$22 * W$9 * (in_gen!$F$26 * in_loc!W$42 * (1 - in_loc!W$39) * (1 + in_gen!$F$43) - in_loc!W$16) * (1 - in_loc!W$38 * _xlfn.SEQUENCE(1, in_gen!$F$51, 0, 1)) * (1 - in_gen!$F$42) ^ _xlfn.SEQUENCE(1, in_gen!$F$51, 0, 1), _xlfn.LAMBDA(_xlpm.a,_xlpm.b, _xlpm.a + _xlpm.b)), 0), "-")} -> - | X33: {=IFERROR(MATCH(TRUE, X$23 <= _xlfn.SCAN(0, in_loc!X$22 * X$9 * (in_gen!$F$26 * in_loc!X$42 * (1 - in_loc!X$39) * (1 + in_gen!$F$43) - in_loc!X$16) * (1 - in_loc!X$38 * _xlfn.SEQUENCE(1, in_gen!$F$51, 0, 1)) * (1 - in_gen!$F$42) ^ _xlfn.SEQUENCE(1, in_gen!$F$51, 0, 1), _xlfn.LAMBDA(_xlpm.a,_xlpm.b, _xlpm.a + _xlpm.b)), 0), "-")} -> - | Y33: {=IFERROR(MATCH(TRUE, Y$23 <= _xlfn.SCAN(0, in_loc!Y$22 * Y$9 * (in_gen!$F$26 * in_loc!Y$42 * (1 - in_loc!Y$39) * (1 + in_gen!$F$43) - in_loc!Y$16) * (1 - in_loc!Y$38 * _xlfn.SEQUENCE(1, in_gen!$F$51, 0, 1)) * (1 - in_gen!$F$42) ^ _xlfn.SEQUENCE(1, in_gen!$F$51, 0, 1), _xlfn.LAMBDA(_xlpm.a,_xlpm.b, _xlpm.a + _xlpm.b)), 0), "-")} -> 26 | Z33: {=IFERROR(MATCH(TRUE, Z$23 <= _xlfn.SCAN(0, in_loc!Z$22 * Z$9 * (in_gen!$F$26 * in_loc!Z$42 * (1 - in_loc!Z$39) * (1 + in_gen!$F$43) - in_loc!Z$16) * (1 - in_loc!Z$38 * _xlfn.SEQUENCE(1, in_gen!$F$51, 0, 1)) * (1 - in_gen!$F$42) ^ _xlfn.SEQUENCE(1, in_gen!$F$51, 0, 1), _xlfn.LAMBDA(_xlpm.a,_xlpm.b, _xlpm.a + _xlpm.b)), 0), "-")} -> 25 | AA33: {=IFERROR(MATCH(TRUE, AA$23 <= _xlfn.SCAN(0, in_loc!AA$22 * AA$9 * (in_gen!$F$26 * in_loc!AA$42 * (1 - in_loc!AA$39) * (1 + in_gen!$F$43) - in_loc!AA$16) * (1 - in_loc!AA$38 * _xlfn.SEQUENCE(1, in_gen!$F$51, 0, 1)) * (1 - in_gen!$F$42) ^ _xlfn.SEQUENCE(1, in_gen!$F$51, 0, 1), _xlfn.LAMBDA(_xlpm.a,_xlpm.b, _xlpm.a + _xlpm.b)), 0), "-")} -> 14 | AB33: {=IFERROR(MATCH(TRUE, AB$23 <= _xlfn.SCAN(0, in_loc!AB$22 * AB$9 * (in_gen!$F$26 * in_loc!AB$42 * (1 - in_loc!AB$39) * (1 + in_gen!$F$43) - in_loc!AB$16) * (1 - in_loc!AB$38 * _xlfn.SEQUENCE(1, in_gen!$F$51, 0, 1)) * (1 - in_gen!$F$42) ^ _xlfn.SEQUENCE(1, in_gen!$F$51, 0, 1), _xlfn.LAMBDA(_xlpm.a,_xlpm.b, _xlpm.a + _xlpm.b)), 0), "-")} -> 10 | AC33: {=IFERROR(MATCH(TRUE, AC$23 <= _xlfn.SCAN(0, in_loc!AC$22 * AC$9 * (in_gen!$F$26 * in_loc!AC$42 * (1 - in_loc!AC$39) * (1 + in_gen!$F$43) - in_loc!AC$16) * (1 - in_loc!AC$38 * _xlfn.SEQUENCE(1, in_gen!$F$51, 0, 1)) * (1 - in_gen!$F$42) ^ _xlfn.SEQUENCE(1, in_gen!$F$51, 0, 1), _xlfn.LAMBDA(_xlpm.a,_xlpm.b, _xlpm.a + _xlpm.b)), 0), "-")} -> 10 | AD33: {=IFERROR(MATCH(TRUE, AD$23 <= _xlfn.SCAN(0, in_loc!AD$22 * AD$9 * (in_gen!$F$26 * in_loc!AD$42 * (1 - in_loc!AD$39) * (1 + in_gen!$F$43) - in_loc!AD$16) * (1 - in_loc!AD$38 * _xlfn.SEQUENCE(1, in_gen!$F$51, 0, 1)) * (1 - in_gen!$F$42) ^ _xlfn.SEQUENCE(1, in_gen!$F$51, 0, 1), _xlfn.LAMBDA(_xlpm.a,_xlpm.b, _xlpm.a + _xlpm.b)), 0), "-")} -> 7
A34: irr | B34: % | C34: Internal rate of return up until but not including the first reinstall | D34: {=IRR(in_loc!D$22 * D$9 * (in_gen!$C$26 * in_loc!D$42 * (1 - in_loc!D$39) * (1 + in_gen!$C$43) - in_loc!D$16) * (1 - in_loc!D$38 * _xlfn.SEQUENCE(1, in_gen!$C$51, 0, 1)) * (1 - in_gen!$C$42) ^ _xlfn.SEQUENCE(1, in_gen!$C$51, 0, 1) - IF(_xlfn.SEQUENCE(1, in_gen!$C$51) = 1, D$23, 0))} -> -0.063591133 | E34: {=IRR(in_loc!E$22 * E$9 * (in_gen!$C$26 * in_loc!E$42 * (1 - in_loc!E$39) * (1 + in_gen!$C$43) - in_loc!E$16) * (1 - in_loc!E$38 * _xlfn.SEQUENCE(1, in_gen!$C$51, 0, 1)) * (1 - in_gen!$C$42) ^ _xlfn.SEQUENCE(1, in_gen!$C$51, 0, 1) - IF(_xlfn.SEQUENCE(1, in_gen!$C$51) = 1, E$23, 0))} -> -0.057564486 | F34: {=IRR(in_loc!F$22 * F$9 * (in_gen!$C$26 * in_loc!F$42 * (1 - in_loc!F$39) * (1 + in_gen!$C$43) - in_loc!F$16) * (1 - in_loc!F$38 * _xlfn.SEQUENCE(1, in_gen!$C$51, 0, 1)) * (1 - in_gen!$C$42) ^ _xlfn.SEQUENCE(1, in_gen!$C$51, 0, 1) - IF(_xlfn.SEQUENCE(1, in_gen!$C$51) = 1, F$23, 0))} -> -0.030717707 | G34: {=IRR(in_loc!G$22 * G$9 * (in_gen!$C$26 * in_loc!G$42 * (1 - in_loc!G$39) * (1 + in_gen!$C$43) - in_loc!G$16) * (1 - in_loc!G$38 * _xlfn.SEQUENCE(1, in_gen!$C$51, 0, 1)) * (1 - in_gen!$C$42) ^ _xlfn.SEQUENCE(1, in_gen!$C$51, 0, 1) - IF(_xlfn.SEQUENCE(1, in_gen!$C$51) = 1, G$23, 0))} -> -0.011461387 | H34: {=IRR(in_loc!H$22 * H$9 * (in_gen!$C$26 * in_loc!H$42 * (1 - in_loc!H$39) * (1 + in_gen!$C$43) - in_loc!H$16) * (1 - in_loc!H$38 * _xlfn.SEQUENCE(1, in_gen!$C$51, 0, 1)) * (1 - in_gen!$C$42) ^ _xlfn.SEQUENCE(1, in_gen!$C$51, 0, 1) - IF(_xlfn.SEQUENCE(1, in_gen!$C$51) = 1, H$23, 0))} -> -0.0095622736 | I34: {=IRR(in_loc!I$22 * I$9 * (in_gen!$C$26 * in_loc!I$42 * (1 - in_loc!I$39) * (1 + in_gen!$C$43) - in_loc!I$16) * (1 - in_loc!I$38 * _xlfn.SEQUENCE(1, in_gen!$C$51, 0, 1)) * (1 - in_gen!$C$42) ^ _xlfn.SEQUENCE(1, in_gen!$C$51, 0, 1) - IF(_xlfn.SEQUENCE(1, in_gen!$C$51) = 1, I$23, 0))} -> 0.022949343 | J34: {=IRR(in_loc!J$22 * J$9 * (in_gen!$C$26 * in_loc!J$42 * (1 - in_loc!J$39) * (1 + in_gen!$C$43) - in_loc!J$16) * (1 - in_loc!J$38 * _xlfn.SEQUENCE(1, in_gen!$C$51, 0, 1)) * (1 - in_gen!$C$42) ^ _xlfn.SEQUENCE(1, in_gen!$C$51, 0, 1) - IF(_xlfn.SEQUENCE(1, in_gen!$C$51) = 1, J$23, 0))} -> 0.056559485 | K34: {=IRR(in_loc!K$22 * K$9 * (in_gen!$C$26 * in_loc!K$42 * (1 - in_loc!K$39) * (1 + in_gen!$C$43) - in_loc!K$16) * (1 - in_loc!K$38 * _xlfn.SEQUENCE(1, in_gen!$C$51, 0, 1)) * (1 - in_gen!$C$42) ^ _xlfn.SEQUENCE(1, in_gen!$C$51, 0, 1) - IF(_xlfn.SEQUENCE(1, in_gen!$C$51) = 1, K$23, 0))} -> 0.059693657 | L34: {=IRR(in_loc!L$22 * L$9 * (in_gen!$C$26 * in_loc!L$42 * (1 - in_loc!L$39) * (1 + in_gen!$C$43) - in_loc!L$16) * (1 - in_loc!L$38 * _xlfn.SEQUENCE(1, in_gen!$C$51, 0, 1)) * (1 - in_gen!$C$42) ^ _xlfn.SEQUENCE(1, in_gen!$C$51, 0, 1) - IF(_xlfn.SEQUENCE(1, in_gen!$C$51) = 1, L$23, 0))} -> 0.10827542 | M34: {=IRR(in_loc!M$22 * M$9 * (in_gen!$E$26 * in_loc!M$42 * (1 - in_loc!M$39) * (1 + in_gen!$E$43) - in_loc!M$16) * (1 - in_loc!M$38 * _xlfn.SEQUENCE(1, in_gen!$E$51, 0, 1)) * (1 - in_gen!$E$42) ^ _xlfn.SEQUENCE(1, in_gen!$E$51, 0, 1) - IF(_xlfn.SEQUENCE(1, in_gen!$E$51) = 1, M$23, 0))} -> -0.07228915 | N34: {=IRR(in_loc!N$22 * N$9 * (in_gen!$E$26 * in_loc!N$42 * (1 - in_loc!N$39) * (1 + in_gen!$E$43) - in_loc!N$16) * (1 - in_loc!N$38 * _xlfn.SEQUENCE(1, in_gen!$E$51, 0, 1)) * (1 - in_gen!$E$42) ^ _xlfn.SEQUENCE(1, in_gen!$E$51, 0, 1) - IF(_xlfn.SEQUENCE(1, in_gen!$E$51) = 1, N$23, 0))} -> -0.066075183 | O34: {=IRR(in_loc!O$22 * O$9 * (in_gen!$E$26 * in_loc!O$42 * (1 - in_loc!O$39) * (1 + in_gen!$E$43) - in_loc!O$16) * (1 - in_loc!O$38 * _xlfn.SEQUENCE(1, in_gen!$E$51, 0, 1)) * (1 - in_gen!$E$42) ^ _xlfn.SEQUENCE(1, in_gen!$E$51, 0, 1) - IF(_xlfn.SEQUENCE(1, in_gen!$E$51) = 1, O$23, 0))} -> -0.038233774 | P34: {=IRR(in_loc!P$22 * P$9 * (in_gen!$E$26 * in_loc!P$42 * (1 - in_loc!P$39) * (1 + in_gen!$E$43) - in_loc!P$16) * (1 - in_loc!P$38 * _xlfn.SEQUENCE(1, in_gen!$E$51, 0, 1)) * (1 - in_gen!$E$42) ^ _xlfn.SEQUENCE(1, in_gen!$E$51, 0, 1) - IF(_xlfn.SEQUENCE(1, in_gen!$E$51) = 1, P$23, 0))} -> -0.018248877 | Q34: {=IRR(in_loc!Q$22 * Q$9 * (in_gen!$E$26 * in_loc!Q$42 * (1 - in_loc!Q$39) * (1 + in_gen!$E$43) - in_loc!Q$16) * (1 - in_loc!Q$38 * _xlfn.SEQUENCE(1, in_gen!$E$51, 0, 1)) * (1 - in_gen!$E$42) ^ _xlfn.SEQUENCE(1, in_gen!$E$51, 0, 1) - IF(_xlfn.SEQUENCE(1, in_gen!$E$51) = 1, Q$23, 0))} -> -0.016264367 | R34: {=IRR(in_loc!R$22 * R$9 * (in_gen!$E$26 * in_loc!R$42 * (1 - in_loc!R$39) * (1 + in_gen!$E$43) - in_loc!R$16) * (1 - in_loc!R$38 * _xlfn.SEQUENCE(1, in_gen!$E$51, 0, 1)) * (1 - in_gen!$E$42) ^ _xlfn.SEQUENCE(1, in_gen!$E$51, 0, 1) - IF(_xlfn.SEQUENCE(1, in_gen!$E$51) = 1, R$23, 0))} -> 0.017858163 | S34: {=IRR(in_loc!S$22 * S$9 * (in_gen!$E$26 * in_loc!S$42 * (1 - in_loc!S$39) * (1 + in_gen!$E$43) - in_loc!S$16) * (1 - in_loc!S$38 * _xlfn.SEQUENCE(1, in_gen!$E$51, 0, 1)) * (1 - in_gen!$E$42) ^ _xlfn.SEQUENCE(1, in_gen!$E$51, 0, 1) - IF(_xlfn.SEQUENCE(1, in_gen!$E$51) = 1, S$23, 0))} -> 0.050678536 | T34: {=IRR(in_loc!T$22 * T$9 * (in_gen!$E$26 * in_loc!T$42 * (1 - in_loc!T$39) * (1 + in_gen!$E$43) - in_loc!T$16) * (1 - in_loc!T$38 * _xlfn.SEQUENCE(1, in_gen!$E$51, 0, 1)) * (1 - in_gen!$E$42) ^ _xlfn.SEQUENCE(1, in_gen!$E$51, 0, 1) - IF(_xlfn.SEQUENCE(1, in_gen!$E$51) = 1, T$23, 0))} -> 0.053941424 | U34: {=IRR(in_loc!U$22 * U$9 * (in_gen!$E$26 * in_loc!U$42 * (1 - in_loc!U$39) * (1 + in_gen!$E$43) - in_loc!U$16) * (1 - in_loc!U$38 * _xlfn.SEQUENCE(1, in_gen!$E$51, 0, 1)) * (1 - in_gen!$E$42) ^ _xlfn.SEQUENCE(1, in_gen!$E$51, 0, 1) - IF(_xlfn.SEQUENCE(1, in_gen!$E$51) = 1, U$23, 0))} -> 0.10478506 | V34: {=IRR(in_loc!V$22 * V$9 * (in_gen!$F$26 * in_loc!V$42 * (1 - in_loc!V$39) * (1 + in_gen!$F$43) - in_loc!V$16) * (1 - in_loc!V$38 * _xlfn.SEQUENCE(1, in_gen!$F$51, 0, 1)) * (1 - in_gen!$F$42) ^ _xlfn.SEQUENCE(1, in_gen!$F$51, 0, 1) - IF(_xlfn.SEQUENCE(1, in_gen!$F$51) = 1, V$23, 0))} -> -0.052745576 | W34: {=IRR(in_loc!W$22 * W$9 * (in_gen!$F$26 * in_loc!W$42 * (1 - in_loc!W$39) * (1 + in_gen!$F$43) - in_loc!W$16) * (1 - in_loc!W$38 * _xlfn.SEQUENCE(1, in_gen!$F$51, 0, 1)) * (1 - in_gen!$F$42) ^ _xlfn.SEQUENCE(1, in_gen!$F$51, 0, 1) - IF(_xlfn.SEQUENCE(1, in_gen!$F$51) = 1, W$23, 0))} -> -0.046601845 | X34: {=IRR(in_loc!X$22 * X$9 * (in_gen!$F$26 * in_loc!X$42 * (1 - in_loc!X$39) * (1 + in_gen!$F$43) - in_loc!X$16) * (1 - in_loc!X$38 * _xlfn.SEQUENCE(1, in_gen!$F$51, 0, 1)) * (1 - in_gen!$F$42) ^ _xlfn.SEQUENCE(1, in_gen!$F$51, 0, 1) - IF(_xlfn.SEQUENCE(1, in_gen!$F$51) = 1, X$23, 0))} -> -0.019229051 | Y34: {=IRR(in_loc!Y$22 * Y$9 * (in_gen!$F$26 * in_loc!Y$42 * (1 - in_loc!Y$39) * (1 + in_gen!$F$43) - in_loc!Y$16) * (1 - in_loc!Y$38 * _xlfn.SEQUENCE(1, in_gen!$F$51, 0, 1)) * (1 - in_gen!$F$42) ^ _xlfn.SEQUENCE(1, in_gen!$F$51, 0, 1) - IF(_xlfn.SEQUENCE(1, in_gen!$F$51) = 1, Y$23, 0))} -> 0.00041424725 | Z34: {=IRR(in_loc!Z$22 * Z$9 * (in_gen!$F$26 * in_loc!Z$42 * (1 - in_loc!Z$39) * (1 + in_gen!$F$43) - in_loc!Z$16) * (1 - in_loc!Z$38 * _xlfn.SEQUENCE(1, in_gen!$F$51, 0, 1)) * (1 - in_gen!$F$42) ^ _xlfn.SEQUENCE(1, in_gen!$F$51, 0, 1) - IF(_xlfn.SEQUENCE(1, in_gen!$F$51) = 1, Z$23, 0))} -> 0.0023874909 | AA34: {=IRR(in_loc!AA$22 * AA$9 * (in_gen!$F$26 * in_loc!AA$42 * (1 - in_loc!AA$39) * (1 + in_gen!$F$43) - in_loc!AA$16) * (1 - in_loc!AA$38 * _xlfn.SEQUENCE(1, in_gen!$F$51, 0, 1)) * (1 - in_gen!$F$42) ^ _xlfn.SEQUENCE(1, in_gen!$F$51, 0, 1) - IF(_xlfn.SEQUENCE(1, in_gen!$F$51) = 1, AA$23, 0))} -> 0.036194228 | AB34: {=IRR(in_loc!AB$22 * AB$9 * (in_gen!$F$26 * in_loc!AB$42 * (1 - in_loc!AB$39) * (1 + in_gen!$F$43) - in_loc!AB$16) * (1 - in_loc!AB$38 * _xlfn.SEQUENCE(1, in_gen!$F$51, 0, 1)) * (1 - in_gen!$F$42) ^ _xlfn.SEQUENCE(1, in_gen!$F$51, 0, 1) - IF(_xlfn.SEQUENCE(1, in_gen!$F$51) = 1, AB$23, 0))} -> 0.070680658 | AC34: {=IRR(in_loc!AC$22 * AC$9 * (in_gen!$F$26 * in_loc!AC$42 * (1 - in_loc!AC$39) * (1 + in_gen!$F$43) - in_loc!AC$16) * (1 - in_loc!AC$38 * _xlfn.SEQUENCE(1, in_gen!$F$51, 0, 1)) * (1 - in_gen!$F$42) ^ _xlfn.SEQUENCE(1, in_gen!$F$51, 0, 1) - IF(_xlfn.SEQUENCE(1, in_gen!$F$51) = 1, AC$23, 0))} -> 0.074001075 | AD34: {=IRR(in_loc!AD$22 * AD$9 * (in_gen!$F$26 * in_loc!AD$42 * (1 - in_loc!AD$39) * (1 + in_gen!$F$43) - in_loc!AD$16) * (1 - in_loc!AD$38 * _xlfn.SEQUENCE(1, in_gen!$F$51, 0, 1)) * (1 - in_gen!$F$42) ^ _xlfn.SEQUENCE(1, in_gen!$F$51, 0, 1) - IF(_xlfn.SEQUENCE(1, in_gen!$F$51) = 1, AD$23, 0))} -> 0.12580191

Sheet pontoons
A1: Pontoon full data | G1: Costs | I1: Counts | L1: Aggregated costs | P1: Minimum costs | U1: Location total costs | Z1: Location total costs
A2: Design | B2: Installation | C2: Pontoon | D2: Material | E2: Total Weight | F2: Total Cost (€) | G2: Material | H2: Cost (€/t) | I2: =B2 -> Installation | J2: =C2 -> Pontoon | K2: Count | L2: =A2 -> Design | M2: =B2 -> Installation | N2: =C2 -> Pontoon | O2: =F2 -> Total Cost (€) | P2: =A2 -> Design | Q2: =B2 -> Installation | R2: =C2 -> Pontoon | S2: =F2 -> Total Cost (€) | T2: =K2 -> Count | U2: Component | V2: Installation | W2: Weight | X2: Cost/ton (€) | Y2: Total cost (€) | Z2: Location | AA2: Total Costs (€)
A3: O0 Conv Ref | B3: 10MW | C3: Breakwater | D3: CC | E3: 6107.7 | F3: =VLOOKUP($D3,$G$3:$H$8,2,FALSE)*$E3 -> 610770 | G3: LWAC | H3: 150 | I3: 10MW | J3: Bridge1968 | K3: 17 | L3: {=_xlfn.UNIQUE(A3:C1031)} -> O0 Conv Ref | M3: 10MW | N3: Breakwater | O3: =SUMIFS($F$3:$F1031,$A$3:$A1031,$L3,$B$3:$B1031,$M3,$C$3:C1031,$N3) -> 1221594 | P3: {=_xlfn.MAP(Q3:Q1019, R3:R1019, S3:S1019, _xlfn.LAMBDA(_xlpm.inst,_xlpm.pont,_xlpm.cost, INDEX(L3:L1019, MATCH(1, (M3:M1019 = _xlpm.inst) * (N3:N1019 = _xlpm.pont) * (O3:O1019 = _xlpm.cost), 0))))} -> O0 Conv Ref | Q3: {=_xlfn.UNIQUE(_xlfn._xlws.FILTER(M3:N1019, (M3:M1019 <> "") * (N3:N1019 <> "")))} -> 10MW | R3: Breakwater | S3: {=_xlfn.MAP(Q3:Q1019, R3:R1019, _xlfn.LAMBDA(_xlpm.inst,_xlpm.pont, _xlfn.MINIFS(O3:O1019, M3:M1019, _xlpm.inst, N3:N1019, _xlpm.pont)))} -> 1221594 | T3: {=_xlfn._xlws.FILTER($K$3:$K1019, ($I$3:$I1019 = $Q3) * ($J$3:$J1019 = $R3))} -> 56 | U3: Structural Steel | V3: 10MW | W3: 214.9 | X3: 600 | Y3: =W3*X3 -> 128940 | Z3: {=TRANSPOSE(in_loc!D1:AD1)} -> n_2 | AA3: =AA4/5 -> 678095.6
A4: O0 Conv Ref | B4: 10MW | C4: Breakwater | D4: EPS | E4: 195.1 | F4: =VLOOKUP($D4,$G$3:$H$8,2,FALSE)*$E4 -> 214610 | G4: EPS | H4: 1100 | I4: 10MW | J4: Bridge1830 | K4: 18 | L4: O0 Conv Ref | M4: 10MW | N4: Bridge1968 | O4: =SUMIFS($F$3:$F1032,$A$3:$A1032,$L4,$B$3:$B1032,$M4,$C$3:C1032,$N4) -> 379588 | P4: O0 Conv Ref | Q4: 10MW | R4: Bridge1968 | S4: 379588 | T4: {=_xlfn._xlws.FILTER($K$3:$K1019, ($I$3:$I1019 = $Q4) * ($J$3:$J1019 = $R4))} -> 17 | U4: Structural Steel | V4: 2MW_5 | W4: 472.5 | X4: 600 | Y4: =W4*X4 -> 283500 | Z4: n_25 | AA4: =IFERROR(__xludf.UNSUPPORTED("SUMPRODUCT({FILTER($S$3:$S1019,$Q$3:$Q1019=""2MW_5""),FILTER($T$3:$T1019,$Q$3:$Q1019=""2MW_5"")})+SUM(FILTER($Y$3:$Y1019,$V$3:$V1019=""2MW_5""))"),3390478) -> 3390478
A5: O0 Conv Ref | B5: 10MW | C5: Breakwater | D5: Reinforcement | E5: 404.3 | F5: =VLOOKUP($D5,$G$3:$H$8,2,FALSE)*$E5 -> 396214 | G5: Reinforcement | H5: 980 | I5: 10MW | J5: Breakwater | K5: 56 | L5: O0 Conv Ref | M5: 10MW | N5: Bridge1830 | O5: =SUMIFS($F$3:$F1033,$A$3:$A1033,$L5,$B$3:$B1033,$M5,$C$3:C1033,$N5) -> 375926 | P5: O0 Conv Ref | Q5: 10MW | R5: Bridge1830 | S5: 375926 | T5: {=_xlfn._xlws.FILTER($K$3:$K1019, ($I$3:$I1019 = $Q5) * ($J$3:$J1019 = $R5))} -> 18 | U5: Rubber | V5: 10MW | W5: 31.9 | X5: 400 | Y5: =W5*X5 -> 12760 | Z5: n_10 | AA5: =IFERROR(__xludf.UNSUPPORTED("SUMPRODUCT({FILTER($S$3:$S1019,$Q$3:$Q1019=""10MW""),FILTER($T$3:$T1019,$Q$3:$Q1019=""10MW"")})+SUM(FILTER($Y$3:$Y1019,$V$3:$V1019=""10MW""))"),2118899) -> 2118899
A6: O0 Conv Ref | B6: 10MW | C6: Bridge1968 | D6: CC | E6: 1900.5 | F6: =VLOOKUP($D6,$G$3:$H$8,2,FALSE)*$E6 -> 190050 | G6: CCLC | H6: 110 | I6: 2MW_5 | J6: Breakwater | K6: 32 | L6: O0 Conv Ref | M6: 2MW_5 | N6: Breakwater | O6: =SUMIFS($F$3:$F1034,$A$3:$A1034,$L6,$B$3:$B1034,$M6,$C$3:C1034,$N6) -> 3084546 | P6: O0 Conv Ref | Q6: 2MW_5 | R6: Breakwater | S6: 3084546 | T6: {=_xlfn._xlws.FILTER($K$3:$K1019, ($I$3:$I1019 = $Q6) * ($J$3:$J1019 = $R6))} -> 32 | U6: Rubber | V6: 2MW_5 | W6: 56 | X6: 400 | Y6: =W6*X6 -> 22400 | Z6: b_2 | AA6: =AA3 -> 678095.6
A7: O0 Conv Ref | B7: 10MW | C7: Bridge1968 | D7: EPS | E7: 61.3 | F7: =VLOOKUP($D7,$G$3:$H$8,2,FALSE)*$E7 -> 67430 | G7: HPC | H7: 275 | L7: O1 Conv LWAC | M7: 10MW | N7: Breakwater | O7: =SUMIFS($F$3:$F1035,$A$3:$A1035,$L7,$B$3:$B1035,$M7,$C$3:C1035,$N7) -> 1341740 | P7: 0 | Q7: 0 | R7: 0 | S7: 0 | Z7: b_25 | AA7: =AA4 -> 3390478
A8: O0 Conv Ref | B8: 10MW | C8: Bridge1968 | D8: Reinforcement | E8: 124.6 | F8: =VLOOKUP($D8,$G$3:$H$8,2,FALSE)*$E8 -> 122108 | G8: CC | H8: 100 | L8: O1 Conv LWAC | M8: 10MW | N8: Bridge1968 | O8: =SUMIFS($F$3:$F1036,$A$3:$A1036,$L8,$B$3:$B1036,$M8,$C$3:C1036,$N8) -> 416937 | P8: 0 | S8: 0 | Z8: b_10 | AA8: =AA5 -> 2118899
A9: O0 Conv Ref | B9: 10MW | C9: Bridge1830 | D9: CC | E9: 1882.1 | F9: =VLOOKUP($D9,$G$3:$H$8,2,FALSE)*$E9 -> 188210 | L9: O1 Conv LWAC | M9: 10MW | N9: Bridge1830 | O9: =SUMIFS($F$3:$F1042,$A$3:$A1042,$L9,$B$3:$B1042,$M9,$C$3:C1042,$N9) -> 412266 | P9: 0 | S9: 0 | Z9: m_2 | AA9: =AA6 -> 678095.6
A10: O0 Conv Ref | B10: 10MW | C10: Bridge1830 | D10: EPS | E10: 60 | F10: =VLOOKUP($D10,$G$3:$H$8,2,FALSE)*$E10 -> 66000 | L10: O1 Conv LWAC | M10: 2MW_5 | N10: Breakwater | O10: =SUMIFS($F$3:$F1043,$A$3:$A1043,$L10,$B$3:$B1043,$M10,$C$3:C1043,$N10) -> 3390913 | P10: 0 | S10: 0 | Z10: m_25 | AA10: =AA7 -> 3390478
A11: O0 Conv Ref | B11: 10MW | C11: Bridge1830 | D11: Reinforcement | E11: 124.2 | F11: =VLOOKUP($D11,$G$3:$H$8,2,FALSE)*$E11 -> 121716 | L11: O2 Hybrid | M11: 10MW | N11: Breakwater | O11: =SUMIFS($F$3:$F1044,$A$3:$A1044,$L11,$B$3:$B1044,$M11,$C$3:C1044,$N11) -> 1403286 | P11: 0 | S11: 0 | Z11: m_10 | AA11: =AA8 -> 2118899
A12: O0 Conv Ref | B12: 2MW_5 | C12: Breakwater | D12: CC | E12: 15520.4 | F12: =VLOOKUP($D12,$G$3:$H$8,2,FALSE)*$E12 -> 1552040 | L12: O2 Hybrid | M12: 10MW | N12: Bridge1968 | O12: =SUMIFS($F$3:$F1045,$A$3:$A1045,$L12,$B$3:$B1045,$M12,$C$3:C1045,$N12) -> 435233 | P12: 0 | S12: 0 | Z12: n_2_pes | AA12: =AA3*(1+in_gen!$C$44) -> 705219.42
A13: O0 Conv Ref | B13: 2MW_5 | C13: Breakwater | D13: EPS | E13: 492.3 | F13: =VLOOKUP($D13,$G$3:$H$8,2,FALSE)*$E13 -> 541530 | L13: O2 Hybrid | M13: 10MW | N13: Bridge1830 | O13: =SUMIFS($F$3:$F1046,$A$3:$A1046,$L13,$B$3:$B1046,$M13,$C$3:C1046,$N13) -> 433686 | P13: 0 | S13: 0 | Z13: n_25_pes | AA13: =AA4*(1+in_gen!$C$44) -> 3526097.1
A14: O0 Conv Ref | B14: 2MW_5 | C14: Breakwater | D14: Reinforcement | E14: 1011.2 | F14: =VLOOKUP($D14,$G$3:$H$8,2,FALSE)*$E14 -> 990976 | L14: O2 Hybrid | M14: 2MW_5 | N14: Breakwater | O14: =SUMIFS($F$3:$F1047,$A$3:$A1047,$L14,$B$3:$B1047,$M14,$C$3:C1047,$N14) -> 3481663 | P14: 0 | S14: 0 | Z14: n_10_pes | AA14: =AA5*(1+in_gen!$C$44) -> 2203655
A15: O1 Conv LWAC | B15: 10MW | C15: Breakwater | D15: LWAC | E15: 5119.2 | F15: =VLOOKUP($D15,$G$3:$H$8,2,FALSE)*$E15 -> 767880 | L15: O3 Sure LWAC | M15: 10MW | N15: Breakwater | O15: =SUMIFS($F$3:$F1048,$A$3:$A1048,$L15,$B$3:$B1048,$M15,$C$3:C1048,$N15) -> 1513384 | P15: 0 | S15: 0 | Z15: b_2_pes | AA15: =AA6*(1+in_gen!$C$44) -> 705219.42
A16: O1 Conv LWAC | B16: 10MW | C16: Breakwater | D16: EPS | E16: 168 | F16: =VLOOKUP($D16,$G$3:$H$8,2,FALSE)*$E16 -> 184800 | L16: O3 Sure LWAC | M16: 10MW | N16: Bridge1968 | O16: =SUMIFS($F$3:$F1049,$A$3:$A1049,$L16,$B$3:$B1049,$M16,$C$3:C1049,$N16) -> 468718 | P16: 0 | S16: 0 | T16: {=_xlfn._xlws.FILTER($K$3:$K1019, ($I$3:$I1019 = $Q16) * ($J$3:$J1019 = $R16))} -> 0 | Z16: b_25_pes | AA16: =AA7*(1+in_gen!$C$44) -> 3526097.1
A17: O1 Conv LWAC | B17: 10MW | C17: Breakwater | D17: Reinforcement | E17: 397 | F17: =VLOOKUP($D17,$G$3:$H$8,2,FALSE)*$E17 -> 389060 | L17: O3 Sure LWAC | M17: 10MW | N17: Bridge1830 | O17: =SUMIFS($F$3:$F1050,$A$3:$A1050,$L17,$B$3:$B1050,$M17,$C$3:C1050,$N17) -> 470903 | P17: 0 | S17: 0 | T17: 0 | Z17: b_10_pes | AA17: =AA8*(1+in_gen!$C$44) -> 2203655
A18: O1 Conv LWAC | B18: 10MW | C18: Bridge1968 | D18: LWAC | E18: 1592.7 | F18: =VLOOKUP($D18,$G$3:$H$8,2,FALSE)*$E18 -> 238905 | L18: O3 Sure LWAC | M18: 2MW_5 | N18: Breakwater | O18: =SUMIFS($F$3:$F1051,$A$3:$A1051,$L18,$B$3:$B1051,$M18,$C$3:C1051,$N18) -> 3823934 | P18: 0 | S18: 0 | T18: 0 | Z18: m_2_pes | AA18: =AA9*(1+in_gen!$C$44) -> 705219.42
A19: O1 Conv LWAC | B19: 10MW | C19: Bridge1968 | D19: EPS | E19: 52.8 | F19: =VLOOKUP($D19,$G$3:$H$8,2,FALSE)*$E19 -> 58080 | L19: O4 Sure HPC | M19: 10MW | N19: Breakwater | O19: =SUMIFS($F$3:$F1052,$A$3:$A1052,$L19,$B$3:$B1052,$M19,$C$3:C1052,$N19) -> 2146101.5 | P19: 0 | S19: 0 | T19: 0 | Z19: m_25_pes | AA19: =AA10*(1+in_gen!$C$44) -> 3526097.1
A20: O1 Conv LWAC | B20: 10MW | C20: Bridge1968 | D20: Reinforcement | E20: 122.4 | F20: =VLOOKUP($D20,$G$3:$H$8,2,FALSE)*$E20 -> 119952 | L20: O4 Sure HPC | M20: 10MW | N20: Bridge1968 | O20: =SUMIFS($F$3:$F1053,$A$3:$A1053,$L20,$B$3:$B1053,$M20,$C$3:C1053,$N20) -> 670110 | P20: 0 | S20: 0 | T20: 0 | Z20: m_10_pes | AA20: =AA11*(1+in_gen!$C$44) -> 2203655
A21: O1 Conv LWAC | B21: 10MW | C21: Bridge1830 | D21: LWAC | E21: 1574.2 | F21: =VLOOKUP($D21,$G$3:$H$8,2,FALSE)*$E21 -> 236130 | L21: O4 Sure HPC | M21: 10MW | N21: Bridge1830 | O21: =SUMIFS($F$3:$F1054,$A$3:$A1054,$L21,$B$3:$B1054,$M21,$C$3:C1054,$N21) -> 678486 | P21: 0 | S21: 0 | T21: 0 | Z21: n_2_opt | AA21: =AA3*(1-in_gen!$C$44) -> 650971.78
A22: O1 Conv LWAC | B22: 10MW | C22: Bridge1830 | D22: EPS | E22: 51.7 | F22: =VLOOKUP($D22,$G$3:$H$8,2,FALSE)*$E22 -> 56870 | L22: O4 Sure HPC | M22: 2MW_5 | N22: Breakwater | O22: =SUMIFS($F$3:$F1055,$A$3:$A1055,$L22,$B$3:$B1055,$M22,$C$3:C1055,$N22) -> 5477516 | P22: 0 | S22: 0 | T22: 0 | Z22: n_25_opt | AA22: =AA4*(1-in_gen!$C$44) -> 3254858.9
A23: O1 Conv LWAC | B23: 10MW | C23: Bridge1830 | D23: Reinforcement | E23: 121.7 | F23: =VLOOKUP($D23,$G$3:$H$8,2,FALSE)*$E23 -> 119266 | L23: 0 | M23: 0 | N23: 0 | P23: 0 | S23: 0 | T23: 0 | Z23: n_10_opt | AA23: =AA5*(1-in_gen!$C$44) -> 2034143
A24: O1 Conv LWAC | B24: 2MW_5 | C24: Breakwater | D24: LWAC | E24: 13004.5 | F24: =VLOOKUP($D24,$G$3:$H$8,2,FALSE)*$E24 -> 1950675 | P24: 0 | S24: 0 | T24: 0 | Z24: b_2_opt | AA24: =AA6*(1-in_gen!$C$44) -> 650971.78
A25: O1 Conv LWAC | B25: 2MW_5 | C25: Breakwater | D25: EPS | E25: 424.1 | F25: =VLOOKUP($D25,$G$3:$H$8,2,FALSE)*$E25 -> 466510 | P25: 0 | S25: 0 | T25: 0 | Z25: b_25_opt | AA25: =AA7*(1-in_gen!$C$44) -> 3254858.9
A26: O1 Conv LWAC | B26: 2MW_5 | C26: Breakwater | D26: Reinforcement | E26: 993.6 | F26: =VLOOKUP($D26,$G$3:$H$8,2,FALSE)*$E26 -> 973728 | P26: 0 | S26: 0 | T26: 0 | Z26: b_10_opt | AA26: =AA8*(1-in_gen!$C$44) -> 2034143
A27: O2 Hybrid | B27: 10MW | C27: Breakwater | D27: LWAC | E27: 5160.8 | F27: =VLOOKUP($D27,$G$3:$H$8,2,FALSE)*$E27 -> 774120 | P27: 0 | S27: 0 | T27: 0 | Z27: m_2_opt | AA27: =AA9*(1-in_gen!$C$44) -> 650971.78
A28: O2 Hybrid | B28: 10MW | C28: Breakwater | D28: CCLC | E28: 929.4 | F28: =VLOOKUP($D28,$G$3:$H$8,2,FALSE)*$E28 -> 102234 | P28: 0 | S28: 0 | T28: 0 | Z28: m_25_opt | AA28: =AA10*(1-in_gen!$C$44) -> 3254858.9
A29: O2 Hybrid | B29: 10MW | C29: Breakwater | D29: EPS | E29: 118.3 | F29: =VLOOKUP($D29,$G$3:$H$8,2,FALSE)*$E29 -> 130130 | P29: 0 | S29: 0 | T29: 0 | Z29: m_10_opt | AA29: =AA11*(1-in_gen!$C$44) -> 2034143
A30: O2 Hybrid | B30: 10MW | C30: Breakwater | D30: Reinforcement | E30: 404.9 | F30: =VLOOKUP($D30,$G$3:$H$8,2,FALSE)*$E30 -> 396802 | P30: 0 | S30: 0 | T30: 0
A31: O2 Hybrid | B31: 10MW | C31: Bridge1968 | D31: LWAC | E31: 1599.6 | F31: =VLOOKUP($D31,$G$3:$H$8,2,FALSE)*$E31 -> 239940 | P31: 0 | S31: 0 | T31: 0
A32: O2 Hybrid | B32: 10MW | C32: Bridge1968 | D32: CCLC | E32: 308.1 | F32: =VLOOKUP($D32,$G$3:$H$8,2,FALSE)*$E32 -> 33891 | P32: 0 | S32: 0 | T32: 0
A33: O2 Hybrid | B33: 10MW | C33: Bridge1968 | D33: EPS | E33: 35.9 | F33: =VLOOKUP($D33,$G$3:$H$8,2,FALSE)*$E33 -> 39490 | P33: 0 | S33: 0 | T33: 0
A34: O2 Hybrid | B34: 10MW | C34: Bridge1968 | D34: Reinforcement | E34: 124.4 | F34: =VLOOKUP($D34,$G$3:$H$8,2,FALSE)*$E34 -> 121912 | P34: 0 | S34: 0 | T34: 0
A35: O2 Hybrid | B35: 10MW | C35: Bridge1830 | D35: LWAC | E35: 1611.1 | F35: =VLOOKUP($D35,$G$3:$H$8,2,FALSE)*$E35 -> 241665 | P35: 0 | S35: 0 | T35: 0
A36: O2 Hybrid | B36: 10MW | C36: Bridge1830 | D36: CCLC | E36: 263.7 | F36: =VLOOKUP($D36,$G$3:$H$8,2,FALSE)*$E36 -> 29007 | P36: 0 | S36: 0 | T36: 0
A37: O2 Hybrid | B37: 10MW | C37: Bridge1830 | D37: EPS | E37: 37.9 | F37: =VLOOKUP($D37,$G$3:$H$8,2,FALSE)*$E37 -> 41690 | P37: 0 | S37: 0 | T37: 0
A38: O2 Hybrid | B38: 10MW | C38: Bridge1830 | D38: Reinforcement | E38: 123.8 | F38: =VLOOKUP($D38,$G$3:$H$8,2,FALSE)*$E38 -> 121324 | P38: 0 | S38: 0 | T38: 0
A39: O2 Hybrid | B39: 2MW_5 | C39: Breakwater | D39: LWAC | E39: 12872.8 | F39: =VLOOKUP($D39,$G$3:$H$8,2,FALSE)*$E39 -> 1930920 | P39: 0 | S39: 0 | T39: 0
A40: O2 Hybrid | B40: 2MW_5 | C40: Breakwater | D40: CCLC | E40: 2025.3 | F40: =VLOOKUP($D40,$G$3:$H$8,2,FALSE)*$E40 -> 222783 | P40: 0 | S40: 0 | T40: 0
A41: O2 Hybrid | B41: 2MW_5 | C41: Breakwater | D41: EPS | E41: 309.2 | F41: =VLOOKUP($D41,$G$3:$H$8,2,FALSE)*$E41 -> 340120 | P41: 0 | S41: 0 | T41: 0
... A66: O4 Sure HPC | B66: 2MW_5 | C66: Breakwater | D66: Reinforcement | E66: 1056 | F66: =VLOOKUP($D66,$G$3:$H$8,2,FALSE)*$E66 -> 1034880 | P66: 0 | S66: 0 | T66: 0
P67: 0 | S67: 0 | T67: 0
P68: 0 | S68: 0 | T68: 0
M69: {=_xlfn.UNIQUE(A3:A1036)} -> O0 Conv Ref | P69: 0 | S69: 0 | T69: 0
M70: O1 Conv LWAC | P70: 0 | S70: 0 | T70: 0
M71: O2 Hybrid | P71: 0 | S71: 0 | T71: 0
M72: O3 Sure LWAC | P72: 0 | S72: 0 | T72: 0
M73: O4 Sure HPC | P73: 0 | S73: 0 | T73: 0
M74: 0 | P74: 0 | S74: 0 | T74: 0
P75: 0 | S75: 0 | T75: 0
P76: 0 | S76: 0 | T76: 0
P77: 0 | S77: 0 | T77: 0
P78: 0 | S78: 0 | T78: 0
P79: 0 | S79: 0 | T79: 0
P80: 0 | S80: 0 | T80: 0
P81: 0 | S81: 0 | T81: 0
P82: 0 | S82: 0 | T82: 0
P83: 0 | S83: 0 | T83: 0
P84: 0 | S84: 0 | T84: 0
P85: 0 | S85: 0 | T85: 0
P86: 0 | S86: 0 | T86: 0
... P1019: 0 | S1019: 0 | T1019: 0
T1020: 0
T1021: 0
T1022: 0
T1023: 0
T1024: 0
T1025: 0
T1026: 0
T1027: 0
T1028: 0

Sheet freight
A1: Number of containers | B1: Price per kilometer per container (€)
A2: 1 | B2: 1.5
A3: 2 | B3: 1.3995
A4: 3 | B4: 1.3439
A5: 5 | B5: 1.277
A6: 8 | B6: 1.2157
A7: 13 | B7: 1.1465
A8: 21 | B8: 1.0883
A9: 34 | B9: 1.0371
A10: 55 | B10: 0.9967
A11: 89 | B11: 0.9547
A12: 144 | B12: 0.9186
A13: 233 | B13: 0.8854
... A21: 10946 | B21: 0.7059

Sheet harbors
A1: Water | B1: Nearest Port | C1: Floating Coordinates | D1: Floating Link | E1: Substation Coordinates | F1: Substation Link | G1: Distance (km)
A2: Baltic Sea | B2: Sassnitz, Germany | C2: 54°12'N 14°24'E | D2: https://www.google.com/maps?q=54%C2%B012'N+14%C2%B024'E | E2: 54°29'N 13°36'E | F2: https://www.google.com/maps?q=54%C2%B029'N+13%C2%B036'E | G2: 30
A3: Mediterranean Sea | B3: Valencia, Spain | C3: 39°00'N 00°00'E | D3: https://www.google.com/maps?q=39%C2%B000'N+00%C2%B000'E | E3: 39°40'N -0°14'E | F3: https://www.google.com/maps/place/Port+of+Valencia/@39.4480781,-0.3558521,14z/data=!3m1!4b1!4m6!3m5!1s0xd604835bc0b7b1f:0x6c5c617f0b38e68c!8m2!3d39.4480851!4d-0.3169267!16s%2Fm%2F05c0cd9?entry=ttu&g_ep=EgoyMDI1MDQyMC4wIKXMDSoASAFQAw%3D%3D | G3: 11
A4: North Sea | B4: Esbjerg, Denmark | C4: 56°54'N 05°00'E | D4: https://www.google.com/maps?q=56%C2%B054'N+05%C2%B000'E | E4: 55°29'N 8°26'E | F4: https://www.google.com/maps?q=55%C2%B029'N+8%C2%B026'E | G4: 170

Sheet aggregates
A1: Category | B1: Parameter | C1: Value | D1: Unit
A2: Power Demand | B2: Platform continuous load | C2: 10 | D2: MW
B3: Hours per year | C3: 8760 | D3: h
B4: Annual electricity need | C4: 87600 | D4: MWh/year
A5: Diesel Generator | B5: Electrical efficiency | C5: 0.4 | D5: –
B6: Required diesel energy input | C6: 219000 | D6: MWh/year
B7: Diesel energy content | C7: 10 | D7: kWh/litre
B8: Annual diesel volume | C8: 2190000 | D8: litres/year
A9: Fuel Cost | B9: Offshore diesel price (incl. delivery) | C9: 1.3 | D9: €/litre
B10: Annual diesel cost | C10: 28470000 | D10: €/year
A11: Operations & Logistics | B11: Generator maintenance and service | C11: 1500000 | D11: €/year
B12: Fuel delivery and handling | C12: 2000000 | D12: €/year
B13: Total O&M + logistics | C13: 3500000 | D13: €/year
A14: Total Annual Cost | B14: Total diesel + O&M | C14: 31970000 | D14: €/year
A15: Cost of Electricity | B15: Cost per unit of electricity | C15: 0.365 | D15: €/kWh

Sheet sens_discounts
A1: Parameter | B1: Discount rate | C1: n_10 | D1: b_10 | E1: m_10
A2: CAPEX (€) | B2: 2 | C2: 13420633 | D2: 9749886.9 | E2: 9491668.4
A3: OPEX (€) | B3: 2 | C3: 4910200.8 | D3: 3928160.6 | E3: 2455100.4
A4: Revenue (€) | B4: 2 | C4: 35290119 | D4: 37867706 | E4: 54374045
A5: LCOE (€) | B5: 2 | C5: 0.062331896 | D5: 0.043344736 | E5: 0.026365746
A6: NPV (€) | B6: 2 | C6: 12137414 | D6: 20258428 | E6: 38637389
A7: ROI (%) | B7: 2 | C7: 0.90438461 | D7: 2.0778116 | E7: 4.0706636
A8: Payback (y) | B8: 2 | C8: 16 | D8: 10 | E8: 6
A9: IRR (%) | B9: 2 | C9: 0.03768276 | D9: 0.094748975 | E9: 0.18555681
A10: CAPEX (€) | B10: 3 | C10: 13420633 | D10: 9749886.9 | E10: 9491668.4
A11: OPEX (€) | B11: 3 | C11: 4017456.4 | D11: 3213965.1 | E11: 2008728.2
A12: Revenue (€) | B12: 3 | C12: 28953702 | D12: 31024442 | E12: 44517538
A13: LCOE (€) | B13: 3 | C13: 0.072272994 | D13: 0.050143118 | E13: 0.031000088
... A39: ROI (%) | B39: 6 | C39: 0.022141157 | D39: 0.61068041 | E39: 1.6016367
A40: Payback (y) | B40: 6 | C40: - | D40: 13 | E40: 7
A41: IRR (%) | B41: 6 | C41: -0.0046716385 | D41: 0.050065343 | E41: 0.13716673
A42: CAPEX (€) | B42: 7 | C42: 13420633 | D42: 9749886.9 | E42: 9491668.4
A43: OPEX (€) | B43: 7 | C43: 2142899.5 | D43: 1714319.6 | E43: 1071449.8
A44: Revenue (€) | B44: 7 | C44: 15607781 | D44: 16633838 | E44: 23806051
A45: LCOE (€) | B45: 7 | C45: 0.11965979 | D45: 0.082705192 | E45: 0.053245881
A46: NPV (€) | B46: 7 | C46: -1191397.7 | D46: 4162219.6 | E46: 12271742
A47: ROI (%) | B47: 7 | C47: -0.08877359 | D47: 0.42689927 | E47: 1.2928962
A48: Payback (y) | B48: 7 | C48: - | D48: 14 | E48: 8
A49: IRR (%) | B49: 7 | C49: -0.015260238 | D49: 0.038894435 | E49: 0.12506922
A50: CAPEX (€) | B50: 8 | C50: 13420633 | D50: 9749886.9 | E50: 9491668.4
A51: OPEX (€) | B51: 8 | C51: 1898234.2 | D51: 1518587.4 | E51: 949117.12
A52: Revenue (€) | B52: 8 | C52: 13859636 | D52: 14752333 | E52: 21100502
A53: LCOE (€) | B53: 8 | C53: 0.13263437 | D53: 0.091661226 | E53: 0.059377462
A54: NPV (€) | B54: 8 | C54: -2392101.1 | D54: 2723297.6 | E54: 9926500.9
A55: ROI (%) | B55: 8 | C55: -0.17824056 | D55: 0.27931581 | E55: 1.045812
A56: Payback (y) | B56: 8 | C56: - | D56: 15 | E56: 8
A57: IRR (%) | B57: 8 | C57: -0.025848838 | D57: 0.027723527 | E57: 0.1129717
A58: CAPEX (€) | B58: 9 | C58: 13420633 | D58: 9749886.9 | E58: 9491668.4
A59: OPEX (€) | B59: 9 | C59: 1700309.1 | D59: 1360247.3 | E59: 850154.57
A60: Revenue (€) | B60: 9 | C60: 12443690 | D60: 13229346 | E60: 18911163
A61: LCOE (€) | B61: 9 | C61: 0.14581792 | D61: 0.10077717 | E61: 0.065623608
A62: NPV (€) | B62: 9 | C62: -3379376.1 | D62: 1546776.5 | E62: 8017485.9
A63: ROI (%) | B63: 9 | C63: -0.25180453 | D63: 0.15864558 | E63: 0.84468668
A64: Payback (y) | B64: 9 | C64: - | D64: 18 | E64: 8
A65: IRR (%) | B65: 9 | C65: -0.036437437 | D65: 0.016552619 | E65: 0.10087418
A66: CAPEX (€) | B66: 10 | C66: 13420633 | D66: 9749886.9 | E66: 9491668.4
A67: OPEX (€) | B67: 10 | C67: 1537823.6 | D67: 1230258.9 | E67: 768911.82
A68: Revenue (€) | B68: 10 | C68: 11279775 | D68: 11978276 | E68: 17113283
A69: LCOE (€) | B69: 10 | C69: 0.15913568 | D69: 0.11000059 | E69: 0.071948182
A70: NPV (€) | B70: 10 | C70: -4205477.4 | D70: 568637.87 | E70: 6438652.4
A71: ROI (%) | B71: 10 | C71: -0.3133591 | D71: 0.05832251 | E71: 0.67834781
A72: Payback (y) | B72: 10 | C72: - | D72: 22 | E72: 9
A73: IRR (%) | B73: 10 | C73: -0.047026037 | D73: 0.0053817115 | E73: 0.088776661

Sheet sens_subsea_cable
A1: Parameter | B1: Subsea cable | C1: n_10 | D1: b_10 | E1: m_10
A2: CAPEX (€) | B2: Yes | C2: 47392133 | D2: 15721387 | E2: 11663168
A3: OPEX (€) | B3: Yes | C3: 1794221.3 | D3: 1435377.1 | E3: 897110.66
A4: Revenue (€) | B4: Yes | C4: 13115756 | D4: 13952094 | E4: 19950051
A5: LCOE (€) | B5: Yes | C5: 0.45002077 | D5: 0.14756291 | E5: 0.075550359
A6: NPV (€) | B6: Yes | C6: -36880227 | D6: -3864753.2 | E6: 6753420.5
A7: ROI (%) | B7: Yes | C7: -0.77819303 | D7: -0.24582775 | E7: 0.57903824
A8: Payback (y) | B8: Yes | C8: - | D8: - | E8: 11
A9: IRR (%) | B9: Yes | C9: -0.13105754 | D9: -0.037266573 | E9: 0.062394022
A10: CAPEX (€) | B10: No | C10: 13420633 | D10: 9749886.9 | E10: 9491668.4
A11: OPEX (€) | B11: No | C11: 1794221.3 | D11: 1435377.1 | E11: 897110.66
A12: Revenue (€) | B12: No | C12: 13115756 | D12: 13952094 | E12: 19950051
A13: LCOE (€) | B13: No | C13: 0.13920528 | D13: 0.096202881 | E13: 0.062488738
A14: NPV (€) | B14: No | C14: -2908727.4 | D14: 2106746.8 | E14: 8924920.5
A15: ROI (%) | B15: No | C15: -0.21673549 | D15: 0.21607911 | E15: 0.94028996
A16: Payback (y) | B16: No | C16: - | D16: 16 | E16: 8
A17: IRR (%) | B17: No | C17: -0.031143137 | D17: 0.022138073 | E17: 0.10692294

Sheet sens_pontoons
A1: Parameter | B1: Pontoon Design | C1: n_10 | D1: b_10 | E1: m_10
A2: CAPEX (€) | B2: Conventional | C2: 13420633 | D2: 9749886.9 | E2: 9491668.4
A3: OPEX (€) | B3: Conventional | C3: 1794221.3 | D3: 1435377.1 | E3: 897110.66
A4: Revenue (€) | B4: Conventional | C4: 13115756 | D4: 13952094 | E4: 19950051
A5: LCOE (€) | B5: Conventional | C5: 0.13920528 | D5: 0.096202881 | E5: 0.062488738
A6: NPV (€) | B6: Conventional | C6: -2908727.4 | D6: 2106746.8 | E6: 8924920.5
A7: ROI (%) | B7: Conventional | C7: -0.21673549 | D7: 0.21607911 | E7: 0.94028996
A8: Payback (y) | B8: Conventional | C8: - | D8: 16 | E8: 8
A9: IRR (%) | B9: Conventional | C9: -0.031143137 | D9: 0.022138073 | E9: 0.10692294
A10: CAPEX (€) | B10: Hybrid | C10: 13521895 | D10: 9851148.9 | E10: 9592930.4
A11: OPEX (€) | B11: Hybrid | C11: 1794221.3 | D11: 1435377.1 | E11: 897110.66
A12: Revenue (€) | B12: Hybrid | C12: 13115756 | D12: 13952094 | E12: 19950051
A13: LCOE (€) | B13: Hybrid | C13: 0.14013176 | D13: 0.097073821 | E13: 0.063097831
A14: NPV (€) | B14: Hybrid | C14: -3009989.4 | D14: 2005484.8 | E14: 8823658.5
A15: ROI (%) | B15: Hybrid | C15: -0.22260116 | D15: 0.20357878 | E15: 0.91980846
A16: Payback (y) | B16: Hybrid | C16: - | D16: 17 | E16: 8
A17: IRR (%) | B17: Hybrid | C17: -0.031961486 | D17: 0.020586118 | E17: 0.104344
A18: CAPEX (€) | B18: LWAC | C18: 13702695 | D18: 10031949 | E18: 9773730.4
A19: OPEX (€) | B19: LWAC | C19: 1794221.3 | D19: 1435377.1 | E19: 897110.66
A20: Revenue (€) | B20: LWAC | C20: 13115756 | D20: 13952094 | E20: 19950051
A21: LCOE (€) | B21: LWAC | C21: 0.14178595 | D21: 0.098628856 | E21: 0.064185347
A22: NPV (€) | B22: LWAC | C22: -3190789.4 | D22: 1824684.8 | E22: 8642858.5
A23: ROI (%) | B23: LWAC | C23: -0.23285854 | D23: 0.18188737 | E23: 0.88429476
A24: Payback (y) | B24: LWAC | C24: - | D24: 18 | E24: 8
A25: IRR (%) | B25: LWAC | C25: -0.033397101 | D25: 0.01789036 | E25: 0.099890372
A26: CAPEX (€) | B26: HPC | C26: 14744387 | D26: 11073641 | E26: 10815423
A27: OPEX (€) | B27: HPC | C27: 1794221.3 | D27: 1435377.1 | E27: 897110.66
A28: Revenue (€) | B28: HPC | C28: 13115756 | D28: 13952094 | E28: 19950051
A29: LCOE (€) | B29: HPC | C29: 0.15131671 | D29: 0.10758831 | E29: 0.070451151
A30: NPV (€) | B30: HPC | C30: -4232481.9 | D30: 782992.34 | E30: 7601166
A31: ROI (%) | B31: HPC | C31: -0.28705716 | D31: 0.070707757 | E31: 0.70280803
A32: Payback (y) | B32: HPC | C32: - | D32: 23 | E32: 10
A33: IRR (%) | B33: HPC | C33: -0.041088089 | D33: 0.0039938878 | E33: 0.077450275
